Workbook

Sheet FK Map
A1: S.No. | B1: Table | C1: Column | D1: Reference Table | E1: Reference Column | F1: Cardinality
A2: 1 | B2: Sales_SKU | C2: SKU Code | D2: Material Master | E2: SKU Code | F2: One to one
A3: 2 | B3: Sales_SKU | C3: plant | D3: Plants | E3: plant_code | F3: Many to one
A4: 3 | B4: Sales_SKU | C4: market_eligibility | D4: Regions | E4: region_id | F4: Many to one
A5: 4 | B5: Purchase_SKU | C5: SKU code | D5: Material Master | E5: SKU Code | F5: One to one
A6: 5 | B6: BOM_Line Item | C6: FG SKU Code | D6: Sales_SKU | E6: SKU Code | F6: Many to one
A7: 6 | B7: BOM_Line Item | C7: RM ID | D7: Purchase_SKU | E7: rm_id | F7: Many to one
A8: 7 | B8: BOM_Line Item | C8: RM SKU Code | D8: Material Master | E8: SKU Code | F8: Many to one
A9: 8 | B9: Countries | C9: region_id | D9: Regions | E9: region_id | F9: Many to one
A10: 9 | B10: Customers | C10: country_iso | D10: Countries | E10: iso_code | F10: Many to one
A11: 10 | B11: Customers | C11: customer_region_id | D11: Regions | E11: region_id | F11: Many to one
A12: 11 | B12: SLA Profiles | C12: scope_region_id | D12: Regions | E12: region_id | F12: Many to one
A13: 12 | B13: Orders | C13: Customer ID | D13: Customers | E13: customer_id | F13: Many to one
... A69: 68 | B69: Lessons | C69: Review ID | D69: Review Events | E69: Review Event ID | F69: Many to one

Sheet Material Master
A1: SKU Code (Primary Key) | B1: cas_number | C1: hazard_class | D1: shelf_life_months
A2: ESS-ACETYL-ETHACE-LM-98.5-NEAT-BULK-DST | B2: 141-78-6 | C2: Flam. Liq. 2 | D2: 24
A3: ESS-ACETYL-ETHACE-LM-98.5-NEAT-BULK-DST | B3: 141-78-6 | C3: Flam. Liq. 2 | D3: 24
A4: ESS-ACETYL-ETHACE-LM-98.5-NEAT-BULK-DST | B4: 141-78-6 | C4: Flam. Liq. 2 | D4: 24
A5: SPI-ACETYL-ACEANH-PH-98.6-NEAT-DR200_UN-MHD | B5: 108-24-7 | C5: Skin Corr. 1B | D5: 24
A6: SPI-ACETYL-ACEANH-PH-98.6-NEAT-DR200_UN-MHD | B6: 108-24-7 | C6: Skin Corr. 1B | D6: 24
A7: SPI-ACETYL-ACEANH-PH-98.6-NEAT-DR200_UN-MHD | B7: 108-24-7 | C7: Skin Corr. 1B | D7: 24
A8: SPI-ACETYL-ACE-IND-98.4-NEAT-ISO20-LTE | B8: 75-07-0 | C8: Flam. Liq. 2; Acute Tox. 3 | D8: 12
A9: SPI-ACETYL-ACE-IND-98.4-NEAT-ISO20-LTE | B9: 75-07-0 | C9: Flam. Liq. 2; Acute Tox. 3 | D9: 12
A10: SPI-ACETYL-ACE-IND-98.4-NEAT-ISO20-LTE | B10: 75-07-0 | C10: Flam. Liq. 2; Acute Tox. 3 | D10: 12
A11: ESS-ACETYL-BUTACE-TECH-98.3-NEAT-DR200-DHJ | B11: 123-86-4 | C11: Flam. Liq. 3 | D11: 24
A12: ESS-ACETYL-BUTACE-TECH-98.3-NEAT-DR200-DHJ | B12: 123-86-4 | C12: Flam. Liq. 3 | D12: 24
A13: ESS-ACETYL-BUTACE-TECH-98.3-NEAT-DR200-DHJ | B13: 123-86-4 | C13: Flam. Liq. 3 | D13: 24
... A130: RM-DIK-ET-88412 | B130: 674-82-8 | C130: Flam. Liq. 2 | D130: 12
A131: INT-KET-INS-145120 | B131: 463-51-4 | C131: Flam. Gas 1; Acute Tox. 2
A132: INT-DKD-INT-342781 | C132: Flam. Liq. 3 | D132: 12
A133: INT-ARY-INT-558903 | C133: Skin Irrit. 2 | D133: 12
A134: INT-FLR-BLK-903117 | C134: DG (Fluoro) | D134: 12
A135: RM-SUL-AC-10477 | B135: 7664-93-9 | C135: Skin Corr. 1A | D135: 36
A136: RM-HCL-32-65019 | B136: 7647-01-0 | C136: Skin Corr. 1B | D136: 24
A137: RM-NAO-CP-77811 | B137: 1310-73-2 | C137: Skin Corr. 1A | D137: 36
A138: RM-ACN-SV-33120 | B138: 75-05-8 | C138: Flam. Liq. 2 | D138: 36
A139: RM-TOL-SV-90412 | B139: 108-88-3 | C139: Flam. Liq. 2 | D139: 36
A140: RM-MEO-SV-11024 | B140: 67-56-1 | C140: Flam. Liq. 2; Acute Tox. 3 | D140: 36
A141: RM-PDH-CB-61302 | B141: 7440-05-3 | D141: 36
A142: RM-PTC-CAT-27190 | B142: 1643-19-2 | C142: Acute Tox. 4 | D142: 36
A143: PACK-DRM-HD-20001
A144: PACK-IBC-IB-10002
A145: PACK-BAG-PP-25003
A146: PACK-LIN-FX-12004
A147: PACK-SEA-DR-33005
A148: INT-ACE-ANH-772001 | B148: 108-24-7 | C148: Skin Corr. 1B | D148: 12
A149: INT-AAA-EMM-990812 | D149: 12
A150: RM-ETH-AL-64197 | B150: 64-19-7 | C150: Flam. Liq. 2 | D150: 24
A151: RM-ETH-AL-64219 | B151: 64-21-9 | C151: Flam. Liq. 2 | D151: 24
A152: RM-ETH-AL-64241 | B152: 64-24-1 | C152: Flam. Liq. 2 | D152: 24
A153: INT-KET-674828 | B153: 674-82-8 | C153: Flam. Liq. 1; Acute Tox. 2 | D153: 6
A154: INT-KET-463514 | B154: 463-51-4 | C154: Flam. Gas 1; Acute Tox. 2 | D154: 6
A155: PKG-DR200 | B155: N/A | C155: Non-Hazardous | D155: 60
A156: PKG-DR200_UN | B156: N/A | C156: Non-Hazardous (UN Certified) | D156: 60
A157: PKG-IBC1KL | B157: N/A | C157: Non-Hazardous | D157: 60
A158: PKG-HDPE | B158: N/A | C158: Non-Hazardous | D158: 60
A159: PKG-BAG25 | B159: N/A | C159: Non-Hazardous | D159: 36
A160: PKG-FIBC | B160: N/A | C160: Non-Hazardous | D160: 36
A161: PKG-ISO20 | B161: N/A | C161: Non-Hazardous (Asset) | D161: N/A
A162: PKG-ISO-SWAP | B162: N/A | C162: Non-Hazardous (Asset) | D162: N/A
A163: PKG-FLEXI | B163: N/A | C163: Non-Hazardous | D163: 24
A164: PKG-LINER | B164: N/A | C164: Non-Hazardous | D164: 24
A165: PKG-LABELS | B165: N/A | C165: Non-Hazardous | D165: 24
A166: PKG-DG-MARKS | B166: N/A | C166: Non-Hazardous | D166: 24
A167: PKG-PALLET | B167: N/A | C167: Non-Hazardous | D167: 60
A168: PKG-PALLET-POOL | B168: N/A | C168: Non-Hazardous (Pooled Asset) | D168: N/A

Sheet Sales_SKU
A1: FG_Primary Key | B1: SKU Code (FK) | C1: business_unit | D1: Product family | E1: Product Sub-group (molecule_name) | F1: Variant (grade) | G1: Spec 1 (key_specs_assay_pct) | H1: Spec 2 (key_specs_moisture_ppm) | I1: Spec 3 (key_specs_color_apha) | J1: form | K1: packaging | L1: UOM | M1: plant (plant FK) | N1: market_eligibility (regions FK) | O1: regulatory_set_id
A2: FG01 | B2: ESS-ACETYL-ETHACE-LM-98.5-NEAT-BULK-DST | C2: Essentials | D2: ACETYL | E2: Ethyl Acetate | F2: LM | G2: 98.3 | H2: 233 | I2: 17 | J2: =IF(ISNUMBER(SEARCH("-NEAT-",Sales_SKU!$B2)),"Neat",IF(ISNUMBER(SEARCH("-PWD-",Sales_SKU!$B2)),"powder","")) -> Neat | K2: BULK | L2: =IF(J2="Neat","KL",IF(J2="PWD","MT","MT")) -> KL | M2: DST | N2: DOM | O2: REG-IN-ACETYL-LM
A3: FG02 | B3: ESS-ACETYL-ETHACE-LM-98.5-NEAT-BULK-DST | C3: Essentials | D3: ACETYL | E3: Ethyl Acetate | F3: LM | G3: 98.3 | H3: 246 | I3: 19 | J3: =IF(ISNUMBER(SEARCH("-NEAT-",Sales_SKU!$B3)),"Neat",IF(ISNUMBER(SEARCH("-PWD-",Sales_SKU!$B3)),"powder","")) -> Neat | K3: BULK | L3: =IF(J3="Neat","KL",IF(J3="PWD","MT","MT")) -> KL | M3: DST | N3: EU | O3: REG-EU-ACETYL-LM
A4: FG03 | B4: ESS-ACETYL-ETHACE-LM-98.5-NEAT-BULK-DST | C4: Essentials | D4: ACETYL | E4: Ethyl Acetate | F4: LM | G4: 98.3 | H4: 259 | I4: 23 | J4: =IF(ISNUMBER(SEARCH("-NEAT-",Sales_SKU!$B4)),"Neat",IF(ISNUMBER(SEARCH("-PWD-",Sales_SKU!$B4)),"powder","")) -> Neat | K4: BULK | L4: =IF(J4="Neat","KL",IF(J4="PWD","MT","MT")) -> KL | M4: DST | N4: APAC | O4: REG-APAC-ACETYL-LM
A5: FG04 | B5: SPI-ACETYL-ACEANH-PH-98.6-NEAT-DR200_UN-MHD | C5: Specialties | D5: ACETYL | E5: Acetic Anhydride | F5: PH | G5: 98.8 | H5: 139 | I5: 8 | J5: =IF(ISNUMBER(SEARCH("-NEAT-",Sales_SKU!$B5)),"Neat",IF(ISNUMBER(SEARCH("-PWD-",Sales_SKU!$B5)),"powder","")) -> Neat | K5: DR200_UN | L5: =IF(J5="Neat","KL",IF(J5="PWD","MT","MT")) -> KL | M5: MHD | N5: DOM | O5: REG-IN-ACETYL-PH
A6: FG05 | B6: SPI-ACETYL-ACEANH-PH-98.6-NEAT-DR200_UN-MHD | C6: Specialties | D6: ACETYL | E6: Acetic Anhydride | F6: PH | G6: 98.8 | H6: 51 | I6: 8 | J6: =IF(ISNUMBER(SEARCH("-NEAT-",Sales_SKU!$B6)),"Neat",IF(ISNUMBER(SEARCH("-PWD-",Sales_SKU!$B6)),"powder","")) -> Neat | K6: DR200_UN | L6: =IF(J6="Neat","KL",IF(J6="PWD","MT","MT")) -> KL | M6: MHD | N6: EU | O6: REG-EU-ACETYL-PH
A7: FG06 | B7: SPI-ACETYL-ACEANH-PH-98.6-NEAT-DR200_UN-MHD | C7: Specialties | D7: ACETYL | E7: Acetic Anhydride | F7: PH | G7: 98.8 | H7: 64 | I7: 9 | J7: =IF(ISNUMBER(SEARCH("-NEAT-",Sales_SKU!$B7)),"Neat",IF(ISNUMBER(SEARCH("-PWD-",Sales_SKU!$B7)),"powder","")) -> Neat | K7: DR200_UN | L7: =IF(J7="Neat","KL",IF(J7="PWD","MT","MT")) -> KL | M7: MHD | N7: APAC | O7: REG-APAC-ACETYL-PH
A8: FG07 | B8: SPI-ACETYL-ACE-IND-98.4-NEAT-ISO20-LTE | C8: Specialties | D8: ACETYL | E8: Acetaldehyde | F8: IND | G8: 98.4 | H8: 345 | I8: 22 | J8: =IF(ISNUMBER(SEARCH("-NEAT-",Sales_SKU!$B8)),"Neat",IF(ISNUMBER(SEARCH("-PWD-",Sales_SKU!$B8)),"powder","")) -> Neat | K8: ISO20 | L8: =IF(J8="Neat","KL",IF(J8="PWD","MT","MT")) -> KL | M8: LTE | N8: DOM | O8: REG-IN-ACETYL-IND
A9: FG08 | B9: SPI-ACETYL-ACE-IND-98.4-NEAT-ISO20-LTE | C9: Specialties | D9: ACETYL | E9: Acetaldehyde | F9: IND | G9: 98.4 | H9: 358 | I9: 21 | J9: =IF(ISNUMBER(SEARCH("-NEAT-",Sales_SKU!$B9)),"Neat",IF(ISNUMBER(SEARCH("-PWD-",Sales_SKU!$B9)),"powder","")) -> Neat | K9: ISO20 | L9: =IF(J9="Neat","KL",IF(J9="PWD","MT","MT")) -> KL | M9: LTE | N9: EU | O9: REG-EU-ACETYL-IND
A10: FG09 | B10: SPI-ACETYL-ACE-IND-98.4-NEAT-ISO20-LTE | C10: Specialties | D10: ACETYL | E10: Acetaldehyde | F10: IND | G10: 98.4 | H10: 371 | I10: 17 | J10: =IF(ISNUMBER(SEARCH("-NEAT-",Sales_SKU!$B10)),"Neat",IF(ISNUMBER(SEARCH("-PWD-",Sales_SKU!$B10)),"powder","")) -> Neat | K10: ISO20 | L10: =IF(J10="Neat","KL",IF(J10="PWD","MT","MT")) -> KL | M10: LTE | N10: APAC | O10: REG-APAC-ACETYL-IND
A11: FG10 | B11: ESS-ACETYL-BUTACE-TECH-98.3-NEAT-DR200-DHJ | C11: Essentials | D11: ACETYL | E11: Butyl Acetate | F11: TECH | G11: 98.2 | H11: 200 | I11: 14 | J11: =IF(ISNUMBER(SEARCH("-NEAT-",Sales_SKU!$B11)),"Neat",IF(ISNUMBER(SEARCH("-PWD-",Sales_SKU!$B11)),"powder","")) -> Neat | K11: DR200 | L11: =IF(J11="Neat","KL",IF(J11="PWD","MT","MT")) -> KL | M11: DHJ | N11: DOM | O11: REG-IN-ACETYL-TECH
A12: FG11 | B12: ESS-ACETYL-BUTACE-TECH-98.3-NEAT-DR200-DHJ | C12: Essentials | D12: ACETYL | E12: Butyl Acetate | F12: TECH | G12: 98.2 | H12: 213 | I12: 14 | J12: =IF(ISNUMBER(SEARCH("-NEAT-",Sales_SKU!$B12)),"Neat",IF(ISNUMBER(SEARCH("-PWD-",Sales_SKU!$B12)),"powder","")) -> Neat | K12: DR200 | L12: =IF(J12="Neat","KL",IF(J12="PWD","MT","MT")) -> KL | M12: DHJ | N12: EU | O12: REG-EU-ACETYL-TECH
A13: FG12 | B13: ESS-ACETYL-BUTACE-TECH-98.3-NEAT-DR200-DHJ | C13: Essentials | D13: ACETYL | E13: Butyl Acetate | F13: TECH | G13: 98.2 | H13: 226 | I13: 9 | J13: =IF(ISNUMBER(SEARCH("-NEAT-",Sales_SKU!$B13)),"Neat",IF(ISNUMBER(SEARCH("-PWD-",Sales_SKU!$B13)),"powder","")) -> Neat | K13: DR200 | L13: =IF(J13="Neat","KL",IF(J13="PWD","MT","MT")) -> KL | M13: DHJ | N13: APAC | O13: REG-APAC-ACETYL-TECH
... A121: FG120 | B121: ESS-FLUORO-FLRBLK-LM-98.9-PWD-BAG25-DHJ | C121: Essentials | D121: FLUORO | E121: Fluoro Building Block | F121: LM | G121: 98.7 | H121: 236 | I121: 20 | J121: =IF(ISNUMBER(SEARCH("-NEAT-",Sales_SKU!$B121)),"Neat",IF(ISNUMBER(SEARCH("-PWD-",Sales_SKU!$B121)),"powder","")) -> powder | K121: BAG25 | L121: =IF(J121="Neat","KL",IF(J121="PWD","MT","MT")) -> MT | M121: DHJ | N121: APAC | O121: REG-APAC-FLUORO-LM

Sheet Purchase_SKU
A1: rm_id (Primary Key) | B1: SKU code (FK) | C1: rm_name | D1: rm_category | E1: rm_type | F1: uom | G1: storage_type | H1: storage_temp_c | I1: lead_time_days | J1: criticality | K1: approved_for_families | L1: primary_source_region_id | M1: notes
A2: RM0001 | B2: RM-ETH-AL-64175 | C2: Ethyl Alcohol (Ethanol) | D2: Ethyl Alcohol | E2: RAW_MATERIAL | F2: MT | G2: Tank | H2: Ambient | I2: 7 | J2: A | K2: ACETYL,DKD | L2: DOM | M2: Bulk solvent/feed; excise-controlled; illustrative
A3: RM0002 | B3: RM-AAC-GL-23011 | C3: Acetic Acid (Glacial) | D3: Acetic Acid | E3: RAW_MATERIAL | F3: MT | G3: Tank | H3: Ambient | I3: 10 | J3: A | K3: ACETYL,DKD | L3: DOM | M3: Corrosive; dedicated SS tank; illustrative
A4: RM0003 | B4: RM-BUT-NB-51720 | C4: n-Butanol | D4: Butanol | E4: RAW_MATERIAL | F4: MT | G4: Tank | H4: Ambient | I4: 14 | J4: B | K4: ACETYL | L4: APAC | M4: Flammable; used for butyl acetate; illustrative
A5: RM0004 | B5: RM-ETL-AC-11804 | C5: Ethyl Acetate (Solvent grade) | D5: Ethyl Acetate | E5: RAW_MATERIAL | F5: MT | G5: Tank | H5: Ambient | I5: 12 | J5: B | K5: ACETYL | L5: DOM | M5: Purchased solvent for blends/cleaning; illustrative
A6: RM0005 | B6: RM-MTH-AA-40218 | C6: Methacrylic Acid | D6: Methacrylic Acid | E6: RAW_MATERIAL | F6: KG | G6: Drum/IBC | H6: Ambient | I6: 28 | J6: A | K6: ACETYL | L6: EU | M6: Inhibitor present; check MEHQ ppm; illustrative
A7: RM0006 | B7: RM-ANI-LN-90355 | C7: Aniline | D7: Aniline | E7: RAW_MATERIAL | F7: KG | G7: Drum/IBC | H7: Ambient | I7: 30 | J7: A | K7: ARYLIDE | L7: DOM | M7: Toxic; COA required per batch; illustrative
A8: RM0007 | B8: RM-PCA-AN-77210 | C8: p-Chloroaniline | D8: Chloroaniline | E8: RAW_MATERIAL | F8: KG | G8: Bag | H8: Ambient | I8: 35 | J8: A | K8: ARYLIDE | L8: APAC | M8: Solid; store dry; sieve before charge; illustrative
A9: RM0008 | B9: RM-OAN-AS-55102 | C9: o-Anisidine | D9: Anisidine | E9: RAW_MATERIAL | F9: KG | G9: Drum/IBC | H9: Ambient | I9: 32 | J9: B | K9: ARYLIDE | L9: EU | M9: Light sensitive; nitrogen blanket preferred; illustrative
A10: RM0009 | B10: RM-DIK-ET-88412 | C10: Diketene | D10: Diketene | E10: RAW_MATERIAL | F10: KG | G10: Drum/IBC | H10: 2-8 | I10: 21 | J10: A | K10: DKD,ACETYL | L10: DOM | M10: Refrigerated storage; moisture sensitive; illustrative
A11: RM0010 | B11: INT-KET-INS-145120 | C11: Ketene (in-situ) | D11: Ketene | E11: INTERMEDIATE | F11: KG | G11: On-site Generation | H11: N/A | I11: 0 | J11: A | K11: DKD,ACETYL | L11: DOM | M11: Generated on demand; no inventory; illustrative
A12: RM0011 | B12: INT-DKD-INT-342781 | C12: DKD Intermediate (Crude) | D12: DKD Intermediate | E12: INTERMEDIATE | F12: KG | G12: Drum/IBC | H12: Ambient | I12: 3 | J12: B | K12: DKD | L12: DOM | M12: Internal transfer; QC release required; illustrative
A13: RM0012 | B13: INT-ARY-INT-558903 | C13: Arylide Intermediate (Wet cake) | D13: Arylide Intermediate | E13: INTERMEDIATE | F13: KG | G13: Bag | H13: Ambient | I13: 2 | J13: B | K13: ARYLIDE | L13: DOM | M13: Moist solid; process within 48h; illustrative
... A32: RM0031 | B32: RM-ETH-AL-64241 | C32: Ethyl Alcohol (Denatured) | D32: Ethyl Alcohol | E32: RAW_MATERIAL | F32: MT | G32: Tank | H32: Ambient | I32: 7 | J32: B | K32: ACETYL | L32: DOM | M32: Denatured ethanol for industrial use; non-excise; illustrative
A33: RM0032 | B33: INT-KET-674828 | C33: Diketene (Stabilized) | D33: Diketene | E33: INTERMEDIATE | F33: KG | G33: Drum/IBC | H33: 46061 | I33: 21 | J33: A | K33: DKD,ACETYL | L33: DOM | M33: Refrigerated storage; moisture sensitive; stabilized form; illustrative
A34: RM0033 | B34: INT-KET-463514 | C34: Ketene (Compressed) | D34: Ketene | E34: INTERMEDIATE | F34: KG | G34: On-site Generation | H34: N/A | I34: 0 | J34: A | K34: DKD,ACETYL | L34: DOM | M34: Generated on demand; highly reactive; no inventory hold; illustrative
A35: PKG0001 | B35: PKG-DR200 | C35: Steel Drum 200L (Standard) | D35: Steel Drums | E35: PACKAGING | F35: PCS | G35: Warehouse | H35: Ambient | I35: 10 | J35: B | K35: ACETYL,DKD,ARYLIDE,FLUORO | L35: DOM | M35: Standard 200L steel drums for non-DG products
A36: PKG0002 | B36: PKG-DR200_UN | C36: Steel Drum 200L (UN Certified) | D36: Steel Drums | E36: PACKAGING | F36: PCS | G36: Warehouse | H36: Ambient | I36: 14 | J36: A | K36: ACETYL,DKD,ARYLIDE,FLUORO | L36: DOM | M36: UN-certified drums for DG/hazmat transport; IMDG/ADR compliant
A37: PKG0003 | B37: PKG-IBC1KL | C37: IBC 1000L Composite | D37: IBC Containers | E37: PACKAGING | F37: PCS | G37: Warehouse | H37: Ambient | I37: 14 | J37: A | K37: ACETYL,DKD,ARYLIDE | L37: DOM | M37: 1000L intermediate bulk containers; reusable/reconditionable
A38: PKG0004 | B38: PKG-HDPE | C38: HDPE Container (Various) | D38: HDPE Containers | E38: PACKAGING | F38: PCS | G38: Warehouse | H38: Ambient | I38: 12 | J38: B | K38: ACETYL,DKD | L38: DOM | M38: HDPE containers for corrosive-resistant packaging
A39: PKG0005 | B39: PKG-BAG25 | C39: PP Woven Bag 25kg | D39: Bags | E39: PACKAGING | F39: PCS | G39: Warehouse | H39: Ambient | I39: 7 | J39: B | K39: ARYLIDE,FLUORO | L39: DOM | M39: 25kg woven PP bags for powder products
A40: PKG0006 | B40: PKG-FIBC | C40: FIBC Jumbo Bag 1MT | D40: IBC Containers | E40: PACKAGING | F40: PCS | G40: Warehouse | H40: Ambient | I40: 10 | J40: B | K40: ARYLIDE,FLUORO | L40: DOM | M40: 1MT bulk bags; anti-static option available
A41: PKG0007 | B41: PKG-ISO20 | C41: ISO Tank Container 20ft (Lease) | D41: ISO Tank | E41: PACKAGING | F41: DAYS | G41: Yard | H41: Ambient | I41: 5 | J41: A | K41: ACETYL,DKD | L41: EU | M41: Leased ISO tanks for bulk liquid export; heating coils available
A42: PKG0008 | B42: PKG-ISO-SWAP | C42: ISO Tank Swap Body | D42: ISO Tank | E42: PACKAGING | F42: DAYS | G42: Yard | H42: Ambient | I42: 5 | J42: B | K42: ACETYL,DKD | L42: EU | M42: Swap body tanks for intermodal transport
A43: PKG0009 | B43: PKG-FLEXI | C43: Flexitank 24KL | D43: Flexitank | E43: PACKAGING | F43: PCS | G43: Warehouse | H43: Ambient | I43: 10 | J43: B | K43: ACETYL | L43: DOM | M43: Single-use flexitanks for non-DG bulk liquids; cost-effective
A44: PKG0010 | B44: PKG-LINER | C44: Container Liner | D44: Container Liner | E44: PACKAGING | F44: PCS | G44: Warehouse | H44: Ambient | I44: 7 | J44: C | K44: ACETYL | L44: DOM | M44: Protective liners for container shipments
A45: PKG0011 | B45: PKG-LABELS | C45: Product Labels (DG/GHS) | D45: Labels & Markings | E45: PACKAGING | F45: ROLL | G45: Warehouse | H45: Ambient | I45: 5 | J45: A | K45: ACETYL,DKD,ARYLIDE,FLUORO | L45: DOM | M45: GHS-compliant hazard labels; variable data printing
... A48: PKG0014 | B48: PKG-PALLET-POOL | C48: Pooled Plastic Pallet | D48: Pallets | E48: PACKAGING | F48: TRIP | G48: Yard | H48: Ambient | I48: 3 | J48: C | K48: ACETYL,DKD,ARYLIDE,FLUORO | L48: DOM | M48: Pooled pallets; reduces capital and disposal costs

Sheet BOM_Line Item
A1: BOM Line ID (Primary Key) | B1: FG SKU Code (FK) | C1: Product Family | D1: Molecule | E1: Unit Measure of FG | F1: RM ID (FK) | G1: RM SKU Code (FK) | H1: RM Name | I1: Quantity per Unit FG | J1: UOM | K1: Yield Factor | L1: Scrap Allowance (%) | M1: Effective From | N1: Effective To | O1: Status | P1: Notes
A2: BOM00001 | B2: ESS-ACETYL-ETHACE-LM-98.5-NEAT-BULK-DST | C2: ACETYL | D2: Ethyl Acetate | E2: ="1 "&IFERROR(_xlfn.XLOOKUP(B2,Sales_SKU!$B$2:$B$121,Sales_SKU!$L$2:$L$121,"MT"),"MT") -> 1 KL | F2: RM0001 | G2: RM-ETH-AL-64175 | H2: Ethyl Alcohol (Ethanol) | I2: =IF(RIGHT(E2,2)="KL",0.52*0.9,0.52) -> 0.468 | J2: MT | K2: 0.98 | L2: 0.02 | M2: 46023 | O2: Active | P2: Primary ethanol feed (esterification)
A3: BOM00002 | B3: ESS-ACETYL-ETHACE-LM-98.5-NEAT-BULK-DST | C3: ACETYL | D3: Ethyl Acetate | E3: ="1 "&IFERROR(_xlfn.XLOOKUP(B3,Sales_SKU!$B$2:$B$121,Sales_SKU!$L$2:$L$121,"MT"),"MT") -> 1 KL | F3: RM0002 | G3: RM-AAC-GL-23011 | H3: Acetic Acid (Glacial) | I3: =IF(RIGHT(E3,2)="KL",0.68*0.9,0.68) -> 0.612 | J3: MT | K3: 0.98 | L3: 0.02 | M3: 46023 | O3: Active | P3: Glacial acetic acid for esterification
A4: BOM00003 | B4: ESS-ACETYL-ETHACE-LM-98.5-NEAT-BULK-DST | C4: ACETYL | D4: Ethyl Acetate | E4: ="1 "&IFERROR(_xlfn.XLOOKUP(B4,Sales_SKU!$B$2:$B$121,Sales_SKU!$L$2:$L$121,"MT"),"MT") -> 1 KL | F4: RM0017 | G4: RM-ACN-SV-33120 | H4: Acetonitrile | I4: =IF(RIGHT(E4,2)="KL",0.008*0.9,0.008) -> 0.0072 | J4: KG | K4: 0.98 | L4: 0.02 | M4: 46023 | O4: Active | P4: Sulfuric acid catalyst
A5: BOM00004 | B5: SPI-ACETYL-ACEANH-PH-98.6-NEAT-DR200_UN-MHD | C5: ACETYL | D5: Acetic Anhydride | E5: ="1 "&IFERROR(_xlfn.XLOOKUP(B5,Sales_SKU!$B$2:$B$121,Sales_SKU!$L$2:$L$121,"MT"),"MT") -> 1 KL | F5: RM0002 | G5: RM-AAC-GL-23011 | H5: Acetic Acid (Glacial) | I5: =IF(RIGHT(E5,2)="KL",1.18*0.9,1.18) -> 1.062 | J5: MT | K5: 0.98 | L5: 0.02 | M5: 46023 | O5: Active | P5: Primary acetic acid feed (dehydration)
A6: BOM00005 | B6: SPI-ACETYL-ACEANH-PH-98.6-NEAT-DR200_UN-MHD | C6: ACETYL | D6: Acetic Anhydride | E6: ="1 "&IFERROR(_xlfn.XLOOKUP(B6,Sales_SKU!$B$2:$B$121,Sales_SKU!$L$2:$L$121,"MT"),"MT") -> 1 KL | F6: RM0020 | G6: RM-PDH-CB-61302 | H6: Palladium on Carbon (5%) | I6: =IF(RIGHT(E6,2)="KL",0.003*0.9,0.003) -> 0.0027 | J6: KG | K6: 0.98 | L6: 0.02 | M6: 46023 | O6: Active | P6: Catalyst for dehydration process
A7: BOM00006 | B7: SPI-ACETYL-ACEANH-PH-98.6-NEAT-DR200_UN-MHD | C7: ACETYL | D7: Acetic Anhydride | E7: ="1 "&IFERROR(_xlfn.XLOOKUP(B7,Sales_SKU!$B$2:$B$121,Sales_SKU!$L$2:$L$121,"MT"),"MT") -> 1 KL | F7: RM0036 | G7: PKG-DR200_UN | H7: Steel Drum 200L (UN Certified) | I7: =IF(RIGHT(E7,2)="KL",5*0.9,5) -> 4.5 | J7: PCS | K7: 0.99 | L7: 0.01 | M7: 46023 | O7: Active | P7: UN-certified drums for DG
A8: BOM00007 | B8: SPI-ACETYL-ACEANH-PH-98.6-NEAT-DR200_UN-MHD | C8: ACETYL | D8: Acetic Anhydride | E8: ="1 "&IFERROR(_xlfn.XLOOKUP(B8,Sales_SKU!$B$2:$B$121,Sales_SKU!$L$2:$L$121,"MT"),"MT") -> 1 KL | F8: RM0043 | G8: PKG-LABELS | H8: Product Labels (DG/GHS) | I8: =IF(RIGHT(E8,2)="KL",5*0.9,5) -> 4.5 | J8: SET | K8: 0.99 | L8: 0.01 | M8: 46023 | O8: Active | P8: DG/GHS labels (1 per drum)
A9: BOM00008 | B9: SPI-ACETYL-ACEANH-PH-98.6-NEAT-DR200_UN-MHD | C9: ACETYL | D9: Acetic Anhydride | E9: ="1 "&IFERROR(_xlfn.XLOOKUP(B9,Sales_SKU!$B$2:$B$121,Sales_SKU!$L$2:$L$121,"MT"),"MT") -> 1 KL | F9: RM0044 | G9: PKG-DG-MARKS | H9: DG Placards & Markings | I9: =IF(RIGHT(E9,2)="KL",0.2*0.9,0.2) -> 0.18 | J9: SET | K9: 0.99 | L9: 0.01 | M9: 46023 | O9: Active | P9: DG placards (per pallet)
A10: BOM00009 | B10: SPI-ACETYL-ACEANH-PH-98.6-NEAT-DR200_UN-MHD | C10: ACETYL | D10: Acetic Anhydride | E10: ="1 "&IFERROR(_xlfn.XLOOKUP(B10,Sales_SKU!$B$2:$B$121,Sales_SKU!$L$2:$L$121,"MT"),"MT") -> 1 KL | F10: RM0046 | G10: PKG-PALLET | H10: Wooden Pallet (ISPM-15) | I10: =IF(RIGHT(E10,2)="KL",1.25*0.9,1.25) -> 1.125 | J10: PCS | K10: 0.99 | L10: 0.01 | M10: 46023 | O10: Active | P10: Wooden pallet (4 drums per pallet)
A11: BOM00010 | B11: SPI-ACETYL-ACE-IND-98.4-NEAT-ISO20-LTE | C11: ACETYL | D11: Acetaldehyde | E11: ="1 "&IFERROR(_xlfn.XLOOKUP(B11,Sales_SKU!$B$2:$B$121,Sales_SKU!$L$2:$L$121,"MT"),"MT") -> 1 KL | F11: RM0001 | G11: RM-ETH-AL-64175 | H11: Ethyl Alcohol (Ethanol) | I11: =IF(RIGHT(E11,2)="KL",1.05*0.9,1.05) -> 0.945 | J11: MT | K11: 0.98 | L11: 0.02 | M11: 46023 | O11: Active | P11: Ethanol for catalytic oxidation
A12: BOM00011 | B12: SPI-ACETYL-ACE-IND-98.4-NEAT-ISO20-LTE | C12: ACETYL | D12: Acetaldehyde | E12: ="1 "&IFERROR(_xlfn.XLOOKUP(B12,Sales_SKU!$B$2:$B$121,Sales_SKU!$L$2:$L$121,"MT"),"MT") -> 1 KL | F12: RM0020 | G12: RM-PDH-CB-61302 | H12: Palladium on Carbon (5%) | I12: =IF(RIGHT(E12,2)="KL",0.002*0.9,0.002) -> 0.0018 | J12: KG | K12: 0.98 | L12: 0.02 | M12: 46023 | O12: Active | P12: Oxidation catalyst
A13: BOM00012 | B13: SPI-ACETYL-ACE-IND-98.4-NEAT-ISO20-LTE | C13: ACETYL | D13: Acetaldehyde | E13: ="1 "&IFERROR(_xlfn.XLOOKUP(B13,Sales_SKU!$B$2:$B$121,Sales_SKU!$L$2:$L$121,"MT"),"MT") -> 1 KL | F13: RM0039 | G13: PKG-ISO20 | H13: ISO Tank Container 20ft | I13: =IF(RIGHT(E13,2)="KL",0.05*0.9,0.05) -> 0.045 | J13: TRIP | K13: 0.99 | L13: 0.01 | M13: 46023 | O13: Active | P13: ISO tank (20ft, ~20MT capacity)
A14: BOM00013 | B14: ESS-ACETYL-BUTACE-TECH-98.3-NEAT-DR200-DHJ | C14: ACETYL | D14: Butyl Acetate | E14: ="1 "&IFERROR(_xlfn.XLOOKUP(B14,Sales_SKU!$B$2:$B$121,Sales_SKU!$L$2:$L$121,"MT"),"MT") -> 1 KL | F14: RM0003 | G14: RM-BUT-NB-51720 | H14: n-Butanol | I14: =IF(RIGHT(E14,2)="KL",0.64*0.9,0.64) -> 0.576 | J14: MT | K14: 0.98 | L14: 0.02 | M14: 46023 | O14: Active | P14: n-Butanol primary alcohol
A15: BOM00014 | B15: ESS-ACETYL-BUTACE-TECH-98.3-NEAT-DR200-DHJ | C15: ACETYL | D15: Butyl Acetate | E15: ="1 "&IFERROR(_xlfn.XLOOKUP(B15,Sales_SKU!$B$2:$B$121,Sales_SKU!$L$2:$L$121,"MT"),"MT") -> 1 KL | F15: RM0002 | G15: RM-AAC-GL-23011 | H15: Acetic Acid (Glacial) | I15: =IF(RIGHT(E15,2)="KL",0.52*0.9,0.52) -> 0.468 | J15: MT | K15: 0.98 | L15: 0.02 | M15: 46023 | O15: Active | P15: Acetic acid for esterification
A16: BOM00015 | B16: ESS-ACETYL-BUTACE-TECH-98.3-NEAT-DR200-DHJ | C16: ACETYL | D16: Butyl Acetate | E16: ="1 "&IFERROR(_xlfn.XLOOKUP(B16,Sales_SKU!$B$2:$B$121,Sales_SKU!$L$2:$L$121,"MT"),"MT") -> 1 KL | F16: RM0017 | G16: RM-ACN-SV-33120 | H16: Acetonitrile | I16: =IF(RIGHT(E16,2)="KL",0.012*0.9,0.012) -> 0.0108 | J16: KG | K16: 0.98 | L16: 0.02 | M16: 46023 | O16: Active | P16: Sulfuric acid catalyst
A17: BOM00016 | B17: ESS-ACETYL-BUTACE-TECH-98.3-NEAT-DR200-DHJ | C17: ACETYL | D17: Butyl Acetate | E17: ="1 "&IFERROR(_xlfn.XLOOKUP(B17,Sales_SKU!$B$2:$B$121,Sales_SKU!$L$2:$L$121,"MT"),"MT") -> 1 KL | F17: RM0035 | G17: PKG-DR200 | H17: Steel Drum 200L (Standard) | I17: =IF(RIGHT(E17,2)="KL",5*0.9,5) -> 4.5 | J17: PCS | K17: 0.99 | L17: 0.01 | M17: 46023 | O17: Active | P17: 200L drums (5 per MT)
A18: BOM00017 | B18: ESS-ACETYL-BUTACE-TECH-98.3-NEAT-DR200-DHJ | C18: ACETYL | D18: Butyl Acetate | E18: ="1 "&IFERROR(_xlfn.XLOOKUP(B18,Sales_SKU!$B$2:$B$121,Sales_SKU!$L$2:$L$121,"MT"),"MT") -> 1 KL | F18: RM0046 | G18: PKG-PALLET | H18: Wooden Pallet (ISPM-15) | I18: =IF(RIGHT(E18,2)="KL",1.25*0.9,1.25) -> 1.125 | J18: PCS | K18: 0.99 | L18: 0.01 | M18: 46023 | O18: Active | P18: Wooden pallet (4 drums per pallet)
A19: BOM00018 | B19: ESS-ACETYL-MAA-LM-98.4-NEAT-IBC1KL-DST | C19: ACETYL | D19: Methyl Acetoacetate | E19: ="1 "&IFERROR(_xlfn.XLOOKUP(B19,Sales_SKU!$B$2:$B$121,Sales_SKU!$L$2:$L$121,"MT"),"MT") -> 1 KL | F19: RM0009 | G19: RM-DIK-ET-88412 | H19: Diketene | I19: =IF(RIGHT(E19,2)="KL",0.85*0.9,0.85) -> 0.765 | J19: KG | K19: 0.98 | L19: 0.02 | M19: 46023 | O19: Active | P19: Diketene for acetoacetylation
A20: BOM00019 | B20: ESS-ACETYL-MAA-LM-98.4-NEAT-IBC1KL-DST | C20: ACETYL | D20: Methyl Acetoacetate | E20: ="1 "&IFERROR(_xlfn.XLOOKUP(B20,Sales_SKU!$B$2:$B$121,Sales_SKU!$L$2:$L$121,"MT"),"MT") -> 1 KL | F20: RM0001 | G20: RM-ETH-AL-64175 | H20: Ethyl Alcohol (Ethanol) | I20: =IF(RIGHT(E20,2)="KL",0.38*0.9,0.38) -> 0.342 | J20: MT | K20: 0.98 | L20: 0.02 | M20: 46023 | O20: Active | P20: Alcohol for ester formation
A21: BOM00020 | B21: ESS-ACETYL-MAA-LM-98.4-NEAT-IBC1KL-DST | C21: ACETYL | D21: Methyl Acetoacetate | E21: ="1 "&IFERROR(_xlfn.XLOOKUP(B21,Sales_SKU!$B$2:$B$121,Sales_SKU!$L$2:$L$121,"MT"),"MT") -> 1 KL | F21: RM0020 | G21: RM-PDH-CB-61302 | H21: Palladium on Carbon (5%) | I21: =IF(RIGHT(E21,2)="KL",0.002*0.9,0.002) -> 0.0018 | J21: KG | K21: 0.98 | L21: 0.02 | M21: 46023 | O21: Active | P21: Process catalyst
A22: BOM00021 | B22: ESS-ACETYL-MAA-LM-98.4-NEAT-IBC1KL-DST | C22: ACETYL | D22: Methyl Acetoacetate | E22: ="1 "&IFERROR(_xlfn.XLOOKUP(B22,Sales_SKU!$B$2:$B$121,Sales_SKU!$L$2:$L$121,"MT"),"MT") -> 1 KL | F22: RM0037 | G22: PKG-IBC1KL | H22: IBC 1000L Composite | I22: =IF(RIGHT(E22,2)="KL",1*0.9,1) -> 0.9 | J22: PCS | K22: 0.99 | L22: 0.01 | M22: 46023 | O22: Active | P22: 1000L IBC (~1 MT capacity)
A23: BOM00022 | B23: SPI-ACETYL-EAA-IND-99.2-NEAT-DR200-MHD | C23: ACETYL | D23: Ethyl Acetoacetate | E23: ="1 "&IFERROR(_xlfn.XLOOKUP(B23,Sales_SKU!$B$2:$B$121,Sales_SKU!$L$2:$L$121,"MT"),"MT") -> 1 KL | F23: RM0009 | G23: RM-DIK-ET-88412 | H23: Diketene | I23: =IF(RIGHT(E23,2)="KL",0.65*0.9,0.65) -> 0.585 | J23: KG | K23: 0.98 | L23: 0.02 | M23: 46023 | O23: Active | P23: Diketene derivative source
A24: BOM00023 | B24: SPI-ACETYL-EAA-IND-99.2-NEAT-DR200-MHD | C24: ACETYL | D24: Ethyl Acetoacetate | E24: ="1 "&IFERROR(_xlfn.XLOOKUP(B24,Sales_SKU!$B$2:$B$121,Sales_SKU!$L$2:$L$121,"MT"),"MT") -> 1 KL | F24: RM0001 | G24: RM-ETH-AL-64175 | H24: Ethyl Alcohol (Ethanol) | I24: =IF(RIGHT(E24,2)="KL",0.36*0.9,0.36) -> 0.324 | J24: MT | K24: 0.98 | L24: 0.02 | M24: 46023 | O24: Active | P24: Ethanol for esterification
A25: BOM00024 | B25: SPI-ACETYL-EAA-IND-99.2-NEAT-DR200-MHD | C25: ACETYL | D25: Ethyl Acetoacetate | E25: ="1 "&IFERROR(_xlfn.XLOOKUP(B25,Sales_SKU!$B$2:$B$121,Sales_SKU!$L$2:$L$121,"MT"),"MT") -> 1 KL | F25: RM0020 | G25: RM-PDH-CB-61302 | H25: Palladium on Carbon (5%) | I25: =IF(RIGHT(E25,2)="KL",0.002*0.9,0.002) -> 0.0018 | J25: KG | K25: 0.98 | L25: 0.02 | M25: 46023 | O25: Active | P25: Catalyst
A26: BOM00025 | B26: SPI-ACETYL-EAA-IND-99.2-NEAT-DR200-MHD | C26: ACETYL | D26: Ethyl Acetoacetate | E26: ="1 "&IFERROR(_xlfn.XLOOKUP(B26,Sales_SKU!$B$2:$B$121,Sales_SKU!$L$2:$L$121,"MT"),"MT") -> 1 KL | F26: RM0035 | G26: PKG-DR200 | H26: Steel Drum 200L (Standard) | I26: =IF(RIGHT(E26,2)="KL",5*0.9,5) -> 4.5 | J26: PCS | K26: 0.99 | L26: 0.01 | M26: 46023 | O26: Active | P26: 200L drums (5 per MT)
A27: BOM00026 | B27: SPI-ACETYL-EAA-IND-99.2-NEAT-DR200-MHD | C27: ACETYL | D27: Ethyl Acetoacetate | E27: ="1 "&IFERROR(_xlfn.XLOOKUP(B27,Sales_SKU!$B$2:$B$121,Sales_SKU!$L$2:$L$121,"MT"),"MT") -> 1 KL | F27: RM0046 | G27: PKG-PALLET | H27: Wooden Pallet (ISPM-15) | I27: =IF(RIGHT(E27,2)="KL",1.25*0.9,1.25) -> 1.125 | J27: PCS | K27: 0.99 | L27: 0.01 | M27: 46023 | O27: Active | P27: Wooden pallet (4 drums per pallet)
A28: BOM00027 | B28: ESS-ACETYL-AAEM-TECH-98.8-NEAT-BULK-LTE | C28: ACETYL | D28: AAEM (Acetoacetoxyethyl Methacrylate) | E28: ="1 "&IFERROR(_xlfn.XLOOKUP(B28,Sales_SKU!$B$2:$B$121,Sales_SKU!$L$2:$L$121,"MT"),"MT") -> 1 KL | F28: RM0005 | G28: RM-MTH-AA-40218 | H28: Methacrylic Acid | I28: =IF(RIGHT(E28,2)="KL",0.67*0.9,0.67) -> 0.603 | J28: KG | K28: 0.98 | L28: 0.02 | M28: 46023 | O28: Active | P28: Methacrylic acid for acrylate synthesis
A29: BOM00028 | B29: ESS-ACETYL-AAEM-TECH-98.8-NEAT-BULK-LTE | C29: ACETYL | D29: AAEM (Acetoacetoxyethyl Methacrylate) | E29: ="1 "&IFERROR(_xlfn.XLOOKUP(B29,Sales_SKU!$B$2:$B$121,Sales_SKU!$L$2:$L$121,"MT"),"MT") -> 1 KL | F29: RM0009 | G29: RM-DIK-ET-88412 | H29: Diketene | I29: =IF(RIGHT(E29,2)="KL",0.55*0.9,0.55) -> 0.495 | J29: KG | K29: 0.98 | L29: 0.02 | M29: 46023 | O29: Active | P29: Diketene for acetoacetyl group
A30: BOM00029 | B30: ESS-ACETYL-AAEM-TECH-98.8-NEAT-BULK-LTE | C30: ACETYL | D30: AAEM (Acetoacetoxyethyl Methacrylate) | E30: ="1 "&IFERROR(_xlfn.XLOOKUP(B30,Sales_SKU!$B$2:$B$121,Sales_SKU!$L$2:$L$121,"MT"),"MT") -> 1 KL | F30: RM0001 | G30: RM-ETH-AL-64175 | H30: Ethyl Alcohol (Ethanol) | I30: =IF(RIGHT(E30,2)="KL",0.22*0.9,0.22) -> 0.198 | J30: MT | K30: 0.98 | L30: 0.02 | M30: 46023 | O30: Active | P30: Ethanol solvent/reactant
A31: BOM00030 | B31: ESS-ACETYL-AAEM-TECH-98.8-NEAT-BULK-LTE | C31: ACETYL | D31: AAEM (Acetoacetoxyethyl Methacrylate) | E31: ="1 "&IFERROR(_xlfn.XLOOKUP(B31,Sales_SKU!$B$2:$B$121,Sales_SKU!$L$2:$L$121,"MT"),"MT") -> 1 KL | F31: RM0020 | G31: RM-PDH-CB-61302 | H31: Palladium on Carbon (5%) | I31: =IF(RIGHT(E31,2)="KL",0.003*0.9,0.003) -> 0.0027 | J31: KG | K31: 0.98 | L31: 0.02 | M31: 46023 | O31: Active | P31: Process catalyst
A32: BOM00031 | B32: ESS-DKD-DKDINT-INK-99.6-NEAT-DR200-DHJ | C32: DKD | D32: DKD Intermediate | E32: ="1 "&IFERROR(_xlfn.XLOOKUP(B32,Sales_SKU!$B$2:$B$121,Sales_SKU!$L$2:$L$121,"MT"),"MT") -> 1 KL | F32: RM0009 | G32: RM-DIK-ET-88412 | H32: Diketene | I32: =IF(RIGHT(E32,2)="KL",0.92*0.9,0.92) -> 0.828 | J32: KG | K32: 0.98 | L32: 0.02 | M32: 46023 | O32: Active | P32: Primary diketene feed
A33: BOM00032 | B33: ESS-DKD-DKDINT-INK-99.6-NEAT-DR200-DHJ | C33: DKD | D33: DKD Intermediate | E33: ="1 "&IFERROR(_xlfn.XLOOKUP(B33,Sales_SKU!$B$2:$B$121,Sales_SKU!$L$2:$L$121,"MT"),"MT") -> 1 KL | F33: RM0001 | G33: RM-ETH-AL-64175 | H33: Ethyl Alcohol (Ethanol) | I33: =IF(RIGHT(E33,2)="KL",0.28*0.9,0.28) -> 0.252 | J33: MT | K33: 0.98 | L33: 0.02 | M33: 46023 | O33: Active | P33: Ethanol process solvent
A34: BOM00033 | B34: ESS-DKD-DKDINT-INK-99.6-NEAT-DR200-DHJ | C34: DKD | D34: DKD Intermediate | E34: ="1 "&IFERROR(_xlfn.XLOOKUP(B34,Sales_SKU!$B$2:$B$121,Sales_SKU!$L$2:$L$121,"MT"),"MT") -> 1 KL | F34: RM0002 | G34: RM-AAC-GL-23011 | H34: Acetic Acid (Glacial) | I34: =IF(RIGHT(E34,2)="KL",0.15*0.9,0.15) -> 0.135 | J34: MT | K34: 0.98 | L34: 0.02 | M34: 46023 | O34: Active | P34: Acetic acid for process
A35: BOM00034 | B35: ESS-DKD-DKDINT-INK-99.6-NEAT-DR200-DHJ | C35: DKD | D35: DKD Intermediate | E35: ="1 "&IFERROR(_xlfn.XLOOKUP(B35,Sales_SKU!$B$2:$B$121,Sales_SKU!$L$2:$L$121,"MT"),"MT") -> 1 KL | F35: RM0035 | G35: PKG-DR200 | H35: Steel Drum 200L (Standard) | I35: =IF(RIGHT(E35,2)="KL",5*0.9,5) -> 4.5 | J35: PCS | K35: 0.99 | L35: 0.01 | M35: 46023 | O35: Active | P35: 200L drums (5 per MT)
A36: BOM00035 | B36: ESS-DKD-DKDINT-INK-99.6-NEAT-DR200-DHJ | C36: DKD | D36: DKD Intermediate | E36: ="1 "&IFERROR(_xlfn.XLOOKUP(B36,Sales_SKU!$B$2:$B$121,Sales_SKU!$L$2:$L$121,"MT"),"MT") -> 1 KL | F36: RM0046 | G36: PKG-PALLET | H36: Wooden Pallet (ISPM-15) | I36: =IF(RIGHT(E36,2)="KL",1.25*0.9,1.25) -> 1.125 | J36: PCS | K36: 0.99 | L36: 0.01 | M36: 46023 | O36: Active | P36: Wooden pallet (4 drums per pallet)
A37: BOM00036 | B37: ESS-ARYLIDE-ARYINT-IND-99.9-PWD-BAG25-DST | C37: ARYLIDE | D37: Arylide Intermediate | E37: ="1 "&IFERROR(_xlfn.XLOOKUP(B37,Sales_SKU!$B$2:$B$121,Sales_SKU!$L$2:$L$121,"MT"),"MT") -> 1 MT | F37: RM0006 | G37: RM-ANI-LN-90355 | H37: Aniline | I37: =IF(RIGHT(E37,2)="KL",0.72*0.9,0.72) -> 0.72 | J37: KG | K37: 0.98 | L37: 0.02 | M37: 46023 | O37: Active | P37: Aniline primary aromatic amine
A38: BOM00037 | B38: ESS-ARYLIDE-ARYINT-IND-99.9-PWD-BAG25-DST | C38: ARYLIDE | D38: Arylide Intermediate | E38: ="1 "&IFERROR(_xlfn.XLOOKUP(B38,Sales_SKU!$B$2:$B$121,Sales_SKU!$L$2:$L$121,"MT"),"MT") -> 1 MT | F38: RM0007 | G38: RM-PCA-AN-77210 | H38: p-Chloroaniline | I38: =IF(RIGHT(E38,2)="KL",0.35*0.9,0.35) -> 0.35 | J38: KG | K38: 0.98 | L38: 0.02 | M38: 46023 | O38: Active | P38: p-Chloroaniline for coupling
A39: BOM00038 | B39: ESS-ARYLIDE-ARYINT-IND-99.9-PWD-BAG25-DST | C39: ARYLIDE | D39: Arylide Intermediate | E39: ="1 "&IFERROR(_xlfn.XLOOKUP(B39,Sales_SKU!$B$2:$B$121,Sales_SKU!$L$2:$L$121,"MT"),"MT") -> 1 MT | F39: RM0008 | G39: RM-OAN-AS-55102 | H39: o-Anisidine | I39: =IF(RIGHT(E39,2)="KL",0.18*0.9,0.18) -> 0.18 | J39: KG | K39: 0.98 | L39: 0.02 | M39: 46023 | O39: Active | P39: o-Anisidine methoxy derivative
A40: BOM00039 | B40: ESS-ARYLIDE-ARYINT-IND-99.9-PWD-BAG25-DST | C40: ARYLIDE | D40: Arylide Intermediate | E40: ="1 "&IFERROR(_xlfn.XLOOKUP(B40,Sales_SKU!$B$2:$B$121,Sales_SKU!$L$2:$L$121,"MT"),"MT") -> 1 MT | F40: RM0002 | G40: RM-AAC-GL-23011 | H40: Acetic Acid (Glacial) | I40: =IF(RIGHT(E40,2)="KL",0.25*0.9,0.25) -> 0.25 | J40: MT | K40: 0.98 | L40: 0.02 | M40: 46023 | O40: Active | P40: Acetic acid for acetylation step
A41: BOM00040 | B41: ESS-ARYLIDE-ARYINT-IND-99.9-PWD-BAG25-DST | C41: ARYLIDE | D41: Arylide Intermediate | E41: ="1 "&IFERROR(_xlfn.XLOOKUP(B41,Sales_SKU!$B$2:$B$121,Sales_SKU!$L$2:$L$121,"MT"),"MT") -> 1 MT | F41: RM0041 | G41: PKG-BAG25 | H41: PP Woven Bag 25kg | I41: =IF(RIGHT(E41,2)="KL",40*0.9,40) -> 40 | J41: PCS | K41: 0.99 | L41: 0.01 | M41: 46023 | O41: Active | P41: 25kg PP bags (40 per MT)
A42: BOM00041 | B42: ESS-ARYLIDE-ARYINT-IND-99.9-PWD-BAG25-DST | C42: ARYLIDE | D42: Arylide Intermediate | E42: ="1 "&IFERROR(_xlfn.XLOOKUP(B42,Sales_SKU!$B$2:$B$121,Sales_SKU!$L$2:$L$121,"MT"),"MT") -> 1 MT | F42: RM0046 | G42: PKG-PALLET | H42: Wooden Pallet (ISPM-15) | I42: =IF(RIGHT(E42,2)="KL",1*0.9,1) -> 1 | J42: PCS | K42: 0.99 | L42: 0.01 | M42: 46023 | O42: Active | P42: Wooden pallet (for bagged goods)
A43: BOM00042 | B43: ESS-FLUORO-FLRBLK-LM-99.9-PWD-BAG25-MHD | C43: FLUORO | D43: Fluoro Building Block | E43: ="1 "&IFERROR(_xlfn.XLOOKUP(B43,Sales_SKU!$B$2:$B$121,Sales_SKU!$L$2:$L$121,"MT"),"MT") -> 1 MT | F43: RM0006 | G43: RM-ANI-LN-90355 | H43: Aniline | I43: =IF(RIGHT(E43,2)="KL",0.42*0.9,0.42) -> 0.42 | J43: KG | K43: 0.98 | L43: 0.02 | M43: 46023 | O43: Active | P43: Aniline aromatic base
A44: BOM00043 | B44: ESS-FLUORO-FLRBLK-LM-99.9-PWD-BAG25-MHD | C44: FLUORO | D44: Fluoro Building Block | E44: ="1 "&IFERROR(_xlfn.XLOOKUP(B44,Sales_SKU!$B$2:$B$121,Sales_SKU!$L$2:$L$121,"MT"),"MT") -> 1 MT | F44: RM0007 | G44: RM-PCA-AN-77210 | H44: p-Chloroaniline | I44: =IF(RIGHT(E44,2)="KL",0.28*0.9,0.28) -> 0.28 | J44: KG | K44: 0.98 | L44: 0.02 | M44: 46023 | O44: Active | P44: Chloroaniline intermediate
A45: BOM00044 | B45: ESS-FLUORO-FLRBLK-LM-99.9-PWD-BAG25-MHD | C45: FLUORO | D45: Fluoro Building Block | E45: ="1 "&IFERROR(_xlfn.XLOOKUP(B45,Sales_SKU!$B$2:$B$121,Sales_SKU!$L$2:$L$121,"MT"),"MT") -> 1 MT | F45: RM0017 | G45: RM-ACN-SV-33120 | H45: Acetonitrile | I45: =IF(RIGHT(E45,2)="KL",0.15*0.9,0.15) -> 0.15 | J45: KG | K45: 0.98 | L45: 0.02 | M45: 46023 | O45: Active | P45: Sulfuric acid catalyst/reagent
A46: BOM00045 | B46: ESS-FLUORO-FLRBLK-LM-99.9-PWD-BAG25-MHD | C46: FLUORO | D46: Fluoro Building Block | E46: ="1 "&IFERROR(_xlfn.XLOOKUP(B46,Sales_SKU!$B$2:$B$121,Sales_SKU!$L$2:$L$121,"MT"),"MT") -> 1 MT | F46: RM0019 | G46: RM-MEO-SV-11024 | H46: Methanol | I46: =IF(RIGHT(E46,2)="KL",0.32*0.9,0.32) -> 0.32 | J46: MT | K46: 0.98 | L46: 0.02 | M46: 46023 | O46: Active | P46: Toluene process solvent
A47: BOM00046 | B47: ESS-FLUORO-FLRBLK-LM-99.9-PWD-BAG25-MHD | C47: FLUORO | D47: Fluoro Building Block | E47: ="1 "&IFERROR(_xlfn.XLOOKUP(B47,Sales_SKU!$B$2:$B$121,Sales_SKU!$L$2:$L$121,"MT"),"MT") -> 1 MT | F47: RM0041 | G47: PKG-BAG25 | H47: PP Woven Bag 25kg | I47: =IF(RIGHT(E47,2)="KL",40*0.9,40) -> 40 | J47: PCS | K47: 0.99 | L47: 0.01 | M47: 46023 | O47: Active | P47: 25kg PP bags (40 per MT)
A48: BOM00047 | B48: ESS-FLUORO-FLRBLK-LM-99.9-PWD-BAG25-MHD | C48: FLUORO | D48: Fluoro Building Block | E48: ="1 "&IFERROR(_xlfn.XLOOKUP(B48,Sales_SKU!$B$2:$B$121,Sales_SKU!$L$2:$L$121,"MT"),"MT") -> 1 MT | F48: RM0046 | G48: PKG-PALLET | H48: Wooden Pallet (ISPM-15) | I48: =IF(RIGHT(E48,2)="KL",1*0.9,1) -> 1 | J48: PCS | K48: 0.99 | L48: 0.01 | M48: 46023 | O48: Active | P48: Wooden pallet (for bagged goods)
A49: BOM00048 | B49: SPI-ACETYL-ETHACE-TECH-99.9-NEAT-BULK-LTE | C49: ACETYL | D49: Ethyl Acetate | E49: ="1 "&IFERROR(_xlfn.XLOOKUP(B49,Sales_SKU!$B$2:$B$121,Sales_SKU!$L$2:$L$121,"MT"),"MT") -> 1 KL | F49: RM0001 | G49: RM-ETH-AL-64175 | H49: Ethyl Alcohol (Ethanol) | I49: =IF(RIGHT(E49,2)="KL",0.52*0.9,0.52) -> 0.468 | J49: MT | K49: 0.98 | L49: 0.02 | M49: 46023 | O49: Active | P49: Primary ethanol feed (esterification)
A50: BOM00049 | B50: SPI-ACETYL-ETHACE-TECH-99.9-NEAT-BULK-LTE | C50: ACETYL | D50: Ethyl Acetate | E50: ="1 "&IFERROR(_xlfn.XLOOKUP(B50,Sales_SKU!$B$2:$B$121,Sales_SKU!$L$2:$L$121,"MT"),"MT") -> 1 KL | F50: RM0002 | G50: RM-AAC-GL-23011 | H50: Acetic Acid (Glacial) | I50: =IF(RIGHT(E50,2)="KL",0.68*0.9,0.68) -> 0.612 | J50: MT | K50: 0.98 | L50: 0.02 | M50: 46023 | O50: Active | P50: Glacial acetic acid for esterification
A51: BOM00050 | B51: SPI-ACETYL-ETHACE-TECH-99.9-NEAT-BULK-LTE | C51: ACETYL | D51: Ethyl Acetate | E51: ="1 "&IFERROR(_xlfn.XLOOKUP(B51,Sales_SKU!$B$2:$B$121,Sales_SKU!$L$2:$L$121,"MT"),"MT") -> 1 KL | F51: RM0017 | G51: RM-ACN-SV-33120 | H51: Acetonitrile | I51: =IF(RIGHT(E51,2)="KL",0.008*0.9,0.008) -> 0.0072 | J51: KG | K51: 0.98 | L51: 0.02 | M51: 46023 | O51: Active | P51: Sulfuric acid catalyst
A52: BOM00051 | B52: ESS-ACETYL-ACEANH-TECH-98.1-NEAT-ISO20-DHJ | C52: ACETYL | D52: Acetic Anhydride | E52: ="1 "&IFERROR(_xlfn.XLOOKUP(B52,Sales_SKU!$B$2:$B$121,Sales_SKU!$L$2:$L$121,"MT"),"MT") -> 1 KL | F52: RM0002 | G52: RM-AAC-GL-23011 | H52: Acetic Acid (Glacial) | I52: =IF(RIGHT(E52,2)="KL",1.18*0.9,1.18) -> 1.062 | J52: MT | K52: 0.98 | L52: 0.02 | M52: 46023 | O52: Active | P52: Primary acetic acid feed (dehydration)
A53: BOM00052 | B53: ESS-ACETYL-ACEANH-TECH-98.1-NEAT-ISO20-DHJ | C53: ACETYL | D53: Acetic Anhydride | E53: ="1 "&IFERROR(_xlfn.XLOOKUP(B53,Sales_SKU!$B$2:$B$121,Sales_SKU!$L$2:$L$121,"MT"),"MT") -> 1 KL | F53: RM0020 | G53: RM-PDH-CB-61302 | H53: Palladium on Carbon (5%) | I53: =IF(RIGHT(E53,2)="KL",0.003*0.9,0.003) -> 0.0027 | J53: KG | K53: 0.98 | L53: 0.02 | M53: 46023 | O53: Active | P53: Catalyst for dehydration process
A54: BOM00053 | B54: ESS-ACETYL-ACEANH-TECH-98.1-NEAT-ISO20-DHJ | C54: ACETYL | D54: Acetic Anhydride | E54: ="1 "&IFERROR(_xlfn.XLOOKUP(B54,Sales_SKU!$B$2:$B$121,Sales_SKU!$L$2:$L$121,"MT"),"MT") -> 1 KL | F54: RM0039 | G54: PKG-ISO20 | H54: ISO Tank Container 20ft | I54: =IF(RIGHT(E54,2)="KL",0.05*0.9,0.05) -> 0.045 | J54: TRIP | K54: 0.99 | L54: 0.01 | M54: 46023 | O54: Active | P54: ISO tank (20ft, ~20MT capacity)
A55: BOM00054 | B55: ESS-ACETYL-ACE-TECH-98.8-NEAT-DR200_UN-DST | C55: ACETYL | D55: Acetaldehyde | E55: ="1 "&IFERROR(_xlfn.XLOOKUP(B55,Sales_SKU!$B$2:$B$121,Sales_SKU!$L$2:$L$121,"MT"),"MT") -> 1 KL | F55: RM0001 | G55: RM-ETH-AL-64175 | H55: Ethyl Alcohol (Ethanol) | I55: =IF(RIGHT(E55,2)="KL",1.05*0.9,1.05) -> 0.945 | J55: MT | K55: 0.98 | L55: 0.02 | M55: 46023 | O55: Active | P55: Ethanol for catalytic oxidation
A56: BOM00055 | B56: ESS-ACETYL-ACE-TECH-98.8-NEAT-DR200_UN-DST | C56: ACETYL | D56: Acetaldehyde | E56: ="1 "&IFERROR(_xlfn.XLOOKUP(B56,Sales_SKU!$B$2:$B$121,Sales_SKU!$L$2:$L$121,"MT"),"MT") -> 1 KL | F56: RM0020 | G56: RM-PDH-CB-61302 | H56: Palladium on Carbon (5%) | I56: =IF(RIGHT(E56,2)="KL",0.002*0.9,0.002) -> 0.0018 | J56: KG | K56: 0.98 | L56: 0.02 | M56: 46023 | O56: Active | P56: Oxidation catalyst
A57: BOM00056 | B57: ESS-ACETYL-ACE-TECH-98.8-NEAT-DR200_UN-DST | C57: ACETYL | D57: Acetaldehyde | E57: ="1 "&IFERROR(_xlfn.XLOOKUP(B57,Sales_SKU!$B$2:$B$121,Sales_SKU!$L$2:$L$121,"MT"),"MT") -> 1 KL | F57: RM0036 | G57: PKG-DR200_UN | H57: Steel Drum 200L (UN Certified) | I57: =IF(RIGHT(E57,2)="KL",5*0.9,5) -> 4.5 | J57: PCS | K57: 0.99 | L57: 0.01 | M57: 46023 | O57: Active | P57: UN-certified drums for DG
A58: BOM00057 | B58: ESS-ACETYL-ACE-TECH-98.8-NEAT-DR200_UN-DST | C58: ACETYL | D58: Acetaldehyde | E58: ="1 "&IFERROR(_xlfn.XLOOKUP(B58,Sales_SKU!$B$2:$B$121,Sales_SKU!$L$2:$L$121,"MT"),"MT") -> 1 KL | F58: RM0043 | G58: PKG-LABELS | H58: Product Labels (DG/GHS) | I58: =IF(RIGHT(E58,2)="KL",5*0.9,5) -> 4.5 | J58: SET | K58: 0.99 | L58: 0.01 | M58: 46023 | O58: Active | P58: DG/GHS labels (1 per drum)
A59: BOM00058 | B59: ESS-ACETYL-ACE-TECH-98.8-NEAT-DR200_UN-DST | C59: ACETYL | D59: Acetaldehyde | E59: ="1 "&IFERROR(_xlfn.XLOOKUP(B59,Sales_SKU!$B$2:$B$121,Sales_SKU!$L$2:$L$121,"MT"),"MT") -> 1 KL | F59: RM0044 | G59: PKG-DG-MARKS | H59: DG Placards & Markings | I59: =IF(RIGHT(E59,2)="KL",0.2*0.9,0.2) -> 0.18 | J59: SET | K59: 0.99 | L59: 0.01 | M59: 46023 | O59: Active | P59: DG placards (per pallet)
A60: BOM00059 | B60: ESS-ACETYL-ACE-TECH-98.8-NEAT-DR200_UN-DST | C60: ACETYL | D60: Acetaldehyde | E60: ="1 "&IFERROR(_xlfn.XLOOKUP(B60,Sales_SKU!$B$2:$B$121,Sales_SKU!$L$2:$L$121,"MT"),"MT") -> 1 KL | F60: RM0046 | G60: PKG-PALLET | H60: Wooden Pallet (ISPM-15) | I60: =IF(RIGHT(E60,2)="KL",1.25*0.9,1.25) -> 1.125 | J60: PCS | K60: 0.99 | L60: 0.01 | M60: 46023 | O60: Active | P60: Wooden pallet (4 drums per pallet)
A61: BOM00060 | B61: ESS-ACETYL-BUTACE-IND-98.3-NEAT-ISO20-MHD | C61: ACETYL | D61: Butyl Acetate | E61: ="1 "&IFERROR(_xlfn.XLOOKUP(B61,Sales_SKU!$B$2:$B$121,Sales_SKU!$L$2:$L$121,"MT"),"MT") -> 1 KL | F61: RM0003 | G61: RM-BUT-NB-51720 | H61: n-Butanol | I61: =IF(RIGHT(E61,2)="KL",0.64*0.9,0.64) -> 0.576 | J61: MT | K61: 0.98 | L61: 0.02 | M61: 46023 | O61: Active | P61: n-Butanol primary alcohol
A62: BOM00061 | B62: ESS-ACETYL-BUTACE-IND-98.3-NEAT-ISO20-MHD | C62: ACETYL | D62: Butyl Acetate | E62: ="1 "&IFERROR(_xlfn.XLOOKUP(B62,Sales_SKU!$B$2:$B$121,Sales_SKU!$L$2:$L$121,"MT"),"MT") -> 1 KL | F62: RM0002 | G62: RM-AAC-GL-23011 | H62: Acetic Acid (Glacial) | I62: =IF(RIGHT(E62,2)="KL",0.52*0.9,0.52) -> 0.468 | J62: MT | K62: 0.98 | L62: 0.02 | M62: 46023 | O62: Active | P62: Acetic acid for esterification
A63: BOM00062 | B63: ESS-ACETYL-BUTACE-IND-98.3-NEAT-ISO20-MHD | C63: ACETYL | D63: Butyl Acetate | E63: ="1 "&IFERROR(_xlfn.XLOOKUP(B63,Sales_SKU!$B$2:$B$121,Sales_SKU!$L$2:$L$121,"MT"),"MT") -> 1 KL | F63: RM0017 | G63: RM-ACN-SV-33120 | H63: Acetonitrile | I63: =IF(RIGHT(E63,2)="KL",0.012*0.9,0.012) -> 0.0108 | J63: KG | K63: 0.98 | L63: 0.02 | M63: 46023 | O63: Active | P63: Sulfuric acid catalyst
A64: BOM00063 | B64: ESS-ACETYL-BUTACE-IND-98.3-NEAT-ISO20-MHD | C64: ACETYL | D64: Butyl Acetate | E64: ="1 "&IFERROR(_xlfn.XLOOKUP(B64,Sales_SKU!$B$2:$B$121,Sales_SKU!$L$2:$L$121,"MT"),"MT") -> 1 KL | F64: RM0039 | G64: PKG-ISO20 | H64: ISO Tank Container 20ft | I64: =IF(RIGHT(E64,2)="KL",0.05*0.9,0.05) -> 0.045 | J64: TRIP | K64: 0.99 | L64: 0.01 | M64: 46023 | O64: Active | P64: ISO tank (20ft, ~20MT capacity)
A65: BOM00064 | B65: SPI-ACETYL-MAA-TECH-98.7-NEAT-DR200-LTE | C65: ACETYL | D65: Methyl Acetoacetate | E65: ="1 "&IFERROR(_xlfn.XLOOKUP(B65,Sales_SKU!$B$2:$B$121,Sales_SKU!$L$2:$L$121,"MT"),"MT") -> 1 KL | F65: RM0009 | G65: RM-DIK-ET-88412 | H65: Diketene | I65: =IF(RIGHT(E65,2)="KL",0.85*0.9,0.85) -> 0.765 | J65: KG | K65: 0.98 | L65: 0.02 | M65: 46023 | O65: Active | P65: Diketene for acetoacetylation
A66: BOM00065 | B66: SPI-ACETYL-MAA-TECH-98.7-NEAT-DR200-LTE | C66: ACETYL | D66: Methyl Acetoacetate | E66: ="1 "&IFERROR(_xlfn.XLOOKUP(B66,Sales_SKU!$B$2:$B$121,Sales_SKU!$L$2:$L$121,"MT"),"MT") -> 1 KL | F66: RM0001 | G66: RM-ETH-AL-64175 | H66: Ethyl Alcohol (Ethanol) | I66: =IF(RIGHT(E66,2)="KL",0.38*0.9,0.38) -> 0.342 | J66: MT | K66: 0.98 | L66: 0.02 | M66: 46023 | O66: Active | P66: Alcohol for ester formation
A67: BOM00066 | B67: SPI-ACETYL-MAA-TECH-98.7-NEAT-DR200-LTE | C67: ACETYL | D67: Methyl Acetoacetate | E67: ="1 "&IFERROR(_xlfn.XLOOKUP(B67,Sales_SKU!$B$2:$B$121,Sales_SKU!$L$2:$L$121,"MT"),"MT") -> 1 KL | F67: RM0020 | G67: RM-PDH-CB-61302 | H67: Palladium on Carbon (5%) | I67: =IF(RIGHT(E67,2)="KL",0.002*0.9,0.002) -> 0.0018 | J67: KG | K67: 0.98 | L67: 0.02 | M67: 46023 | O67: Active | P67: Process catalyst
A68: BOM00067 | B68: SPI-ACETYL-MAA-TECH-98.7-NEAT-DR200-LTE | C68: ACETYL | D68: Methyl Acetoacetate | E68: ="1 "&IFERROR(_xlfn.XLOOKUP(B68,Sales_SKU!$B$2:$B$121,Sales_SKU!$L$2:$L$121,"MT"),"MT") -> 1 KL | F68: RM0035 | G68: PKG-DR200 | H68: Steel Drum 200L (Standard) | I68: =IF(RIGHT(E68,2)="KL",5*0.9,5) -> 4.5 | J68: PCS | K68: 0.99 | L68: 0.01 | M68: 46023 | O68: Active | P68: 200L drums (5 per MT)
A69: BOM00068 | B69: SPI-ACETYL-MAA-TECH-98.7-NEAT-DR200-LTE | C69: ACETYL | D69: Methyl Acetoacetate | E69: ="1 "&IFERROR(_xlfn.XLOOKUP(B69,Sales_SKU!$B$2:$B$121,Sales_SKU!$L$2:$L$121,"MT"),"MT") -> 1 KL | F69: RM0046 | G69: PKG-PALLET | H69: Wooden Pallet (ISPM-15) | I69: =IF(RIGHT(E69,2)="KL",1.25*0.9,1.25) -> 1.125 | J69: PCS | K69: 0.99 | L69: 0.01 | M69: 46023 | O69: Active | P69: Wooden pallet (4 drums per pallet)
A70: BOM00069 | B70: ESS-ACETYL-EAA-INK-98.3-NEAT-DR200-DHJ | C70: ACETYL | D70: Ethyl Acetoacetate | E70: ="1 "&IFERROR(_xlfn.XLOOKUP(B70,Sales_SKU!$B$2:$B$121,Sales_SKU!$L$2:$L$121,"MT"),"MT") -> 1 KL | F70: RM0009 | G70: RM-DIK-ET-88412 | H70: Diketene | I70: =IF(RIGHT(E70,2)="KL",0.65*0.9,0.65) -> 0.585 | J70: KG | K70: 0.98 | L70: 0.02 | M70: 46023 | O70: Active | P70: Diketene derivative source
A71: BOM00070 | B71: ESS-ACETYL-EAA-INK-98.3-NEAT-DR200-DHJ | C71: ACETYL | D71: Ethyl Acetoacetate | E71: ="1 "&IFERROR(_xlfn.XLOOKUP(B71,Sales_SKU!$B$2:$B$121,Sales_SKU!$L$2:$L$121,"MT"),"MT") -> 1 KL | F71: RM0001 | G71: RM-ETH-AL-64175 | H71: Ethyl Alcohol (Ethanol) | I71: =IF(RIGHT(E71,2)="KL",0.36*0.9,0.36) -> 0.324 | J71: MT | K71: 0.98 | L71: 0.02 | M71: 46023 | O71: Active | P71: Ethanol for esterification
A72: BOM00071 | B72: ESS-ACETYL-EAA-INK-98.3-NEAT-DR200-DHJ | C72: ACETYL | D72: Ethyl Acetoacetate | E72: ="1 "&IFERROR(_xlfn.XLOOKUP(B72,Sales_SKU!$B$2:$B$121,Sales_SKU!$L$2:$L$121,"MT"),"MT") -> 1 KL | F72: RM0020 | G72: RM-PDH-CB-61302 | H72: Palladium on Carbon (5%) | I72: =IF(RIGHT(E72,2)="KL",0.002*0.9,0.002) -> 0.0018 | J72: KG | K72: 0.98 | L72: 0.02 | M72: 46023 | O72: Active | P72: Catalyst
A73: BOM00072 | B73: ESS-ACETYL-EAA-INK-98.3-NEAT-DR200-DHJ | C73: ACETYL | D73: Ethyl Acetoacetate | E73: ="1 "&IFERROR(_xlfn.XLOOKUP(B73,Sales_SKU!$B$2:$B$121,Sales_SKU!$L$2:$L$121,"MT"),"MT") -> 1 KL | F73: RM0035 | G73: PKG-DR200 | H73: Steel Drum 200L (Standard) | I73: =IF(RIGHT(E73,2)="KL",5*0.9,5) -> 4.5 | J73: PCS | K73: 0.99 | L73: 0.01 | M73: 46023 | O73: Active | P73: 200L drums (5 per MT)
A74: BOM00073 | B74: ESS-ACETYL-EAA-INK-98.3-NEAT-DR200-DHJ | C74: ACETYL | D74: Ethyl Acetoacetate | E74: ="1 "&IFERROR(_xlfn.XLOOKUP(B74,Sales_SKU!$B$2:$B$121,Sales_SKU!$L$2:$L$121,"MT"),"MT") -> 1 KL | F74: RM0046 | G74: PKG-PALLET | H74: Wooden Pallet (ISPM-15) | I74: =IF(RIGHT(E74,2)="KL",1.25*0.9,1.25) -> 1.125 | J74: PCS | K74: 0.99 | L74: 0.01 | M74: 46023 | O74: Active | P74: Wooden pallet (4 drums per pallet)
A75: BOM00074 | B75: ESS-ACETYL-AAEM-PH-99.3-NEAT-BULK-DST | C75: ACETYL | D75: AAEM (Acetoacetoxyethyl Methacrylate) | E75: ="1 "&IFERROR(_xlfn.XLOOKUP(B75,Sales_SKU!$B$2:$B$121,Sales_SKU!$L$2:$L$121,"MT"),"MT") -> 1 KL | F75: RM0005 | G75: RM-MTH-AA-40218 | H75: Methacrylic Acid | I75: =IF(RIGHT(E75,2)="KL",0.67*0.9,0.67) -> 0.603 | J75: KG | K75: 0.98 | L75: 0.02 | M75: 46023 | O75: Active | P75: Methacrylic acid for acrylate synthesis
A76: BOM00075 | B76: ESS-ACETYL-AAEM-PH-99.3-NEAT-BULK-DST | C76: ACETYL | D76: AAEM (Acetoacetoxyethyl Methacrylate) | E76: ="1 "&IFERROR(_xlfn.XLOOKUP(B76,Sales_SKU!$B$2:$B$121,Sales_SKU!$L$2:$L$121,"MT"),"MT") -> 1 KL | F76: RM0009 | G76: RM-DIK-ET-88412 | H76: Diketene | I76: =IF(RIGHT(E76,2)="KL",0.55*0.9,0.55) -> 0.495 | J76: KG | K76: 0.98 | L76: 0.02 | M76: 46023 | O76: Active | P76: Diketene for acetoacetyl group
A77: BOM00076 | B77: ESS-ACETYL-AAEM-PH-99.3-NEAT-BULK-DST | C77: ACETYL | D77: AAEM (Acetoacetoxyethyl Methacrylate) | E77: ="1 "&IFERROR(_xlfn.XLOOKUP(B77,Sales_SKU!$B$2:$B$121,Sales_SKU!$L$2:$L$121,"MT"),"MT") -> 1 KL | F77: RM0001 | G77: RM-ETH-AL-64175 | H77: Ethyl Alcohol (Ethanol) | I77: =IF(RIGHT(E77,2)="KL",0.22*0.9,0.22) -> 0.198 | J77: MT | K77: 0.98 | L77: 0.02 | M77: 46023 | O77: Active | P77: Ethanol solvent/reactant
A78: BOM00077 | B78: ESS-ACETYL-AAEM-PH-99.3-NEAT-BULK-DST | C78: ACETYL | D78: AAEM (Acetoacetoxyethyl Methacrylate) | E78: ="1 "&IFERROR(_xlfn.XLOOKUP(B78,Sales_SKU!$B$2:$B$121,Sales_SKU!$L$2:$L$121,"MT"),"MT") -> 1 KL | F78: RM0020 | G78: RM-PDH-CB-61302 | H78: Palladium on Carbon (5%) | I78: =IF(RIGHT(E78,2)="KL",0.003*0.9,0.003) -> 0.0027 | J78: KG | K78: 0.98 | L78: 0.02 | M78: 46023 | O78: Active | P78: Process catalyst
A79: BOM00078 | B79: ESS-DKD-DKDINT-LM-98.0-NEAT-DR200-MHD | C79: DKD | D79: DKD Intermediate | E79: ="1 "&IFERROR(_xlfn.XLOOKUP(B79,Sales_SKU!$B$2:$B$121,Sales_SKU!$L$2:$L$121,"MT"),"MT") -> 1 KL | F79: RM0009 | G79: RM-DIK-ET-88412 | H79: Diketene | I79: =IF(RIGHT(E79,2)="KL",0.92*0.9,0.92) -> 0.828 | J79: KG | K79: 0.98 | L79: 0.02 | M79: 46023 | O79: Active | P79: Primary diketene feed
A80: BOM00079 | B80: ESS-DKD-DKDINT-LM-98.0-NEAT-DR200-MHD | C80: DKD | D80: DKD Intermediate | E80: ="1 "&IFERROR(_xlfn.XLOOKUP(B80,Sales_SKU!$B$2:$B$121,Sales_SKU!$L$2:$L$121,"MT"),"MT") -> 1 KL | F80: RM0001 | G80: RM-ETH-AL-64175 | H80: Ethyl Alcohol (Ethanol) | I80: =IF(RIGHT(E80,2)="KL",0.28*0.9,0.28) -> 0.252 | J80: MT | K80: 0.98 | L80: 0.02 | M80: 46023 | O80: Active | P80: Ethanol process solvent
A81: BOM00080 | B81: ESS-DKD-DKDINT-LM-98.0-NEAT-DR200-MHD | C81: DKD | D81: DKD Intermediate | E81: ="1 "&IFERROR(_xlfn.XLOOKUP(B81,Sales_SKU!$B$2:$B$121,Sales_SKU!$L$2:$L$121,"MT"),"MT") -> 1 KL | F81: RM0002 | G81: RM-AAC-GL-23011 | H81: Acetic Acid (Glacial) | I81: =IF(RIGHT(E81,2)="KL",0.15*0.9,0.15) -> 0.135 | J81: MT | K81: 0.98 | L81: 0.02 | M81: 46023 | O81: Active | P81: Acetic acid for process
A82: BOM00081 | B82: ESS-DKD-DKDINT-LM-98.0-NEAT-DR200-MHD | C82: DKD | D82: DKD Intermediate | E82: ="1 "&IFERROR(_xlfn.XLOOKUP(B82,Sales_SKU!$B$2:$B$121,Sales_SKU!$L$2:$L$121,"MT"),"MT") -> 1 KL | F82: RM0035 | G82: PKG-DR200 | H82: Steel Drum 200L (Standard) | I82: =IF(RIGHT(E82,2)="KL",5*0.9,5) -> 4.5 | J82: PCS | K82: 0.99 | L82: 0.01 | M82: 46023 | O82: Active | P82: 200L drums (5 per MT)
A83: BOM00082 | B83: ESS-DKD-DKDINT-LM-98.0-NEAT-DR200-MHD | C83: DKD | D83: DKD Intermediate | E83: ="1 "&IFERROR(_xlfn.XLOOKUP(B83,Sales_SKU!$B$2:$B$121,Sales_SKU!$L$2:$L$121,"MT"),"MT") -> 1 KL | F83: RM0046 | G83: PKG-PALLET | H83: Wooden Pallet (ISPM-15) | I83: =IF(RIGHT(E83,2)="KL",1.25*0.9,1.25) -> 1.125 | J83: PCS | K83: 0.99 | L83: 0.01 | M83: 46023 | O83: Active | P83: Wooden pallet (4 drums per pallet)
A84: BOM00083 | B84: ESS-ARYLIDE-ARYINT-LM-98.5-PWD-BAG25-LTE | C84: ARYLIDE | D84: Arylide Intermediate | E84: ="1 "&IFERROR(_xlfn.XLOOKUP(B84,Sales_SKU!$B$2:$B$121,Sales_SKU!$L$2:$L$121,"MT"),"MT") -> 1 MT | F84: RM0006 | G84: RM-ANI-LN-90355 | H84: Aniline | I84: =IF(RIGHT(E84,2)="KL",0.72*0.9,0.72) -> 0.72 | J84: KG | K84: 0.98 | L84: 0.02 | M84: 46023 | O84: Active | P84: Aniline primary aromatic amine
A85: BOM00084 | B85: ESS-ARYLIDE-ARYINT-LM-98.5-PWD-BAG25-LTE | C85: ARYLIDE | D85: Arylide Intermediate | E85: ="1 "&IFERROR(_xlfn.XLOOKUP(B85,Sales_SKU!$B$2:$B$121,Sales_SKU!$L$2:$L$121,"MT"),"MT") -> 1 MT | F85: RM0007 | G85: RM-PCA-AN-77210 | H85: p-Chloroaniline | I85: =IF(RIGHT(E85,2)="KL",0.35*0.9,0.35) -> 0.35 | J85: KG | K85: 0.98 | L85: 0.02 | M85: 46023 | O85: Active | P85: p-Chloroaniline for coupling
A86: BOM00085 | B86: ESS-ARYLIDE-ARYINT-LM-98.5-PWD-BAG25-LTE | C86: ARYLIDE | D86: Arylide Intermediate | E86: ="1 "&IFERROR(_xlfn.XLOOKUP(B86,Sales_SKU!$B$2:$B$121,Sales_SKU!$L$2:$L$121,"MT"),"MT") -> 1 MT | F86: RM0008 | G86: RM-OAN-AS-55102 | H86: o-Anisidine | I86: =IF(RIGHT(E86,2)="KL",0.18*0.9,0.18) -> 0.18 | J86: KG | K86: 0.98 | L86: 0.02 | M86: 46023 | O86: Active | P86: o-Anisidine methoxy derivative
A87: BOM00086 | B87: ESS-ARYLIDE-ARYINT-LM-98.5-PWD-BAG25-LTE | C87: ARYLIDE | D87: Arylide Intermediate | E87: ="1 "&IFERROR(_xlfn.XLOOKUP(B87,Sales_SKU!$B$2:$B$121,Sales_SKU!$L$2:$L$121,"MT"),"MT") -> 1 MT | F87: RM0002 | G87: RM-AAC-GL-23011 | H87: Acetic Acid (Glacial) | I87: =IF(RIGHT(E87,2)="KL",0.25*0.9,0.25) -> 0.25 | J87: MT | K87: 0.98 | L87: 0.02 | M87: 46023 | O87: Active | P87: Acetic acid for acetylation step
A88: BOM00087 | B88: ESS-ARYLIDE-ARYINT-LM-98.5-PWD-BAG25-LTE | C88: ARYLIDE | D88: Arylide Intermediate | E88: ="1 "&IFERROR(_xlfn.XLOOKUP(B88,Sales_SKU!$B$2:$B$121,Sales_SKU!$L$2:$L$121,"MT"),"MT") -> 1 MT | F88: RM0041 | G88: PKG-BAG25 | H88: PP Woven Bag 25kg | I88: =IF(RIGHT(E88,2)="KL",40*0.9,40) -> 40 | J88: PCS | K88: 0.99 | L88: 0.01 | M88: 46023 | O88: Active | P88: 25kg PP bags (40 per MT)
A89: BOM00088 | B89: ESS-ARYLIDE-ARYINT-LM-98.5-PWD-BAG25-LTE | C89: ARYLIDE | D89: Arylide Intermediate | E89: ="1 "&IFERROR(_xlfn.XLOOKUP(B89,Sales_SKU!$B$2:$B$121,Sales_SKU!$L$2:$L$121,"MT"),"MT") -> 1 MT | F89: RM0046 | G89: PKG-PALLET | H89: Wooden Pallet (ISPM-15) | I89: =IF(RIGHT(E89,2)="KL",1*0.9,1) -> 1 | J89: PCS | K89: 0.99 | L89: 0.01 | M89: 46023 | O89: Active | P89: Wooden pallet (for bagged goods)
A90: BOM00089 | B90: SPI-FLUORO-FLRBLK-LM-99.0-PWD-BAG25-DHJ | C90: FLUORO | D90: Fluoro Building Block | E90: ="1 "&IFERROR(_xlfn.XLOOKUP(B90,Sales_SKU!$B$2:$B$121,Sales_SKU!$L$2:$L$121,"MT"),"MT") -> 1 MT | F90: RM0006 | G90: RM-ANI-LN-90355 | H90: Aniline | I90: =IF(RIGHT(E90,2)="KL",0.42*0.9,0.42) -> 0.42 | J90: KG | K90: 0.98 | L90: 0.02 | M90: 46023 | O90: Active | P90: Aniline aromatic base
A91: BOM00090 | B91: SPI-FLUORO-FLRBLK-LM-99.0-PWD-BAG25-DHJ | C91: FLUORO | D91: Fluoro Building Block | E91: ="1 "&IFERROR(_xlfn.XLOOKUP(B91,Sales_SKU!$B$2:$B$121,Sales_SKU!$L$2:$L$121,"MT"),"MT") -> 1 MT | F91: RM0007 | G91: RM-PCA-AN-77210 | H91: p-Chloroaniline | I91: =IF(RIGHT(E91,2)="KL",0.28*0.9,0.28) -> 0.28 | J91: KG | K91: 0.98 | L91: 0.02 | M91: 46023 | O91: Active | P91: Chloroaniline intermediate
A92: BOM00091 | B92: SPI-FLUORO-FLRBLK-LM-99.0-PWD-BAG25-DHJ | C92: FLUORO | D92: Fluoro Building Block | E92: ="1 "&IFERROR(_xlfn.XLOOKUP(B92,Sales_SKU!$B$2:$B$121,Sales_SKU!$L$2:$L$121,"MT"),"MT") -> 1 MT | F92: RM0017 | G92: RM-ACN-SV-33120 | H92: Acetonitrile | I92: =IF(RIGHT(E92,2)="KL",0.15*0.9,0.15) -> 0.15 | J92: KG | K92: 0.98 | L92: 0.02 | M92: 46023 | O92: Active | P92: Sulfuric acid catalyst/reagent
A93: BOM00092 | B93: SPI-FLUORO-FLRBLK-LM-99.0-PWD-BAG25-DHJ | C93: FLUORO | D93: Fluoro Building Block | E93: ="1 "&IFERROR(_xlfn.XLOOKUP(B93,Sales_SKU!$B$2:$B$121,Sales_SKU!$L$2:$L$121,"MT"),"MT") -> 1 MT | F93: RM0019 | G93: RM-MEO-SV-11024 | H93: Methanol | I93: =IF(RIGHT(E93,2)="KL",0.32*0.9,0.32) -> 0.32 | J93: MT | K93: 0.98 | L93: 0.02 | M93: 46023 | O93: Active | P93: Toluene process solvent
A94: BOM00093 | B94: SPI-FLUORO-FLRBLK-LM-99.0-PWD-BAG25-DHJ | C94: FLUORO | D94: Fluoro Building Block | E94: ="1 "&IFERROR(_xlfn.XLOOKUP(B94,Sales_SKU!$B$2:$B$121,Sales_SKU!$L$2:$L$121,"MT"),"MT") -> 1 MT | F94: RM0041 | G94: PKG-BAG25 | H94: PP Woven Bag 25kg | I94: =IF(RIGHT(E94,2)="KL",40*0.9,40) -> 40 | J94: PCS | K94: 0.99 | L94: 0.01 | M94: 46023 | O94: Active | P94: 25kg PP bags (40 per MT)
A95: BOM00094 | B95: SPI-FLUORO-FLRBLK-LM-99.0-PWD-BAG25-DHJ | C95: FLUORO | D95: Fluoro Building Block | E95: ="1 "&IFERROR(_xlfn.XLOOKUP(B95,Sales_SKU!$B$2:$B$121,Sales_SKU!$L$2:$L$121,"MT"),"MT") -> 1 MT | F95: RM0046 | G95: PKG-PALLET | H95: Wooden Pallet (ISPM-15) | I95: =IF(RIGHT(E95,2)="KL",1*0.9,1) -> 1 | J95: PCS | K95: 0.99 | L95: 0.01 | M95: 46023 | O95: Active | P95: Wooden pallet (for bagged goods)
A96: BOM00095 | B96: ESS-ACETYL-ETHACE-LM-99.7-NEAT-IBC1KL-DST | C96: ACETYL | D96: Ethyl Acetate | E96: ="1 "&IFERROR(_xlfn.XLOOKUP(B96,Sales_SKU!$B$2:$B$121,Sales_SKU!$L$2:$L$121,"MT"),"MT") -> 1 KL | F96: RM0001 | G96: RM-ETH-AL-64175 | H96: Ethyl Alcohol (Ethanol) | I96: =IF(RIGHT(E96,2)="KL",0.52*0.9,0.52) -> 0.468 | J96: MT | K96: 0.98 | L96: 0.02 | M96: 46023 | O96: Active | P96: Primary ethanol feed (esterification)
A97: BOM00096 | B97: ESS-ACETYL-ETHACE-LM-99.7-NEAT-IBC1KL-DST | C97: ACETYL | D97: Ethyl Acetate | E97: ="1 "&IFERROR(_xlfn.XLOOKUP(B97,Sales_SKU!$B$2:$B$121,Sales_SKU!$L$2:$L$121,"MT"),"MT") -> 1 KL | F97: RM0002 | G97: RM-AAC-GL-23011 | H97: Acetic Acid (Glacial) | I97: =IF(RIGHT(E97,2)="KL",0.68*0.9,0.68) -> 0.612 | J97: MT | K97: 0.98 | L97: 0.02 | M97: 46023 | O97: Active | P97: Glacial acetic acid for esterification
A98: BOM00097 | B98: ESS-ACETYL-ETHACE-LM-99.7-NEAT-IBC1KL-DST | C98: ACETYL | D98: Ethyl Acetate | E98: ="1 "&IFERROR(_xlfn.XLOOKUP(B98,Sales_SKU!$B$2:$B$121,Sales_SKU!$L$2:$L$121,"MT"),"MT") -> 1 KL | F98: RM0017 | G98: RM-ACN-SV-33120 | H98: Acetonitrile | I98: =IF(RIGHT(E98,2)="KL",0.008*0.9,0.008) -> 0.0072 | J98: KG | K98: 0.98 | L98: 0.02 | M98: 46023 | O98: Active | P98: Sulfuric acid catalyst
A99: BOM00098 | B99: ESS-ACETYL-ETHACE-LM-99.7-NEAT-IBC1KL-DST | C99: ACETYL | D99: Ethyl Acetate | E99: ="1 "&IFERROR(_xlfn.XLOOKUP(B99,Sales_SKU!$B$2:$B$121,Sales_SKU!$L$2:$L$121,"MT"),"MT") -> 1 KL | F99: RM0037 | G99: PKG-IBC1KL | H99: IBC 1000L Composite | I99: =IF(RIGHT(E99,2)="KL",1*0.9,1) -> 0.9 | J99: PCS | K99: 0.99 | L99: 0.01 | M99: 46023 | O99: Active | P99: 1000L IBC (~1 MT capacity)
A100: BOM00099 | B100: ESS-ACETYL-ACEANH-IND-98.8-NEAT-BULK-MHD | C100: ACETYL | D100: Acetic Anhydride | E100: ="1 "&IFERROR(_xlfn.XLOOKUP(B100,Sales_SKU!$B$2:$B$121,Sales_SKU!$L$2:$L$121,"MT"),"MT") -> 1 KL | F100: RM0002 | G100: RM-AAC-GL-23011 | H100: Acetic Acid (Glacial) | I100: =IF(RIGHT(E100,2)="KL",1.18*0.9,1.18) -> 1.062 | J100: MT | K100: 0.98 | L100: 0.02 | M100: 46023 | O100: Active | P100: Primary acetic acid feed (dehydration)
...

Sheet Regions
A1: region_id (Primary Key) | B1: region_name | C1: type | D1: active | E1: notes
A2: DOM | B2: India (Domestic) | C2: COUNTRY | D2: TRUE | E2: Domestic sales; GST invoicing; standard road lanes.
A3: EU | B3: European Union | C3: BLOC | D3: TRUE | E3: REACH/CLP compliance; SDS in local languages; DG-capable sea lanes.
A4: AMER | B4: Americas | C4: REGION | D4: TRUE | E4: US/LatAm exports; TSCA alignment; longer lead times via ocean freight.
A5: APAC | B5: Asia Pacific | C5: REGION | D5: TRUE | E5: APAC export hub; varied local registrations; mixed sea/road lanes.
A6: MEA | B6: Middle East & Africa | C6: REGION | D6: TRUE | E6: Often DG documentation required; bank LC common; temperature exposure risk.
A7: ROW | B7: Rest of World | C7: REGION | D7: TRUE | E7: Catch-all region for ad-hoc exports; validate local regulatory needs per shipment.

Sheet Countries
A1: country_id (Primary Key) | B1: country_name | C1: type | D1: iso_code | E1: region_id (FK) | F1: active | G1: notes
A2: IND | B2: India | C2: COUNTRY | D2: IN | E2: DOM | F2: TRUE | G2: Home market; GST/road lanes.
A3: DEU | B3: Germany | C3: COUNTRY | D3: DE | E3: EU | F3: TRUE | G3: EU; REACH/CLP aligned.
A4: FRA | B4: France | C4: COUNTRY | D4: FR | E4: EU | F4: TRUE | G4: EU; DG documentation common.
A5: ITA | B5: Italy | C5: COUNTRY | D5: IT | E5: EU | F5: TRUE | G5: EU; port lead times vary.
A6: ESP | B6: Spain | C6: COUNTRY | D6: ES | E6: EU | F6: TRUE | G6: EU; distributor network.
A7: NLD | B7: Netherlands | C7: COUNTRY | D7: NL | E7: EU | F7: TRUE | G7: EU hub; Rotterdam.
A8: BEL | B8: Belgium | C8: COUNTRY | D8: BE | E8: EU | F8: TRUE | G8: EU chemicals; strict SDS.
A9: POL | B9: Poland | C9: COUNTRY | D9: PL | E9: EU | F9: TRUE | G9: EU; growing demand.
A10: SWE | B10: Sweden | C10: COUNTRY | D10: SE | E10: EU | F10: TRUE | G10: EU; DG sea lanes.
A11: DNK | B11: Denmark | C11: COUNTRY | D11: DK | E11: EU | F11: TRUE | G11: EU; DG sea lanes.
A12: AUT | B12: Austria | C12: COUNTRY | D12: AT | E12: EU | F12: TRUE | G12: EU; inland trucking.
A13: CZE | B13: Czech Republic | C13: COUNTRY | D13: CZ | E13: EU | F13: TRUE | G13: EU; labeling compliance.
... A53: IRN | B53: Iran | C53: COUNTRY | D53: IR | E53: MEA | F53: FALSE | G53: Restricted market; illustrative inactive.

Sheet Customers
A1: customer_id (Primary Key) | B1: customer_name | C1: customer_type | D1: industry | E1: industry_code | F1: customer_region_id (FK-style) | G1: country_iso (FK) | H1: city | I1: currency | J1: channel | K1: risk_rating | L1: status | M1: gst_vat_id | N1: key_account_manager | O1: created_date
A2: CUS0001 | B2: GreenField Pharma GmbH | C2: B2B | D2: Pharmaceuticals | E2: PHARMA | F2: DOM | G2: IN | H2: Ahmedabad | I2: INR | J2: Direct | K2: C | L2: Active | M2: TAX-IN-499676 | N2: Team-Strategic | O2: 45994
A3: CUS0002 | B3: Keystone Pigments Co. Ltd | C3: B2B | D3: Adhesives | E3: ADH | F3: APAC | G3: CN | H3: Shanghai | I3: CNY | J3: Distributor | K3: A | L3: Active | M3: TAX-CN-943121 | N3: Team-Intl | O3: 46191
A4: CUS0003 | B4: Aurum Agro S.A. | C4: B2B | D4: Industrial Solvents | E4: SOLV | F4: DOM | G4: IN | H4: Mumbai | I4: INR | J4: Distributor | K4: C | L4: Active | M4: TAX-IN-696397 | N4: Team-South | O4: 46070
A5: CUS0004 | B5: BluePeak Agro Ltd | C5: B2B | D5: Pigments | E5: PIGM | F5: AMER | G5: US | H5: Newark | I5: USD | J5: Distributor | K5: B | L5: Active | M5: TAX-US-215769 | N5: Team-Intl | O5: 45589
A6: CUS0005 | B6: Keystone Coatings S.A. | C6: B2B | D6: Inks & Coatings | E6: INKS | F6: DOM | G6: IN | H6: Gurgaon | I6: INR | J6: Distributor | K6: B | L6: Active | M6: TAX-IN-979970 | N6: Team-West | O6: 45404
A7: CUS0006 | B7: Sapphire Pharma NV | C7: B2B | D7: Industrial Solvents | E7: SOLV | F7: APAC | G7: CN | H7: Shenzhen | I7: CNY | J7: Direct | K7: A | L7: Active | M7: TAX-CN-490679 | N7: Team-Strategic | O7: 45521
A8: CUS0007 | B8: Sterling Solvents GmbH | C8: B2B | D8: Adhesives | E8: ADH | F8: DOM | G8: IN | H8: Gurgaon | I8: INR | J8: Direct | K8: A | L8: Active | M8: TAX-IN-987820 | N8: Team-South | O8: 45758
A9: CUS0008 | B9: Nimbus Pigments S.A. | C9: B2B | D9: Agrochemicals | E9: AGRO | F9: AMER | G9: US | H9: Newark | I9: USD | J9: Direct | K9: B | L9: Active | M9: TAX-US-840961 | N9: Team-Intl | O9: 46292
A10: CUS0009 | B10: Silverline Pharma Inc. | C10: B2B | D10: Packaging | E10: PKG | F10: DOM | G10: IN | H10: Ahmedabad | I10: INR | J10: Direct | K10: B | L10: Active | M10: TAX-IN-700729 | N10: Team-South | O10: 45897
A11: CUS0010 | B11: Keystone Coatings Co. Ltd | C11: B2B | D11: Inks & Coatings | E11: INKS | F11: EU | G11: FR | H11: Lyon | I11: EUR | J11: Distributor | K11: B | L11: Active | M11: TAX-FR-255209 | N11: Team-Intl | O11: 45884
A12: CUS0011 | B12: Nimbus Packaging NV | C12: B2B | D12: Pigments | E12: PIGM | F12: EU | G12: SE | H12: Barcelona | I12: EUR | J12: Distributor | K12: A | L12: Active | M12: TAX-SE-766346 | N12: Team-Intl | O12: 46356
A13: CUS0012 | B13: Sterling Agro LLP | C13: B2B | D13: Adhesives | E13: ADH | F13: DOM | G13: IN | H13: Chennai | I13: INR | J13: Distributor | K13: B | L13: Prospect | M13: TAX-IN-731425 | N13: Team-Strategic | O13: 46281
... A101: CUS0100 | B101: Atlas Pigments LLP | C101: B2B | D101: Pigments | E101: PIGM | F101: EU | G101: DE | H101: Warsaw | I101: EUR | J101: Direct | K101: C | L101: Active | M101: TAX-DE-234001 | N101: Team-Intl | O101: 46341

Sheet SLA Profiles
A1: sla_id (Primary Key) | B1: sla_name | C1: scope_region_id (FK) | D1: applicable_channels | E1: applicable_families | F1: incoterms_scope | G1: service_window_cutoff_local | H1: service_days | I1: dispatch_lead_time_days (min) | J1: dispatch_lead_time_days (max) | K1: Handover at | L1: delivery_window_days (min) | M1: delivery_window_days (max) | N1: otif_target_pct | O1: ot_time_tolerance | P1: in_full_target_pct | Q1: fill_rate_target_pct | R1: backorder_resolution_days | S1: quote_tat_hours | T1: order_ack_tat_hours | U1: documentation_requirements | V1: documentation_accuracy_pct | W1: pod_submission_hours | X1: claims_response_business_days | Y1: claims_closure_business_days | Z1: temperature_control | AA1: dg_class_handling | AB1: min_order_quantity | AC1: packaging_constraints | AD1: penalty_credit_logic | AE1: review_frequency | AF1: effective_from | AG1: effective_to | AH1: status
A2: SLA_STD_DOM_T1 | B2: Domestic Standard T1 (Bulk Liquids) | C2: DOM | D2: Direct,Distributor | E2: ACETYL,DKD | F2: EXW/FCA | G2: 14:00 | H2: Mon-Sat | I2: 1 | J2: 2 | K2: Plant gate | L2: 1 | M2: 3 | N2: 94 | O2: +/-1 day | P2: 97 | Q2: 96 | R2: 5 | S2: 8 | T2: 4 | U2: COA,Invoice,Ewaybill | V2: 99.5 | W2: 48 | X2: 3 | Y2: 10 | Z2: Ambient | AA2: DG allowed (where applicable) | AB2: 2000 KG | AC2: BULK,ISO20,IBC1KL | AD2: 1% credit if OTIF < target (monthly) on eligible orders | AE2: Quarterly | AF2: 2026-01-01 | AH2: Active
A3: SLA_STD_DOM_T2 | B3: Domestic Priority T2 (Drums/IBCs) | C3: DOM | D3: Direct,Distributor | E3: ACETYL,DKD,ARYLIDE | F3: EXW/FCA | G3: 16:00 | H3: Mon-Sat | I3: 0 | J3: 1 | K3: Plant gate | L3: 1 | M3: 2 | N3: 96 | O3: +/-0 day | P3: 98 | Q3: 97 | R3: 3 | S3: 6 | T3: 2 | U3: COA,Invoice,Ewaybill,UN Pack Cert (if DG) | V3: 99.7 | W3: 36 | X3: 2 | Y3: 7 | Z3: Ambient | AA3: DG allowed | AB3: 500 KG | AC3: DR200,DR200_UN,IBC1KL | AD3: 2% credit on freight line if OTIF < target (monthly) | AE3: Monthly | AF3: 2026-01-01 | AH3: Active
A4: SLA_STD_DOM_T3 | B4: Domestic Economy T3 (Powders) | C4: DOM | D4: Distributor | E4: ARYLIDE,FLUORO | F4: EXW | G4: 12:00 | H4: Mon-Fri | I4: 2 | J4: 4 | K4: Plant gate | L4: 2 | M4: 5 | N4: 92 | O4: +/-1 day | P4: 96 | Q4: 95 | R4: 7 | S4: 12 | T4: 6 | U4: COA,Invoice | V4: 99 | W4: 72 | X4: 4 | Y4: 15 | Z4: Ambient | AA4: DG by exception | AB4: 1000 KG | AC4: BAG25 only | AD4: No penalties; service credits only for documented failures above 3% of orders | AE4: Semi-Annual | AF4: 2026-01-01 | AH4: Active
A5: SLA_EXPORT_EU_T1 | B5: Export EU T1 (REACH-ready) | C5: EU | D5: Export-Direct,Distributor | E5: ACETYL,DKD,ARYLIDE | F5: FOB/CIF/CIP | G5: 13:00 | H5: Mon-Fri | I5: 3 | J5: 5 | K5: Port (Nhava Sheva/Mundra) | L5: 14 | M5: 21 | N5: 94 | O5: +/-2 days | P5: 97 | Q5: 96 | R5: 10 | S5: 24 | T5: 12 | U5: COA,Invoice,Packing List,SDS,REACH docs,BL | V5: 99.5 | W5: 120 | X5: 5 | Y5: 20 | Z5: Ambient | AA5: DG allowed (IMO) | AB5: 10 MT | AC5: ISO20,Flexitank,DR200_UN | AD5: 1% credit on invoice value if OTIF < target (quarterly) for contract orders | AE5: Quarterly | AF5: 2026-01-01 | AH5: Active
A6: SLA_EXPORT_US_T1_D | B6: Export US T1 (DG capable - Direct) | C6: AMER | D6: Export-Direct | E6: ACETYL,DKD | F6: FOB/CIF | G6: 13:00 | H6: Mon-Fri | I6: 3 | J6: 6 | K6: Port (Nhava Sheva) | L6: 18 | M6: 28 | N6: 93 | O6: +/-3 days | P6: 96 | Q6: 95 | R6: 12 | S6: 24 | T6: 12 | U6: COA,Invoice,Packing List,SDS,TSCA statement,BL | V6: 99.3 | W6: 168 | X6: 5 | Y6: 25 | Z6: Ambient | AA6: DG allowed (IMO) | AB6: 10 MT | AC6: ISO20,DR200_UN | AD6: 2% credit on ocean freight component if OTIF < target (quarterly) | AE6: Quarterly | AF6: 2026-01-01 | AH6: Active
A7: SLA_EXPORT_US_T1_P | B7: Export US T1 (Pharma/High Purity) | C7: AMER | D7: Export-Direct | E7: ACETYL | F7: CIP/DDP (case by case) | G7: 12:00 | H7: Mon-Fri | I7: 2 | J7: 4 | K7: Port + Forwarder handoff | L7: 14 | M7: 24 | N7: 95 | O7: +/-2 days | P7: 98 | Q7: 97 | R7: 8 | S7: 16 | T7: 8 | U7: COA,Invoice,Packing List,SDS,TSCA,Allergen/Pharma statement,BL | V7: 99.7 | W7: 120 | X7: 4 | Y7: 18 | Z7: 46061 | AA7: Non-DG preferred | AB7: 5 MT | AC7: DR200_UN,IBC1KL | AD7: Service credit 1% if documentation accuracy < target; OTIF credits per contract | AE7: Monthly | AF7: 2026-01-01 | AH7: Active
A8: SLA_EXPORT_APAC_T1_D | B8: Export APAC T1 (SEA lanes) | C8: APAC | D8: Export-Direct,Distributor | E8: ACETYL,DKD,FLUORO | F8: FOB/CIF | G8: 14:00 | H8: Mon-Fri | I8: 2 | J8: 5 | K8: Port (Nhava Sheva/Mundra) | L8: 10 | M8: 18 | N8: 94 | O8: +/-2 days | P8: 97 | Q8: 96 | R8: 8 | S8: 18 | T8: 8 | U8: COA,Invoice,Packing List,SDS,BL | V8: 99.2 | W8: 96 | X8: 4 | Y8: 15 | Z8: Ambient | AA8: DG allowed (IMO) | AB8: 5 MT | AC8: ISO20,DR200_UN,IBC1KL | AD8: 0.5% credit if OTIF < target (quarterly) for annual contracts | AE8: Quarterly | AF8: 2026-01-01 | AH8: Active
A9: SLA_EXPORT_APAC_T1_P | B9: Export APAC T1 (Powders) | C9: APAC | D9: Export-Direct,Distributor | E9: ARYLIDE,FLUORO | F9: FOB/CIF | G9: 12:00 | H9: Mon-Fri | I9: 3 | J9: 6 | K9: Port (Nhava Sheva/Mundra) | L9: 12 | M9: 20 | N9: 92 | O9: +/-3 days | P9: 96 | Q9: 95 | R9: 10 | S9: 24 | T9: 12 | U9: COA,Invoice,Packing List,SDS,BL | V9: 99 | W9: 120 | X9: 5 | Y9: 20 | Z9: Ambient | AA9: DG where required | AB9: 3 MT | AC9: BAG25,IBC1KL | AD9: No penalties for port delays; credit applies only for documentation failures | AE9: Semi-Annual | AF9: 2026-01-01 | AH9: Active
A10: SLA_EXPORT_ROW_T2_D | B10: Export ROW T2 (DG/Remote - Direct) | C10: MEA | D10: Export-Direct | E10: ACETYL,DKD,FLUORO | F10: FOB/CFR/CIF | G10: 11:00 | H10: Mon-Fri | I10: 4 | J10: 8 | K10: Port (Nhava Sheva) | L10: 20 | M10: 35 | N10: 90 | O10: +/-4 days | P10: 95 | Q10: 94 | R10: 15 | S10: 30 | T10: 12 | U10: COA,Invoice,Packing List,SDS,BL,Legalization (if required) | V10: 98.8 | W10: 240 | X10: 7 | Y10: 30 | Z10: Ambient | AA10: DG allowed (IMO) | AB10: 10 MT | AC10: ISO20,DR200_UN | AD10: Credits capped at 0.5% of invoice; exclusions for force majeure/port congestion | AE10: Annual | AF10: 2026-01-01 | AH10: Active
A11: SLA_EXPORT_ROW_T2_P | B11: Export ROW T2 (Project/Small lots) | C11: MEA | D11: Distributor | E11: ARYLIDE,FLUORO | F11: EXW/FCA/FOB | G11: 10:00 | H11: Mon-Fri | I11: 5 | J11: 10 | K11: Plant gate / Port | L11: 25 | M11: 45 | N11: 90 | O11: +/-5 days | P11: 95 | Q11: 94 | R11: 20 | S11: 36 | T11: 24 | U11: COA,Invoice,Packing List,SDS | V11: 98.5 | W11: 240 | X11: 8 | Y11: 35 | Z11: Ambient | AA11: DG by exception | AB11: 1000 KG | AC11: BAG25,DR200_UN | AD11: No penalties; review service gaps in QBR and agree corrective actions | AE11: Annual | AF11: 2026-01-01 | AG11: 2026-12-31 | AH11: Planned

Sheet Orders
A1: Order ID (Primary Key) | B1: Order Type | C1: Order Date | D1: Customer ID (FK) | E1: To WH ID | F1: Payment Terms | G1: Order Status
A2: ORD202504-0001 | B2: Transfer Order | C2: 2025-04-01 | E2: TNK_EUR_RTM | F2: Advance | G2: Delivered
A3: ORD202504-0002 | B3: Sales Order | C3: 2025-04-02 | D3: CUS0002 | F3: Net 15 | G3: Delivered
A4: ORD202504-0003 | B4: Sales Order | C4: 2025-04-03 | D4: CUS0003 | F4: Net 30 | G4: Delivered
A5: ORD202504-0004 | B5: Sales Order | C5: 2025-04-04 | D5: CUS0004 | F5: Net 45 | G5: Delivered
A6: ORD202504-0005 | B6: Sales Order | C6: 2025-04-05 | D6: CUS0005 | F6: Advance | G6: Delivered
A7: ORD202504-0006 | B7: Sales Order | C7: 2025-04-06 | D7: CUS0006 | F7: Net 15 | G7: Delivered
A8: ORD202504-0007 | B8: Sales Order | C8: 2025-04-07 | D8: CUS0007 | F8: Net 30 | G8: Delivered
A9: ORD202504-0008 | B9: Transfer Order | C9: 2025-04-08 | E9: WH_IN_SOUTH_HYD | F9: Net 45 | G9: Delivered
A10: ORD202504-0009 | B10: Sales Order | C10: 2025-04-09 | D10: CUS0009 | F10: Advance | G10: Delivered
A11: ORD202504-0010 | B11: Sales Order | C11: 2025-04-10 | D11: CUS0010 | F11: Net 15 | G11: Delivered
A12: ORD202504-0011 | B12: Sales Order | C12: 2025-04-11 | D12: CUS0011 | F12: Net 30 | G12: Delivered
A13: ORD202504-0012 | B13: Sales Order | C13: 2025-04-12 | D13: CUS0012 | F13: Net 45 | G13: Delivered
A14: ORD202504-0013 | B14: Sales Order | C14: 2025-04-13 | D14: CUS0013 | F14: Advance | G14: Delivered
A15: ORD202504-0014 | B15: Sales Order | C15: 2025-04-14 | D15: CUS0014 | F15: Net 15 | G15: Delivered
A16: ORD202504-0015 | B16: Transfer Order | C16: 2025-04-15 | E16: TNK_EUR_RTM | F16: Net 30 | G16: Delivered
A17: ORD202504-0016 | B17: Sales Order | C17: 2025-04-16 | D17: CUS0016 | F17: Net 45 | G17: Delivered
A18: ORD202504-0017 | B18: Sales Order | C18: 2025-04-17 | D18: CUS0017 | F18: Advance | G18: Delivered
A19: ORD202504-0018 | B19: Sales Order | C19: 2025-04-18 | D19: CUS0018 | F19: Net 15 | G19: Delivered
A20: ORD202504-0019 | B20: Sales Order | C20: 2025-04-19 | D20: CUS0019 | F20: Net 30 | G20: Delivered
A21: ORD202504-0020 | B21: Sales Order | C21: 2025-04-20 | D21: CUS0020 | F21: Net 45 | G21: Delivered
A22: ORD202504-0021 | B22: Sales Order | C22: 2025-04-21 | D22: CUS0021 | F22: Advance | G22: Delivered
A23: ORD202504-0022 | B23: Transfer Order | C23: 2025-04-22 | E23: WH_IN_SOUTH_HYD | F23: Net 15 | G23: Delivered
A24: ORD202504-0023 | B24: Sales Order | C24: 2025-04-23 | D24: CUS0023 | F24: Net 30 | G24: Delivered
A25: ORD202504-0024 | B25: Sales Order | C25: 2025-04-24 | D25: CUS0024 | F25: Net 45 | G25: Delivered
A26: ORD202504-0025 | B26: Sales Order | C26: 2025-04-25 | D26: CUS0025 | F26: Advance | G26: Delivered
A27: ORD202504-0026 | B27: Sales Order | C27: 2025-04-26 | D27: CUS0026 | F27: Net 15 | G27: Delivered
A28: ORD202504-0027 | B28: Sales Order | C28: 2025-04-27 | D28: CUS0027 | F28: Net 30 | G28: Delivered
A29: ORD202504-0028 | B29: Sales Order | C29: 2025-04-28 | D29: CUS0028 | F29: Net 45 | G29: Delivered
A30: ORD202504-0029 | B30: Transfer Order | C30: 2025-04-29 | E30: TNK_EUR_RTM | F30: Advance | G30: Delivered
A31: ORD202504-0030 | B31: Sales Order | C31: 2025-04-30 | D31: CUS0030 | F31: Net 15 | G31: Delivered
A32: ORD202504-0031 | B32: Sales Order | C32: 2025-04-01 | D32: CUS0031 | F32: Net 30 | G32: Delivered
A33: ORD202504-0032 | B33: Sales Order | C33: 2025-04-02 | D33: CUS0032 | F33: Net 45 | G33: Delivered
A34: ORD202504-0033 | B34: Sales Order | C34: 2025-04-03 | D34: CUS0033 | F34: Advance | G34: Delivered
A35: ORD202504-0034 | B35: Sales Order | C35: 2025-04-04 | D35: CUS0034 | F35: Net 15 | G35: Delivered
A36: ORD202504-0035 | B36: Sales Order | C36: 2025-04-05 | D36: CUS0035 | F36: Net 30 | G36: Delivered
A37: ORD202504-0036 | B37: Transfer Order | C37: 2025-04-06 | E37: WH_IN_SOUTH_HYD | F37: Net 45 | G37: Delivered
A38: ORD202504-0037 | B38: Sales Order | C38: 2025-04-07 | D38: CUS0037 | F38: Advance | G38: Delivered
A39: ORD202504-0038 | B39: Sales Order | C39: 2025-04-08 | D39: CUS0038 | F39: Net 15 | G39: Delivered
A40: ORD202504-0039 | B40: Sales Order | C40: 2025-04-09 | D40: CUS0039 | F40: Net 30 | G40: Delivered
A41: ORD202504-0040 | B41: Sales Order | C41: 2025-04-10 | D41: CUS0040 | F41: Net 45 | G41: Delivered
A42: ORD202504-0041 | B42: Sales Order | C42: 2025-04-11 | D42: CUS0041 | F42: Advance | G42: Delivered
A43: ORD202504-0042 | B43: Sales Order | C43: 2025-04-12 | D43: CUS0042 | F43: Net 15 | G43: Delivered
A44: ORD202504-0043 | B44: Transfer Order | C44: 2025-04-13 | E44: TNK_EUR_RTM | F44: Net 30 | G44: Delivered
A45: ORD202504-0044 | B45: Sales Order | C45: 2025-04-14 | D45: CUS0044 | F45: Net 45 | G45: Delivered
A46: ORD202504-0045 | B46: Sales Order | C46: 2025-04-15 | D46: CUS0045 | F46: Advance | G46: Delivered
A47: ORD202504-0046 | B47: Sales Order | C47: 2025-04-16 | D47: CUS0046 | F47: Net 15 | G47: Delivered
A48: ORD202504-0047 | B48: Sales Order | C48: 2025-04-17 | D48: CUS0047 | F48: Net 30 | G48: Delivered
A49: ORD202504-0048 | B49: Sales Order | C49: 2025-04-18 | D49: CUS0048 | F49: Net 45 | G49: Delivered
A50: ORD202504-0049 | B50: Sales Order | C50: 2025-04-19 | D50: CUS0049 | F50: Advance | G50: Delivered
A51: ORD202504-0050 | B51: Transfer Order | C51: 2025-04-20 | E51: WH_IN_SOUTH_HYD | F51: Net 15 | G51: Delivered
A52: ORD202504-0051 | B52: Sales Order | C52: 2025-04-21 | D52: CUS0051 | F52: Net 30 | G52: Delivered
A53: ORD202504-0052 | B53: Sales Order | C53: 2025-04-22 | D53: CUS0052 | F53: Net 45 | G53: Delivered
A54: ORD202504-0053 | B54: Sales Order | C54: 2025-04-23 | D54: CUS0053 | F54: Advance | G54: Delivered
A55: ORD202504-0054 | B55: Sales Order | C55: 2025-04-24 | D55: CUS0054 | F55: Net 15 | G55: Delivered
A56: ORD202504-0055 | B56: Sales Order | C56: 2025-04-25 | D56: CUS0055 | F56: Net 30 | G56: Delivered
A57: ORD202504-0056 | B57: Sales Order | C57: 2025-04-26 | D57: CUS0056 | F57: Net 45 | G57: Delivered
A58: ORD202504-0057 | B58: Transfer Order | C58: 2025-04-27 | E58: TNK_EUR_RTM | F58: Advance | G58: Delivered
A59: ORD202504-0058 | B59: Sales Order | C59: 2025-04-28 | D59: CUS0058 | F59: Net 15 | G59: Delivered
A60: ORD202504-0059 | B60: Sales Order | C60: 2025-04-29 | D60: CUS0059 | F60: Net 30 | G60: Delivered
A61: ORD202504-0060 | B61: Sales Order | C61: 2025-04-30 | D61: CUS0060 | F61: Net 45 | G61: Delivered
A62: ORD202504-0061 | B62: Sales Order | C62: 2025-04-01 | D62: CUS0061 | F62: Advance | G62: Delivered
A63: ORD202504-0062 | B63: Sales Order | C63: 2025-04-02 | D63: CUS0062 | F63: Net 15 | G63: Delivered
A64: ORD202504-0063 | B64: Sales Order | C64: 2025-04-03 | D64: CUS0063 | F64: Net 30 | G64: Delivered
A65: ORD202504-0064 | B65: Transfer Order | C65: 2025-04-04 | E65: WH_IN_SOUTH_HYD | F65: Net 45 | G65: Delivered
A66: ORD202504-0065 | B66: Sales Order | C66: 2025-04-05 | D66: CUS0065 | F66: Advance | G66: Delivered
A67: ORD202504-0066 | B67: Sales Order | C67: 2025-04-06 | D67: CUS0066 | F67: Net 15 | G67: Delivered
A68: ORD202504-0067 | B68: Sales Order | C68: 2025-04-07 | D68: CUS0067 | F68: Net 30 | G68: Delivered
A69: ORD202504-0068 | B69: Sales Order | C69: 2025-04-08 | D69: CUS0068 | F69: Net 45 | G69: Delivered
A70: ORD202504-0069 | B70: Sales Order | C70: 2025-04-09 | D70: CUS0069 | F70: Advance | G70: Delivered
A71: ORD202504-0070 | B71: Sales Order | C71: 2025-04-10 | D71: CUS0070 | F71: Net 15 | G71: Delivered
A72: ORD202504-0071 | B72: Transfer Order | C72: 2025-04-11 | E72: TNK_EUR_RTM | F72: Net 30 | G72: Delivered
A73: ORD202504-0072 | B73: Sales Order | C73: 2025-04-12 | D73: CUS0072 | F73: Net 45 | G73: Delivered
A74: ORD202504-0073 | B74: Sales Order | C74: 2025-04-13 | D74: CUS0073 | F74: Advance | G74: Delivered
A75: ORD202504-0074 | B75: Sales Order | C75: 2025-04-14 | D75: CUS0074 | F75: Net 15 | G75: Delivered
A76: ORD202504-0075 | B76: Sales Order | C76: 2025-04-15 | D76: CUS0075 | F76: Net 30 | G76: Delivered
A77: ORD202504-0076 | B77: Sales Order | C77: 2025-04-16 | D77: CUS0076 | F77: Net 45 | G77: Delivered
A78: ORD202504-0077 | B78: Sales Order | C78: 2025-04-17 | D78: CUS0077 | F78: Advance | G78: Delivered
A79: ORD202504-0078 | B79: Transfer Order | C79: 2025-04-18 | E79: WH_IN_SOUTH_HYD | F79: Net 15 | G79: Delivered
A80: ORD202504-0079 | B80: Sales Order | C80: 2025-04-19 | D80: CUS0079 | F80: Net 30 | G80: Delivered
A81: ORD202504-0080 | B81: Sales Order | C81: 2025-04-20 | D81: CUS0080 | F81: Net 45 | G81: Delivered
A82: ORD202504-0081 | B82: Sales Order | C82: 2025-04-21 | D82: CUS0081 | F82: Advance | G82: Delivered
A83: ORD202504-0082 | B83: Sales Order | C83: 2025-04-22 | D83: CUS0082 | F83: Net 15 | G83: Delivered
A84: ORD202504-0083 | B84: Sales Order | C84: 2025-04-23 | D84: CUS0083 | F84: Net 30 | G84: Delivered
A85: ORD202504-0084 | B85: Sales Order | C85: 2025-04-24 | D85: CUS0084 | F85: Net 45 | G85: Delivered
A86: ORD202504-0085 | B86: Transfer Order | C86: 2025-04-25 | E86: TNK_EUR_RTM | F86: Advance | G86: Delivered
A87: ORD202504-0086 | B87: Sales Order | C87: 2025-04-26 | D87: CUS0086 | F87: Net 15 | G87: Delivered
A88: ORD202504-0087 | B88: Sales Order | C88: 2025-04-27 | D88: CUS0087 | F88: Net 30 | G88: Delivered
A89: ORD202504-0088 | B89: Sales Order | C89: 2025-04-28 | D89: CUS0088 | F89: Net 45 | G89: Delivered
A90: ORD202504-0089 | B90: Sales Order | C90: 2025-04-29 | D90: CUS0089 | F90: Advance | G90: Delivered
A91: ORD202504-0090 | B91: Sales Order | C91: 2025-04-30 | D91: CUS0090 | F91: Net 15 | G91: Delivered
A92: ORD202504-0091 | B92: Sales Order | C92: 2025-04-01 | D92: CUS0091 | F92: Net 30 | G92: Delivered
A93: ORD202504-0092 | B93: Transfer Order | C93: 2025-04-02 | E93: WH_IN_SOUTH_HYD | F93: Net 45 | G93: Delivered
A94: ORD202504-0093 | B94: Sales Order | C94: 2025-04-03 | D94: CUS0093 | F94: Advance | G94: Delivered
A95: ORD202504-0094 | B95: Sales Order | C95: 2025-04-04 | D95: CUS0094 | F95: Net 15 | G95: Delivered
A96: ORD202504-0095 | B96: Sales Order | C96: 2025-04-05 | D96: CUS0095 | F96: Net 30 | G96: Delivered
A97: ORD202504-0096 | B97: Sales Order | C97: 2025-04-06 | D97: CUS0096 | F97: Net 45 | G97: Delivered
A98: ORD202504-0097 | B98: Sales Order | C98: 2025-04-07 | D98: CUS0097 | F98: Advance | G98: Delivered
A99: ORD202504-0098 | B99: Sales Order | C99: 2025-04-08 | D99: CUS0098 | F99: Net 15 | G99: Delivered
A100: ORD202504-0099 | B100: Transfer Order | C100: 2025-04-09 | E100: TNK_EUR_RTM | F100: Net 30 | G100: Delivered
...

Sheet Order_Line Items
A1: Order Line Item (Primary Key) | B1: Order_id (FK) | C1: SLA Profile ID (FK) | D1: Delivery_by_date | E1: Requirement Status | F1: Fulfilled by WH ID (WH ID FK) | G1: SKU ID (FK) | H1: Quantity | I1: Unit Price (USD) | J1: Value (USD) | K1: Forecast ID (FK)
A2: OLI202504-0001 | B2: ORD202504-0001 | C2: SLA_STD_DOM_T1 | D2: 2025-04-08 | E2: Fulfilled | F2: TNK_EUR_RTM | G2: ESS-ACETYL-ETHACE-LM-98.5-NEAT-BULK-DST | H2: 21 | I2: 1000 | J2: 21000 | K2: FC202504-DOM-ACETYL
A3: OLI202504-0002 | B3: ORD202504-0002 | C3: SLA_STD_DOM_T2 | D3: 2025-04-10 | E3: Fulfilled | F3: TNK_EUR_ANT | G3: ESS-ACETYL-ETHACE-LM-98.5-NEAT-BULK-DST | H3: 22 | I3: 1001 | J3: 22022 | K3: FC202504-EU-DKD
A4: OLI202504-0003 | B4: ORD202504-0003 | C4: SLA_STD_DOM_T3 | D4: 2025-04-12 | E4: Fulfilled | F4: TNK_EUR_GEN | G4: ESS-ACETYL-ETHACE-LM-98.5-NEAT-BULK-DST | H4: 23 | I4: 1002 | J4: 23046 | K4: FC202504-AMER-ARYLIDE
A5: OLI202504-0004 | B5: ORD202504-0004 | C5: SLA_EXPORT_EU_T1 | D5: 2025-04-14 | E5: Fulfilled | F5: WH_EU_DEU_HAM | G5: SPI-ACETYL-ACEANH-PH-98.6-NEAT-DR200_UN-MHD | H5: 24 | I5: 1003 | J5: 24072 | K5: FC202504-APAC-FLUORO
A6: OLI202504-0005 | B6: ORD202504-0005 | C6: SLA_EXPORT_US_T1_D | D6: 2025-04-16 | E6: Fulfilled | F6: CFS_IN_NHAV | G6: SPI-ACETYL-ACEANH-PH-98.6-NEAT-DR200_UN-MHD | H6: 25 | I6: 1004 | J6: 25100 | K6: FC202504-MEA-ACETYL
A7: OLI202504-0006 | B7: ORD202504-0006 | C7: SLA_EXPORT_US_T1_P | D7: 2025-04-18 | E7: Fulfilled | F7: WH_IN_WEST_BHI | G7: SPI-ACETYL-ACEANH-PH-98.6-NEAT-DR200_UN-MHD | H7: 26 | I7: 1005 | J7: 26130 | K7: FC202504-ROW-DKD
A8: OLI202504-0007 | B8: ORD202504-0007 | C8: SLA_EXPORT_APAC_T1_D | D8: 2025-04-20 | E8: Fulfilled | F8: WH_IN_GUJ_AHD | G8: SPI-ACETYL-ACE-IND-98.4-NEAT-ISO20-LTE | H8: 27 | I8: 1006 | J8: 27162 | K8: FC202504-DOM-ARYLIDE
A9: OLI202504-0008 | B9: ORD202504-0008 | C9: SLA_EXPORT_APAC_T1_P | D9: 2025-04-22 | E9: Fulfilled | F9: WH_IN_SOUTH_HYD | G9: SPI-ACETYL-ACE-IND-98.4-NEAT-ISO20-LTE | H9: 28 | I9: 1007 | J9: 28196 | K9: FC202504-EU-FLUORO
A10: OLI202504-0009 | B10: ORD202504-0009 | C10: SLA_EXPORT_ROW_T2_D | D10: 2025-04-24 | E10: Fulfilled | F10: WH_IN_NORTH_BAW | G10: SPI-ACETYL-ACE-IND-98.4-NEAT-ISO20-LTE | H10: 29 | I10: 1008 | J10: 29232 | K10: FC202504-AMER-ACETYL
A11: OLI202504-0010 | B11: ORD202504-0010 | C11: SLA_EXPORT_ROW_T2_P | D11: 2025-04-26 | E11: Fulfilled | F11: WH_IN_EAST_KOL | G11: ESS-ACETYL-BUTACE-TECH-98.3-NEAT-DR200-DHJ | H11: 30 | I11: 1009 | J11: 30270 | K11: FC202504-APAC-DKD
A12: OLI202504-0011 | B12: ORD202504-0011 | C12: SLA_STD_DOM_T1 | D12: 2025-04-28 | E12: Fulfilled | F12: WH_US_EAST_NJ | G12: ESS-ACETYL-BUTACE-TECH-98.3-NEAT-DR200-DHJ | H12: 31 | I12: 1010 | J12: 31310 | K12: FC202504-MEA-ARYLIDE
A13: OLI202504-0012 | B13: ORD202504-0012 | C13: SLA_STD_DOM_T2 | D13: 2025-04-28 | E13: Fulfilled | F13: WH_US_MID_CHI | G13: ESS-ACETYL-BUTACE-TECH-98.3-NEAT-DR200-DHJ | H13: 32 | I13: 1011 | J13: 32352 | K13: FC202504-ROW-FLUORO
... A217: OLI202504-0216 | B217: ORD202504-0036 | C217: SLA_EXPORT_US_T1_P | D217: 2025-04-18 | E217: Fulfilled | F217: WH_IN_WEST_BHI | G217: ESS-ACETYL-ACEANH-PH-99.7-NEAT-ISO20-DHJ | H217: 55 | I217: 1215 | J217: 66825 | K217: FC202504-ROW-FLUORO
A218: OLI202505-0217 | B218: ORD202505-0001 | C218: SLA_STD_DOM_T1 | D218: 45785 | E218: Fulfilled | F218: TNK_EUR_RTM | G218: ESS-ACETYL-ETHACE-LM-98.5-NEAT-BULK-DST | H218: 56 | I218: 1000 | J218: 56000 | K218: FC202505-DOM-ACETYL
A219: OLI202505-0218 | B219: ORD202505-0002 | C219: SLA_STD_DOM_T2 | D219: 45787 | E219: Fulfilled | F219: TNK_EUR_ANT | G219: ESS-ACETYL-ETHACE-LM-98.5-NEAT-BULK-DST | H219: 57 | I219: 1001 | J219: 57057 | K219: FC202505-EU-DKD
A220: OLI202505-0219 | B220: ORD202505-0003 | C220: SLA_STD_DOM_T3 | D220: 45789 | E220: Fulfilled | F220: TNK_EUR_GEN | G220: ESS-ACETYL-ETHACE-LM-98.5-NEAT-BULK-DST | H220: 58 | I220: 1002 | J220: 58116 | K220: FC202505-AMER-ARYLIDE
A221: OLI202505-0220 | B221: ORD202505-0004 | C221: SLA_EXPORT_EU_T1 | D221: 45791 | E221: Fulfilled | F221: WH_EU_DEU_HAM | G221: SPI-ACETYL-ACEANH-PH-98.6-NEAT-DR200_UN-MHD | H221: 59 | I221: 1003 | J221: 59177 | K221: FC202505-APAC-FLUORO
A222: OLI202505-0221 | B222: ORD202505-0005 | C222: SLA_EXPORT_US_T1_D | D222: 45793 | E222: Fulfilled | F222: CFS_IN_NHAV | G222: SPI-ACETYL-ACEANH-PH-98.6-NEAT-DR200_UN-MHD | H222: 60 | I222: 1004 | J222: 60240 | K222: FC202505-MEA-ACETYL
A223: OLI202505-0222 | B223: ORD202505-0006 | C223: SLA_EXPORT_US_T1_P | D223: 45795 | E223: Fulfilled | F223: WH_IN_WEST_BHI | G223: SPI-ACETYL-ACEANH-PH-98.6-NEAT-DR200_UN-MHD | H223: 61 | I223: 1005 | J223: 61305 | K223: FC202505-ROW-DKD
A224: OLI202505-0223 | B224: ORD202505-0007 | C224: SLA_EXPORT_APAC_T1_D | D224: 45797 | E224: Fulfilled | F224: WH_IN_GUJ_AHD | G224: SPI-ACETYL-ACE-IND-98.4-NEAT-ISO20-LTE | H224: 62 | I224: 1006 | J224: 62372 | K224: FC202505-DOM-ARYLIDE
A225: OLI202505-0224 | B225: ORD202505-0008 | C225: SLA_EXPORT_APAC_T1_P | D225: 45799 | E225: Fulfilled | F225: WH_IN_SOUTH_HYD | G225: SPI-ACETYL-ACE-IND-98.4-NEAT-ISO20-LTE | H225: 63 | I225: 1007 | J225: 63441 | K225: FC202505-EU-FLUORO
A226: OLI202505-0225 | B226: ORD202505-0009 | C226: SLA_EXPORT_ROW_T2_D | D226: 45801 | E226: Fulfilled | F226: WH_IN_NORTH_BAW | G226: SPI-ACETYL-ACE-IND-98.4-NEAT-ISO20-LTE | H226: 64 | I226: 1008 | J226: 64512 | K226: FC202505-AMER-ACETYL
A227: OLI202505-0226 | B227: ORD202505-0010 | C227: SLA_EXPORT_ROW_T2_P | D227: 45803 | E227: Fulfilled | F227: WH_IN_EAST_KOL | G227: ESS-ACETYL-BUTACE-TECH-98.3-NEAT-DR200-DHJ | H227: 65 | I227: 1009 | J227: 65585 | K227: FC202505-APAC-DKD
A228: OLI202505-0227 | B228: ORD202505-0011 | C228: SLA_STD_DOM_T1 | D228: 45805 | E228: Fulfilled | F228: WH_US_EAST_NJ | G228: ESS-ACETYL-BUTACE-TECH-98.3-NEAT-DR200-DHJ | H228: 66 | I228: 1010 | J228: 66660 | K228: FC202505-MEA-ARYLIDE
A229: OLI202505-0228 | B229: ORD202505-0012 | C229: SLA_STD_DOM_T2 | D229: 45805 | E229: Fulfilled | F229: WH_US_MID_CHI | G229: ESS-ACETYL-BUTACE-TECH-98.3-NEAT-DR200-DHJ | H229: 67 | I229: 1011 | J229: 67737 | K229: FC202505-ROW-FLUORO
... A2593: OLI202603-2592 | B2593: ORD202603-0036 | C2593: SLA_EXPORT_US_T1_P | D2593: 46123 | E2593: Pending | F2593: WH_IN_WEST_BHI | G2593: ESS-ACETYL-ACEANH-PH-99.7-NEAT-ISO20-DHJ | H2593: 78 | I2593: 1215 | J2593: 94770 | K2593: FC202603-ROW-FLUORO

Sheet Signals
A1: Signal ID (Primary Key) | B1: Source | C1: Topic headline | D1: Description | E1: Sentiment Score | F1: Confidence | G1: Detected On_Date | H1: Signal Type | I1: Forecast ID (FK) | J1: Exception ID (FK)
A2: SIG202504-0001 | B2: News (ICIS) | C2: European ethanol tightness lifts solvent feedstock costs | D2: European ethanol tightness lifts solvent feedstock costs. Monitor and adjust ACETYL planning accordingly. | E2: -0.30 | F2: 0.65 | G2: 45748 | H2: forecast input | I2: FC202504-DOM-ACETYL
A3: SIG202504-0002 | B3: Finance note (FX/credit) | C3: INR volatility may impact import cost for methacrylic acid | D3: INR volatility may impact import cost for methacrylic acid. Monitor and adjust DKD planning accordingly. | E3: -0.15 | F3: 0.73 | G3: 45755 | H3: forecast input | I3: FC202504-EU-DKD
A4: SIG202504-0003 | B4: Internal memo (Plant Ops) | C4: Plant running stable at higher throughputs | D4: Plant running stable at higher throughputs. Monitor and adjust ARYLIDE planning accordingly. | E4: 0.00 | F4: 0.81 | G4: 45762 | H4: forecast input | I4: FC202504-AMER-ARYLIDE
A5: SIG202504-0004 | B5: LSP bulletin | C5: Port congestion warning for DG containers | D5: Port congestion warning for DG containers. Monitor and adjust FLUORO planning accordingly. | E5: 0.15 | F5: 0.89 | G5: 45769 | H5: exception | J5: EXC202504-0001
A6: SIG202505-0005 | B6: News (ICIS) | C6: Customer requests additional packaging availability | D6: Customer requests additional packaging availability. Monitor and adjust ACETYL planning accordingly. | E6: -0.30 | F6: 0.65 | G6: 45778 | H6: forecast input | I6: FC202505-DOM-ACETYL
A7: SIG202505-0006 | B7: Finance note (FX/credit) | C7: Freight rates soften on Asia-Europe lane | D7: Freight rates soften on Asia-Europe lane. Monitor and adjust DKD planning accordingly. | E7: -0.15 | F7: 0.73 | G7: 45785 | H7: forecast input | I7: FC202505-EU-DKD
A8: SIG202505-0007 | B8: Internal memo (Plant Ops) | C8: Distributor asking for extended credit | D8: Distributor asking for extended credit. Monitor and adjust ARYLIDE planning accordingly. | E8: 0.00 | F8: 0.81 | G8: 45792 | H8: forecast input | I8: FC202505-AMER-ARYLIDE
A9: SIG202505-0008 | B9: LSP bulletin | C9: Acetic acid spot prices firm on maintenance | D9: Acetic acid spot prices firm on maintenance. Monitor and adjust FLUORO planning accordingly. | E9: 0.15 | F9: 0.89 | G9: 45799 | H9: exception | J9: EXC202505-0005
A10: SIG202506-0009 | B10: News (ICIS) | C10: Scheduling constraint for DG packaging | D10: Scheduling constraint for DG packaging. Monitor and adjust ACETYL planning accordingly. | E10: -0.30 | F10: 0.65 | G10: 45809 | H10: forecast input | I10: FC202506-DOM-ACETYL
A11: SIG202506-0010 | B11: Finance note (FX/credit) | C11: Supply chain disruption alert | D11: Supply chain disruption alert. Monitor and adjust DKD planning accordingly. | E11: -0.15 | F11: 0.73 | G11: 45816 | H11: forecast input | I11: FC202506-EU-DKD
A12: SIG202506-0011 | B12: Internal memo (Plant Ops) | C12: European ethanol tightness lifts solvent feedstock costs | D12: European ethanol tightness lifts solvent feedstock costs. Monitor and adjust ARYLIDE planning accordingly. | E12: 0.00 | F12: 0.81 | G12: 45823 | H12: forecast input | I12: FC202506-AMER-ARYLIDE
A13: SIG202506-0012 | B13: LSP bulletin | C13: INR volatility may impact import cost for methacrylic acid | D13: INR volatility may impact import cost for methacrylic acid. Monitor and adjust FLUORO planning accordingly. | E13: 0.15 | F13: 0.89 | G13: 45830 | H13: exception | J13: EXC202506-0008
A14: SIG202507-0013 | B14: News (ICIS) | C14: Plant running stable at higher throughputs | D14: Plant running stable at higher throughputs. Monitor and adjust ACETYL planning accordingly. | E14: -0.30 | F14: 0.65 | G14: 45839 | H14: forecast input | I14: FC202507-DOM-ACETYL
A15: SIG202507-0014 | B15: Finance note (FX/credit) | C15: Port congestion warning for DG containers | D15: Port congestion warning for DG containers. Monitor and adjust DKD planning accordingly. | E15: -0.15 | F15: 0.73 | G15: 45846 | H15: forecast input | I15: FC202507-EU-DKD
A16: SIG202507-0015 | B16: Internal memo (Plant Ops) | C16: Customer requests additional packaging availability | D16: Customer requests additional packaging availability. Monitor and adjust ARYLIDE planning accordingly. | E16: 0.00 | F16: 0.81 | G16: 45853 | H16: forecast input | I16: FC202507-AMER-ARYLIDE
A17: SIG202507-0016 | B17: LSP bulletin | C17: Freight rates soften on Asia-Europe lane | D17: Freight rates soften on Asia-Europe lane. Monitor and adjust FLUORO planning accordingly. | E17: 0.15 | F17: 0.89 | G17: 45860 | H17: exception | J17: EXC202507-0013
A18: SIG202508-0017 | B18: News (ICIS) | C18: Distributor asking for extended credit | D18: Distributor asking for extended credit. Monitor and adjust ACETYL planning accordingly. | E18: -0.30 | F18: 0.65 | G18: 45870 | H18: forecast input | I18: FC202508-DOM-ACETYL
A19: SIG202508-0018 | B19: Finance note (FX/credit) | C19: Acetic acid spot prices firm on maintenance | D19: Acetic acid spot prices firm on maintenance. Monitor and adjust DKD planning accordingly. | E19: -0.15 | F19: 0.73 | G19: 45877 | H19: forecast input | I19: FC202508-EU-DKD
A20: SIG202508-0019 | B20: Internal memo (Plant Ops) | C20: Scheduling constraint for DG packaging | D20: Scheduling constraint for DG packaging. Monitor and adjust ARYLIDE planning accordingly. | E20: 0.00 | F20: 0.81 | G20: 45884 | H20: forecast input | I20: FC202508-AMER-ARYLIDE
A21: SIG202508-0020 | B21: LSP bulletin | C21: Supply chain disruption alert | D21: Supply chain disruption alert. Monitor and adjust FLUORO planning accordingly. | E21: 0.15 | F21: 0.89 | G21: 45891 | H21: exception | J21: EXC202508-0016
A22: SIG202509-0021 | B22: News (ICIS) | C22: European ethanol tightness lifts solvent feedstock costs | D22: European ethanol tightness lifts solvent feedstock costs. Monitor and adjust ACETYL planning accordingly. | E22: -0.30 | F22: 0.65 | G22: 45901 | H22: forecast input | I22: FC202509-DOM-ACETYL
A23: SIG202509-0022 | B23: Finance note (FX/credit) | C23: INR volatility may impact import cost for methacrylic acid | D23: INR volatility may impact import cost for methacrylic acid. Monitor and adjust DKD planning accordingly. | E23: -0.15 | F23: 0.73 | G23: 45908 | H23: forecast input | I23: FC202509-EU-DKD
A24: SIG202509-0023 | B24: Internal memo (Plant Ops) | C24: Plant running stable at higher throughputs | D24: Plant running stable at higher throughputs. Monitor and adjust ARYLIDE planning accordingly. | E24: 0.00 | F24: 0.81 | G24: 45915 | H24: forecast input | I24: FC202509-AMER-ARYLIDE
A25: SIG202509-0024 | B25: LSP bulletin | C25: Port congestion warning for DG containers | D25: Port congestion warning for DG containers. Monitor and adjust FLUORO planning accordingly. | E25: 0.15 | F25: 0.89 | G25: 45922 | H25: exception | J25: EXC202509-0019
A26: SIG202510-0025 | B26: News (ICIS) | C26: Customer requests additional packaging availability | D26: Customer requests additional packaging availability. Monitor and adjust ACETYL planning accordingly. | E26: -0.30 | F26: 0.65 | G26: 45931 | H26: forecast input | I26: FC202510-DOM-ACETYL
A27: SIG202510-0026 | B27: Finance note (FX/credit) | C27: Freight rates soften on Asia-Europe lane | D27: Freight rates soften on Asia-Europe lane. Monitor and adjust DKD planning accordingly. | E27: -0.15 | F27: 0.73 | G27: 45938 | H27: forecast input | I27: FC202510-EU-DKD
A28: SIG202510-0027 | B28: Internal memo (Plant Ops) | C28: Distributor asking for extended credit | D28: Distributor asking for extended credit. Monitor and adjust ARYLIDE planning accordingly. | E28: 0.00 | F28: 0.81 | G28: 45945 | H28: forecast input | I28: FC202510-AMER-ARYLIDE
A29: SIG202510-0028 | B29: LSP bulletin | C29: Acetic acid spot prices firm on maintenance | D29: Acetic acid spot prices firm on maintenance. Monitor and adjust FLUORO planning accordingly. | E29: 0.15 | F29: 0.89 | G29: 45952 | H29: exception | J29: EXC202510-0022
A30: SIG202511-0029 | B30: News (ICIS) | C30: Scheduling constraint for DG packaging | D30: Scheduling constraint for DG packaging. Monitor and adjust ACETYL planning accordingly. | E30: -0.30 | F30: 0.65 | G30: 45962 | H30: forecast input | I30: FC202511-DOM-ACETYL
A31: SIG202511-0030 | B31: Finance note (FX/credit) | C31: Supply chain disruption alert | D31: Supply chain disruption alert. Monitor and adjust DKD planning accordingly. | E31: -0.15 | F31: 0.73 | G31: 45969 | H31: forecast input | I31: FC202511-EU-DKD
A32: SIG202511-0031 | B32: Internal memo (Plant Ops) | C32: European ethanol tightness lifts solvent feedstock costs | D32: European ethanol tightness lifts solvent feedstock costs. Monitor and adjust ARYLIDE planning accordingly. | E32: 0.00 | F32: 0.81 | G32: 45976 | H32: forecast input | I32: FC202511-AMER-ARYLIDE
A33: SIG202511-0032 | B33: LSP bulletin | C33: INR volatility may impact import cost for methacrylic acid | D33: INR volatility may impact import cost for methacrylic acid. Monitor and adjust FLUORO planning accordingly. | E33: 0.15 | F33: 0.89 | G33: 45983 | H33: exception | J33: EXC202511-0025
A34: SIG202512-0033 | B34: News (ICIS) | C34: Plant running stable at higher throughputs | D34: Plant running stable at higher throughputs. Monitor and adjust ACETYL planning accordingly. | E34: -0.30 | F34: 0.65 | G34: 45992 | H34: forecast input | I34: FC202512-DOM-ACETYL
A35: SIG202512-0034 | B35: Finance note (FX/credit) | C35: Port congestion warning for DG containers | D35: Port congestion warning for DG containers. Monitor and adjust DKD planning accordingly. | E35: -0.15 | F35: 0.73 | G35: 45999 | H35: forecast input | I35: FC202512-EU-DKD
A36: SIG202512-0035 | B36: Internal memo (Plant Ops) | C36: Customer requests additional packaging availability | D36: Customer requests additional packaging availability. Monitor and adjust ARYLIDE planning accordingly. | E36: 0.00 | F36: 0.81 | G36: 46006 | H36: forecast input | I36: FC202512-AMER-ARYLIDE
A37: SIG202512-0036 | B37: LSP bulletin | C37: Freight rates soften on Asia-Europe lane | D37: Freight rates soften on Asia-Europe lane. Monitor and adjust FLUORO planning accordingly. | E37: 0.15 | F37: 0.89 | G37: 46013 | H37: exception | J37: EXC202512-0030
A38: SIG202601-0037 | B38: News (ICIS) | C38: Distributor asking for extended credit | D38: Distributor asking for extended credit. Monitor and adjust ACETYL planning accordingly. | E38: -0.30 | F38: 0.65 | G38: 46023 | H38: forecast input | I38: FC202601-DOM-ACETYL
A39: SIG202601-0038 | B39: Finance note (FX/credit) | C39: Acetic acid spot prices firm on maintenance | D39: Acetic acid spot prices firm on maintenance. Monitor and adjust DKD planning accordingly. | E39: -0.15 | F39: 0.73 | G39: 46030 | H39: forecast input | I39: FC202601-EU-DKD
A40: SIG202601-0039 | B40: Internal memo (Plant Ops) | C40: Scheduling constraint for DG packaging | D40: Scheduling constraint for DG packaging. Monitor and adjust ARYLIDE planning accordingly. | E40: 0.00 | F40: 0.81 | G40: 46037 | H40: forecast input | I40: FC202601-AMER-ARYLIDE
A41: SIG202601-0040 | B41: LSP bulletin | C41: Supply chain disruption alert | D41: Supply chain disruption alert. Monitor and adjust FLUORO planning accordingly. | E41: 0.15 | F41: 0.89 | G41: 46044 | H41: exception | J41: EXC202601-0033
A42: SIG202602-0041 | B42: News (ICIS) | C42: European ethanol tightness lifts solvent feedstock costs | D42: European ethanol tightness lifts solvent feedstock costs. Monitor and adjust ACETYL planning accordingly. | E42: -0.3 | F42: 0.65 | G42: 46054 | H42: forecast input | I42: FC202602-DOM-ACETYL
A43: SIG202602-0042 | B43: Finance note (FX/credit) | C43: INR volatility may impact import cost for methacrylic acid | D43: INR volatility may impact import cost for methacrylic acid. Monitor and adjust DKD planning accordingly. | E43: -0.15 | F43: 0.73 | G43: 46061 | H43: forecast input | I43: FC202602-EU-DKD
A44: SIG202602-0043 | B44: Internal memo (Plant Ops) | C44: Plant running stable at higher throughputs | D44: Plant running stable at higher throughputs. Monitor and adjust ARYLIDE planning accordingly. | E44: 0 | F44: 0.81 | G44: 46068 | H44: forecast input | I44: FC202602-AMER-ARYLIDE
A45: SIG202602-0044 | B45: LSP bulletin | C45: Port congestion warning for DG containers | D45: Port congestion warning for DG containers. Monitor and adjust FLUORO planning accordingly. | E45: 0.15 | F45: 0.89 | G45: 46075 | H45: exception | J45: EXC202602-0037
A46: SIG202603-0045 | B46: News (ICIS) | C46: Customer requests additional packaging availability | D46: Customer requests additional packaging availability. Monitor and adjust ACETYL planning accordingly. | E46: -0.3 | F46: 0.65 | G46: 46082 | H46: forecast input | I46: FC202603-DOM-ACETYL
A47: SIG202603-0046 | B47: Finance note (FX/credit) | C47: Freight rates soften on Asia-Europe lane | D47: Freight rates soften on Asia-Europe lane. Monitor and adjust DKD planning accordingly. | E47: -0.15 | F47: 0.73 | G47: 46089 | H47: forecast input | I47: FC202603-EU-DKD
A48: SIG202603-0047 | B48: Internal memo (Plant Ops) | C48: Distributor asking for extended credit | D48: Distributor asking for extended credit. Monitor and adjust ARYLIDE planning accordingly. | E48: 0 | F48: 0.81 | G48: 46096 | H48: forecast input | I48: FC202603-AMER-ARYLIDE
A49: SIG202603-0048 | B49: LSP bulletin | C49: Acetic acid spot prices firm on maintenance | D49: Acetic acid spot prices firm on maintenance. Monitor and adjust FLUORO planning accordingly. | E49: 0.15 | F49: 0.89 | G49: 46103 | H49: exception | J49: EXC202603-0044

Sheet Forecasts
A1: Forecast ID (Primary Key) | B1: Demand Region ID (FK) | C1: Forecast Date | D1: Forecast Horizon | E1: Product Family | F1: Quantity | G1: hould no | H1: Market | I1: Start of period | J1: Duration | K1: Business unit | L1: Product family | M1: Product Sub-group (molecule_name) | N1: Variant (grade) | O1: SKU
A2: FC202504-DOM-ACETYL | B2: DOM | C2: 45777 | D2: Monthly | E2: ACETYL | F2: 5280 | G2: SOP202504-DOM
A3: FC202504-DOM-DKD | B3: DOM | C3: 45777 | D3: Monthly | E3: DKD | F3: 4656 | G3: SOP202504-DOM
A4: FC202504-DOM-ARYLIDE | B4: DOM | C4: 45777 | D4: Monthly | E4: ARYLIDE | F4: 2744 | G4: SOP202504-DOM
A5: FC202504-DOM-FLUORO | B5: DOM | C5: 45777 | D5: Monthly | E5: FLUORO | F5: 1485 | G5: SOP202504-DOM
A6: FC202504-EU-ACETYL | B6: EU | C6: 45777 | D6: Monthly | E6: ACETYL | F6: 5500 | G6: SOP202504-EU
A7: FC202504-EU-DKD | B7: EU | C7: 45777 | D7: Monthly | E7: DKD | F7: 4848 | G7: SOP202504-EU
A8: FC202504-EU-ARYLIDE | B8: EU | C8: 45777 | D8: Monthly | E8: ARYLIDE | F8: 2856 | G8: SOP202504-EU
A9: FC202504-EU-FLUORO | B9: EU | C9: 45777 | D9: Monthly | E9: FLUORO | F9: 1545 | G9: SOP202504-EU
A10: FC202504-AMER-ACETYL | B10: AMER | C10: 45777 | D10: Monthly | E10: ACETYL | F10: 5720 | G10: SOP202504-AMER
A11: FC202504-AMER-DKD | B11: AMER | C11: 45777 | D11: Monthly | E11: DKD | F11: 4560 | G11: SOP202504-AMER
A12: FC202504-AMER-ARYLIDE | B12: AMER | C12: 45777 | D12: Monthly | E12: ARYLIDE | F12: 2688 | G12: SOP202504-AMER
A13: FC202504-AMER-FLUORO | B13: AMER | C13: 45777 | D13: Monthly | E13: FLUORO | F13: 1455 | G13: SOP202504-AMER
... A289: FC202603-ROW-FLUORO | B289: ROW | C289: 46112 | D289: Monthly | E289: FLUORO | F289: 1545 | G289: SOP202603-ROW

Sheet SOP Events
A1: S&OP Event ID (Primary Key) | B1: Frequency | C1: Horizon | D1: Region Scope (Region ID FK) | E1: Date | F1: Minutes
A2: SOP202504-DOM | B2: Monthly | C2: 1M | D2: DOM | E2: 45762 | F2: Illustrative monthly S&OP (DOM)
A3: SOP202504-EU | B3: Monthly | C3: 1M | D3: EU | E3: 45763 | F3: Illustrative monthly S&OP (EU)
A4: SOP202504-AMER | B4: Monthly | C4: 1M | D4: AMER | E4: 45764 | F4: Illustrative monthly S&OP (AMER)
A5: SOP202504-APAC | B5: Monthly | C5: 1M | D5: APAC | E5: 45761 | F5: Illustrative monthly S&OP (APAC)
A6: SOP202504-MEA | B6: Monthly | C6: 1M | D6: MEA | E6: 45765 | F6: Illustrative monthly S&OP (MEA)
A7: SOP202504-ROW | B7: Monthly | C7: 1M | D7: ROW | E7: 45766 | F7: Illustrative monthly S&OP (ROW)
A8: SOP202505-DOM | B8: Monthly | C8: 1M | D8: DOM | E8: 45792 | F8: Illustrative monthly S&OP (DOM)
A9: SOP202505-EU | B9: Monthly | C9: 1M | D9: EU | E9: 45793 | F9: Illustrative monthly S&OP (EU)
A10: SOP202505-AMER | B10: Monthly | C10: 1M | D10: AMER | E10: 45794 | F10: Illustrative monthly S&OP (AMER)
A11: SOP202505-APAC | B11: Monthly | C11: 1M | D11: APAC | E11: 45791 | F11: Illustrative monthly S&OP (APAC)
A12: SOP202505-MEA | B12: Monthly | C12: 1M | D12: MEA | E12: 45795 | F12: Illustrative monthly S&OP (MEA)
A13: SOP202505-ROW | B13: Monthly | C13: 1M | D13: ROW | E13: 45796 | F13: Illustrative monthly S&OP (ROW)
... A73: SOP202603-ROW | B73: Monthly | C73: 1M | D73: ROW | E73: 46100 | F73: Illustrative monthly S&OP (ROW)

Sheet Capacity Reservations
A1: Capacity Reservation ID (Primary Key) | B1: S&OP Event ID (FK) | C1: Product Family | D1: Line ID (FK) | E1: Reserved Quantity | F1: Planned Start Date | G1: Planned End Date | H1: Status
A2: CR202504-0001 | B2: SOP202504-DOM | C2: ACETYL | D2: LINE_MHD_EA_TRAIN1 | E2: 364 | F2: 45748 | G2: 45751 | H2: Completed
A3: CR202504-0002 | B3: SOP202504-EU | C3: ACETYL | D3: LINE_MHD_EA_TRAIN2 | E3: 368 | F3: 45749 | G3: 45753 | H3: Completed
A4: CR202504-0003 | B4: SOP202504-AMER | C4: ACETYL | D4: LINE_MHD_AA_ANHY | E4: 372 | F4: 45750 | G4: 45755 | H4: Completed
A5: CR202504-0004 | B5: SOP202504-APAC | C5: DKD | D5: LINE_MHD_BA_BATCH1 | E5: 329 | F5: 45751 | G5: 45757 | H5: Completed
A6: CR202504-0005 | B6: SOP202504-MEA | C6: DKD | D6: LINE_MHD_AAEM_REACT1 | E6: 333 | F6: 45752 | G6: 45755 | H6: Completed
A7: CR202504-0006 | B7: SOP202504-ROW | C7: ARYLIDE | D7: LINE_LTE_DKD_ESTER1 | E7: 96 | F7: 45753 | G7: 45757 | H7: Completed
A8: CR202504-0007 | B8: SOP202504-DOM | C8: FLUORO | D8: LINE_LTE_DKD_ESTER2 | E8: 58 | F8: 45754 | G8: 45759 | H8: Completed
A9: CR202504-0008 | B9: SOP202504-EU | C9: ACETYL | D9: LINE_LTE_ARY_1 | E9: 392 | F9: 45755 | G9: 45761 | H9: Completed
A10: CR202504-0009 | B10: SOP202504-AMER | C10: ACETYL | D10: LINE_LTE_ARY_2 | E10: 396 | F10: 45756 | G10: 45759 | H10: Completed
A11: CR202504-0010 | B11: SOP202504-APAC | C11: ACETYL | D11: LINE_LTE_FLR_BLOCK200 | E11: 400 | F11: 45757 | G11: 45761 | H11: Completed
A12: CR202504-0011 | B12: SOP202504-MEA | C12: DKD | D12: LINE_LTE_FLR_BLOCK500 | E12: 354 | F12: 45758 | G12: 45763 | H12: Completed
A13: CR202504-0012 | B13: SOP202504-ROW | C13: DKD | D13: LINE_DHJ_SOLV_TRAIN1 | E13: 357 | F13: 45759 | G13: 45765 | H13: Completed
... A721: CR202603-0720 | B721: SOP202603-ROW | C721: DKD | D721: LINE_DHJ_SOLV_TRAIN1 | E721: 315 | F721: 46091 | G721: 46097 | H721: Draft

Sheet Suppliers
A1: supplier_id (Primary Key) | B1: supplier_name | C1: supplier_type | D1: country_iso (FK) | E1: region_id (FK) | F1: city | G1: supply_category | H1: primary_rm_categories | I1: approved_for_families | J1: SKU codes supplied | K1: quality_certification | L1: dg_handling_capable | M1: iso_tank_capable | N1: payment_terms | O1: lead_time_days (min) | P1: lead_time_days (max) | Q1: moq_mt | R1: credit_limit_usd | S1: currency | T1: incoterms_supported | U1: contract_status | V1: contract_valid_from | W1: contract_valid_to | X1: risk_rating | Y1: esg_rating | Z1: primary_contact_name | AA1: contact_email | AB1: contact_phone | AC1: bank_details | AD1: audit_date | AE1: audit_score_pct | AF1: notes
A2: SUP001 | B2: Gujarat Narmada Valley Fertilizers & Chemicals Ltd | C2: Manufacturer | D2: IN | E2: DOM | F2: Bharuch | G2: Raw Material | H2: Acetic Acid,Methanol | I2: ACETYL,DKD | J2: RM-AAC-GL-23011 | K2: ISO 9001:2015,ISO 14001:2015 | L2: Yes | M2: Yes | N2: Net 30 | O2: 7 | P2: 14 | Q2: 50 | R2: 500000 | S2: INR | T2: EXW,FCA | U2: Active | V2: 45292 | W2: 46387 | X2: A | Y2: B | Z2: Rajesh Kumar | AA2: sales.gnfc@example.com | AB2: +91-2642-252001 | AC2: SBI Bharuch | AD2: 45823 | AE2: 92 | AF2: Key domestic acetic acid supplier; long-term contract
A3: SUP002 | B3: Jubilant Life Sciences Ltd | C3: Manufacturer | D3: IN | E3: DOM | F3: Gajraula | G3: Raw Material | H3: Ethanol,Acetic Anhydride | I3: ACETYL,DKD | J3: RM-ETH-AL-64175,RM-ETH-AL-64197 | K3: ISO 9001:2015,ISO 14001:2015,ISO 45001:2018 | L3: Yes | M3: Yes | N3: Net 45 | O3: 5 | P3: 10 | Q3: 25 | R3: 750000 | S3: INR | T3: EXW,FCA,FOR | U3: Active | V3: 45108 | W3: 46203 | X3: A | Y3: A | Z3: Amit Sharma | AA3: procurement.jubilant@example.com | AB3: +91-5924-252100 | AC3: HDFC Gajraula | AD3: 45736 | AE3: 95 | AF3: Premium ethanol supplier; pharma-grade capability
A4: SUP003 | B4: Celanese Corporation | C4: Manufacturer | D4: US | E4: AMER | F4: Dallas | G4: Raw Material | H4: Acetic Acid,Acetyl Intermediates | I4: ACETYL | J4: RM-AAC-GL-23011,INT-ACE-ANH-772001 | K4: ISO 9001:2015,Responsible Care | L4: Yes | M4: Yes | N4: Net 60 | O4: 35 | P4: 50 | Q4: 100 | R4: 2000000 | S4: USD | T4: FOB,CIF,CFR | U4: Active | V4: 45383 | W4: 46477 | X4: A | Y4: A | Z4: Michael Johnson | AA4: asia.sales@celanese.example.com | AB4: +1-972-443-4000 | AC4: JPMorgan Chase Dallas | AD4: 45606 | AE4: 97 | AF4: Global acetyl leader; backup for domestic shortages
A5: SUP004 | B5: Eastman Chemical Company | C5: Manufacturer | D5: US | E5: AMER | F5: Kingsport | G5: Raw Material | H5: Solvents,Specialty Esters | I5: ACETYL | J5: RM-ETL-AC-11804,RM-BUT-NB-51720 | K5: ISO 9001:2015,ISO 14001:2015 | L5: Yes | M5: Yes | N5: Net 60 | O5: 40 | P5: 55 | Q5: 50 | R5: 1500000 | S5: USD | T5: FOB,CIF | U5: Active | V5: 45444 | W5: 46538 | X5: A | Y5: A | Z5: Sarah Williams | AA5: india.sales@eastman.example.com | AB5: +1-423-229-2000 | AC5: Bank of America Tennessee | AD5: 45672 | AE5: 94 | AF5: Specialty solvents for high-purity grades
A6: SUP005 | B6: BASF SE | C6: Manufacturer | D6: DE | E6: EU | F6: Ludwigshafen | G6: Raw Material | H6: Aniline,Specialty Amines | I6: ARYLIDE | J6: RM-ANI-LN-90355,RM-OAN-AS-55102 | K6: ISO 9001:2015,ISO 14001:2015,REACH | L6: Yes | M6: Yes | N6: Net 45 | O6: 28 | P6: 42 | Q6: 20 | R6: 1800000 | S6: EUR | T6: FOB,CIF,DDP | U6: Active | V6: 45323 | W6: 46418 | X6: A | Y6: A | Z6: Hans Mueller | AA6: india.chemicals@basf.example.com | AB6: +49-621-60-0 | AC6: Deutsche Bank Ludwigshafen | AD6: 45560 | AE6: 98 | AF6: Premium arylide intermediates; REACH compliant
A7: SUP006 | B7: Lanxess AG | C7: Manufacturer | D7: DE | E7: EU | F7: Cologne | G7: Raw Material | H7: Chloroanilines,Specialty Chemicals | I7: ARYLIDE | J7: RM-PCA-AN-77210 | K7: ISO 9001:2015,ISO 14001:2015,REACH | L7: Yes | M7: No | N7: Net 45 | O7: 30 | P7: 45 | Q7: 15 | R7: 1200000 | S7: EUR | T7: FOB,CIF | U7: Active | V7: 45352 | W7: 46446 | X7: A | Y7: B | Z7: Klaus Weber | AA7: asia.sales@lanxess.example.com | AB7: +49-221-8885-0 | AC7: Commerzbank Cologne | AD7: 45522 | AE7: 91 | AF7: Specialty chloroanilines for arylide pigments
A8: SUP007 | B8: Lonza Group AG | C8: Manufacturer | D8: CH | E8: EU | F8: Basel | G8: Raw Material | H8: Diketene,Ketene Derivatives | I8: DKD,ACETYL | J8: RM-DIK-ET-88412,INT-KET-674828 | K8: ISO 9001:2015,ISO 14001:2015,GMP | L8: Yes | M8: Yes | N8: Net 30 | O8: 21 | P8: 35 | Q8: 10 | R8: 2500000 | S8: CHF | T8: FOB,CIF,DDP | U8: Active | V8: 45170 | W8: 46265 | X8: A | Y8: A | Z8: Pierre Dubois | AA8: asia.intermediates@lonza.example.com | AB8: +41-61-316-8111 | AC8: UBS Basel | AD8: 45716 | AE8: 96 | AF8: Critical DKD intermediates; refrigerated logistics
A9: SUP008 | B9: Sinopec Chemical Commercial Holding | C9: Manufacturer | D9: CN | E9: APAC | F9: Shanghai | G9: Raw Material | H9: Acetic Acid,Methanol,Solvents | I9: ACETYL,DKD | J9: RM-AAC-GL-23011,RM-ETH-AL-64219 | K9: ISO 9001:2015 | L9: Yes | M9: Yes | N9: Net 30 | O9: 18 | P9: 28 | Q9: 100 | R9: 1000000 | S9: USD | T9: FOB,CIF,CFR | U9: Active | V9: 45292 | W9: 46387 | X9: B | Y9: C | Z9: Li Wei | AA9: india.sales@sinopec.example.com | AB9: +86-21-2207-8000 | AC9: Bank of China Shanghai | AD9: 45570 | AE9: 85 | AF9: Cost-effective bulk chemicals; price-sensitive orders
A10: SUP009 | B10: Mitsubishi Chemical Corporation | C10: Manufacturer | D10: JP | E10: APAC | F10: Tokyo | G10: Raw Material | H10: Specialty Acrylates,AAEM | I10: ACETYL | J10: RM-MTH-AA-40218,INT-AAA-EMM-990812 | K10: ISO 9001:2015,ISO 14001:2015 | L10: Yes | M10: Yes | N10: Net 45 | O10: 25 | P10: 40 | Q10: 15 | R10: 1500000 | S10: JPY | T10: FOB,CIF | U10: Active | V10: 45413 | W10: 46507 | X10: A | Y10: A | Z10: Takeshi Yamamoto | AA10: india.sales@m-chem.example.com | AB10: +81-3-6748-7300 | AC10: MUFG Bank Tokyo | AD10: 45759 | AE10: 93 | AF10: High-purity acrylate monomers for AAEM
A11: SUP010 | B11: Indian Oil Corporation Ltd | C11: Manufacturer | D11: IN | E11: DOM | F11: Panipat | G11: Raw Material | H11: Solvents,Toluene,Xylene | I11: ACETYL,ARYLIDE | J11: RM-TOL-SV-90412,RM-ACN-SV-33120 | K11: ISO 9001:2015,ISO 14001:2015 | L11: Yes | M11: Yes | N11: Net 15 | O11: 3 | P11: 7 | Q11: 50 | R11: 800000 | S11: INR | T11: EXW,FOR | U11: Active | V11: 45292 | W11: 46387 | X11: A | Y11: B | Z11: Vikram Singh | AA11: chemicals.iocl@example.com | AB11: +91-22-2262-6060 | AC11: SBI Panipat | AD11: 45797 | AE11: 90 | AF11: Domestic solvent supply; short lead times
A12: SUP011 | B12: Deepak Nitrite Ltd | C12: Manufacturer | D12: IN | E12: DOM | F12: Vadodara | G12: Raw Material | H12: Aniline,Nitro Compounds | I12: ARYLIDE | J12: RM-ANI-LN-90355 | K12: ISO 9001:2015,ISO 14001:2015,ISO 45001:2018 | L12: Yes | M12: No | N12: Net 30 | O12: 5 | P12: 12 | Q12: 20 | R12: 600000 | S12: INR | T12: EXW,FCA,FOR | U12: Active | V12: 45323 | W12: 46418 | X12: A | Y12: B | Z12: Priya Patel | AA12: sales.deepak@example.com | AB12: +91-22-4477-2000 | AC12: ICICI Vadodara | AD12: 45636 | AE12: 89 | AF12: Domestic aniline supplier; backup to imports
A13: SUP012 | B13: Solvay SA | C13: Manufacturer | D13: BE | E13: EU | F13: Brussels | G13: Raw Material | H13: Fluorochemicals,Specialty Chemicals | I13: FLUORO | J13: INT-FLR-BLK-903117 | K13: ISO 9001:2015,ISO 14001:2015,REACH | L13: Yes | M13: Yes | N13: Net 45 | O13: 28 | P13: 45 | Q13: 10 | R13: 2000000 | S13: EUR | T13: FOB,CIF,DDP | U13: Active | V13: 45383 | W13: 46477 | X13: A | Y13: A | Z13: Jean-Pierre Martin | AA13: asia.fluoro@solvay.example.com | AB13: +91-265-239-8500 | AC13: BNP Paribas Brussels | AD13: 45495 | AE13: 95 | AF13: Critical fluoro intermediates; DG certified
... A29: SUP028 | B29: LEAP India Pvt Ltd (Loscam) | C29: Pooling Service | D29: IN | E29: DOM | F29: Mumbai | G29: Packaging | H29: Wooden Pallets,Plastic Pallets,Pallet Pooling | I29: ACETYL,DKD,ARYLIDE,FLUORO | J29: PKG-PALLET,PKG-PALLET-POOL | K29: ISO 9001:2015,ISPM-15 (Heat Treated) | L29: No | M29: No | N29: Net 15 | O29: 2 | P29: 5 | Q29: 100 | R29: 200000 | S29: INR | T29: EXW,FCA | U29: Active | V29: 45413 | W29: 46507 | X29: B | Y29: B | Z29: Vikram Desai | AA29: india.ops@loscam.example.com | AB29: +91-20-6725-4000 | AC29: Yes Bank Mumbai | AD29: 45820 | AE29: 89 | AF29: Pallet pooling reduces capital; ISPM-15 certified for export

Sheet Material Requirements Plan
A1: MRP ID (Primary Key) | B1: Capacity Reservation ID (FK) | C1: product_family | D1: SKU Code (FK) | E1: gross_requirement_qty | F1: onhand_qty | G1: scheduled_receipts_qty | H1: net_requirement_qty | I1: uom | J1: std_lead_time_days | K1: recommended_order_release_date | L1: priority | M1: notes
A2: MRP202504-0001 | B2: CR202504-0001 | C2: ACETYL | D2: RM-ETH-AL-64175 | E2: 141 | F2: 19 | G2: 28 | H2: 94 | I2: MT | J2: 5 | K2: 45726 | L2: High | M2: ACETYL input RM-ETH-AL-64175; align procurement to 2025-04 runs; illustrative.
A3: MRP202504-0002 | B3: CR202504-0002 | C3: ACETYL | D3: RM-AAC-GL-23011 | E3: 143 | F3: 19 | G3: 29 | H3: 95 | I3: MT | J3: 6 | K3: 45726 | L3: Medium | M3: ACETYL input RM-AAC-GL-23011; align procurement to 2025-04 runs; illustrative.
A4: MRP202504-0003 | B4: CR202504-0003 | C4: ACETYL | D4: RM-BUT-NB-51720 | E4: 144 | F4: 19 | G4: 29 | H4: 96 | I4: MT | J4: 7 | K4: 45726 | L4: Low | M4: ACETYL input RM-BUT-NB-51720; align procurement to 2025-04 runs; illustrative.
A5: MRP202504-0004 | B5: CR202504-0004 | C5: DKD | D5: RM-ETL-AC-11804 | E5: 146 | F5: 19 | G5: 29 | H5: 98 | I5: MT | J5: 8 | K5: 45726 | L5: High | M5: DKD input RM-ETL-AC-11804; align procurement to 2025-04 runs; illustrative.
A6: MRP202504-0005 | B6: CR202504-0005 | C6: DKD | D6: RM-MTH-AA-40218 | E6: 490 | F6: 49 | G6: 98 | H6: 343 | I6: MT | J6: 9 | K6: 45726 | L6: Medium | M6: DKD input RM-MTH-AA-40218; align procurement to 2025-04 runs; illustrative.
A7: MRP202504-0006 | B7: CR202504-0006 | C7: ARYLIDE | D7: RM-ANI-LN-90355 | E7: 495 | F7: 50 | G7: 99 | H7: 346 | I7: MT | J7: 10 | K7: 45726 | L7: Low | M7: ARYLIDE input RM-ANI-LN-90355; align procurement to 2025-04 runs; illustrative.
A8: MRP202504-0007 | B8: CR202504-0007 | C8: FLUORO | D8: RM-PCA-AN-77210 | E8: 500 | F8: 50 | G8: 100 | H8: 350 | I8: MT | J8: 11 | K8: 45726 | L8: High | M8: FLUORO input RM-PCA-AN-77210; align procurement to 2025-04 runs; illustrative.
A9: MRP202504-0008 | B9: CR202504-0008 | C9: ACETYL | D9: RM-OAN-AS-55102 | E9: 505 | F9: 51 | G9: 101 | H9: 353 | I9: MT | J9: 12 | K9: 45726 | L9: Medium | M9: ACETYL input RM-OAN-AS-55102; align procurement to 2025-04 runs; illustrative.
A10: MRP202504-0009 | B10: CR202504-0009 | C10: ACETYL | D10: RM-DIK-ET-88412 | E10: 510 | F10: 51 | G10: 102 | H10: 357 | I10: MT | J10: 13 | K10: 45726 | L10: Low | M10: ACETYL input RM-DIK-ET-88412; align procurement to 2025-04 runs; illustrative.
A11: MRP202504-0010 | B11: CR202504-0010 | C11: ACETYL | D11: INT-KET-INS-145120 | E11: 515 | F11: 52 | G11: 103 | H11: 360 | I11: MT | J11: 14 | K11: 45726 | L11: High | M11: ACETYL input INT-KET-INS-145120; align procurement to 2025-04 runs; illustrative.
A12: MRP202504-0011 | B12: CR202504-0011 | C12: DKD | D12: INT-DKD-INT-342781 | E12: 520 | F12: 52 | G12: 104 | H12: 364 | I12: MT | J12: 5 | K12: 45726 | L12: Medium | M12: DKD input INT-DKD-INT-342781; align procurement to 2025-04 runs; illustrative.
A13: MRP202504-0012 | B13: CR202504-0012 | C13: DKD | D13: INT-ARY-INT-558903 | E13: 525 | F13: 53 | G13: 105 | H13: 367 | I13: MT | J13: 6 | K13: 45726 | L13: Low | M13: DKD input INT-ARY-INT-558903; align procurement to 2025-04 runs; illustrative.
... A1801: MRP202603-1800 | B1801: CR202603-0030 | C1801: ACETYL | D1801: RM-DIK-ET-88412 | E1801: 465 | F1801: 47 | G1801: 93 | H1801: 325 | I1801: MT | J1801: 14 | K1801: 46063 | L1801: Low | M1801: ACETYL input RM-DIK-ET-88412; align procurement to 2026-03 runs; illustrative.

Sheet Production Plan
A1: Production Plan ID (PK) | B1: Capacity Reservations (FK) | C1: SKU ID (FK) | D1: Line ID (FK) | E1: Planned Start | F1: Planned End | G1: Required Quantity | H1: Estimated Scrappage (%) | I1: Quality Defect Rate (%) | J1: Planned Quantity | K1: Status
A2: PP202504-0001 | B2: CR202504-0001 | C2: ESS-ACETYL-ETHACE-LM-98.5-NEAT-BULK-DST | D2: LINE_MHD_EA_TRAIN1 | E2: 45748 | F2: 45749 | G2: 182 | H2: 0.01 | I2: 0.005 | J2: 189 | K2: Completed
A3: PP202504-0002 | B3: CR202504-0002 | C3: ESS-ACETYL-ETHACE-LM-98.5-NEAT-BULK-DST | D3: LINE_MHD_EA_TRAIN2 | E3: 45749 | F3: 45751 | G3: 184 | H3: 0.02 | I3: 0.01 | J3: 191 | K3: Completed
A4: PP202504-0003 | B4: CR202504-0003 | C4: ESS-ACETYL-ETHACE-LM-98.5-NEAT-BULK-DST | D4: LINE_MHD_AA_ANHY | E4: 45750 | F4: 45753 | G4: 186 | H4: 0.03 | I4: 0.015 | J4: 193 | K4: Completed
A5: PP202504-0004 | B5: CR202504-0004 | C5: SPI-ACETYL-ACEANH-PH-98.6-NEAT-DR200_UN-MHD | D5: LINE_MHD_BA_BATCH1 | E5: 45751 | F5: 45752 | G5: 188 | H5: 0.01 | I5: 0.005 | J5: 196 | K5: Completed
A6: PP202504-0005 | B6: CR202504-0005 | C6: SPI-ACETYL-ACEANH-PH-98.6-NEAT-DR200_UN-MHD | D6: LINE_MHD_AAEM_REACT1 | E6: 45752 | F6: 45754 | G6: 190 | H6: 0.02 | I6: 0.01 | J6: 198 | K6: Completed
A7: PP202504-0006 | B7: CR202504-0006 | C7: SPI-ACETYL-ACEANH-PH-98.6-NEAT-DR200_UN-MHD | D7: LINE_LTE_DKD_ESTER1 | E7: 45753 | F7: 45756 | G7: 192 | H7: 0.03 | I7: 0.015 | J7: 200 | K7: Completed
A8: PP202504-0007 | B8: CR202504-0007 | C8: SPI-ACETYL-ACE-IND-98.4-NEAT-ISO20-LTE | D8: LINE_LTE_DKD_ESTER2 | E8: 45754 | F8: 45755 | G8: 194 | H8: 0.01 | I8: 0.005 | J8: 202 | K8: Completed
A9: PP202504-0008 | B9: CR202504-0008 | C9: SPI-ACETYL-ACE-IND-98.4-NEAT-ISO20-LTE | D9: LINE_LTE_ARY_1 | E9: 45755 | F9: 45757 | G9: 196 | H9: 0.02 | I9: 0.01 | J9: 204 | K9: Completed
A10: PP202504-0009 | B10: CR202504-0009 | C10: SPI-ACETYL-ACE-IND-98.4-NEAT-ISO20-LTE | D10: LINE_LTE_ARY_2 | E10: 45756 | F10: 45759 | G10: 198 | H10: 0.03 | I10: 0.015 | J10: 206 | K10: Completed
A11: PP202504-0010 | B11: CR202504-0010 | C11: ESS-ACETYL-BUTACE-TECH-98.3-NEAT-DR200-DHJ | D11: LINE_LTE_FLR_BLOCK200 | E11: 45757 | F11: 45758 | G11: 200 | H11: 0.01 | I11: 0.005 | J11: 208 | K11: Completed
A12: PP202504-0011 | B12: CR202504-0011 | C12: ESS-ACETYL-BUTACE-TECH-98.3-NEAT-DR200-DHJ | D12: LINE_LTE_FLR_BLOCK500 | E12: 45758 | F12: 45760 | G12: 202 | H12: 0.02 | I12: 0.01 | J12: 210 | K12: Completed
A13: PP202504-0012 | B13: CR202504-0012 | C13: ESS-ACETYL-BUTACE-TECH-98.3-NEAT-DR200-DHJ | D13: LINE_DHJ_SOLV_TRAIN1 | E13: 45759 | F13: 45762 | G13: 204 | H13: 0.03 | I13: 0.015 | J13: 212 | K13: Completed
... A101: PP202504-0100 | B101: CR202504-0040 | C101: ESS-ACETYL-BUTACE-PH-98.5-NEAT-ISO20-MHD | D101: LINE_MHD_BA_BATCH1 | E101: 45763 | F101: 45764 | G101: 180 | H101: 0.01 | I101: 0.005 | J101: 187 | K101: Completed
A102: PP202504-0101 | C102: ESS-ACETYL-BUTACE-PH-98.5-NEAT-ISO20-MHD | D102: LINE_MHD_AAEM_REACT1 | E102: 45764 | F102: 45766 | G102: 182 | H102: 0.02 | I102: 0.01 | J102: 189 | K102: Completed
A103: PP202504-0102 | C103: ESS-ACETYL-BUTACE-PH-98.5-NEAT-ISO20-MHD | D103: LINE_LTE_DKD_ESTER1 | E103: 45765 | F103: 45768 | G103: 184 | H103: 0.03 | I103: 0.015 | J103: 191 | K103: Completed
A104: PP202504-0103 | C104: ESS-ACETYL-MAA-IND-98.7-NEAT-DR200-LTE | D104: LINE_LTE_DKD_ESTER2 | E104: 45766 | F104: 45767 | G104: 186 | H104: 0.01 | I104: 0.005 | J104: 193 | K104: Completed
A105: PP202504-0104 | C105: ESS-ACETYL-MAA-IND-98.7-NEAT-DR200-LTE | D105: LINE_LTE_ARY_1 | E105: 45767 | F105: 45769 | G105: 188 | H105: 0.02 | I105: 0.01 | J105: 196 | K105: Completed
A106: PP202504-0105 | C106: ESS-ACETYL-MAA-IND-98.7-NEAT-DR200-LTE | D106: LINE_LTE_ARY_2 | E106: 45768 | F106: 45771 | G106: 190 | H106: 0.03 | I106: 0.015 | J106: 198 | K106: Completed
A107: PP202504-0106 | C107: ESS-ACETYL-EAA-IND-98.8-NEAT-DR200-DHJ | D107: LINE_LTE_FLR_BLOCK200 | E107: 45769 | F107: 45770 | G107: 192 | H107: 0.01 | I107: 0.005 | J107: 200 | K107: Completed
A108: PP202504-0107 | C108: ESS-ACETYL-EAA-IND-98.8-NEAT-DR200-DHJ | D108: LINE_LTE_FLR_BLOCK500 | E108: 45770 | F108: 45772 | G108: 194 | H108: 0.02 | I108: 0.01 | J108: 202 | K108: Completed
A109: PP202504-0108 | C109: ESS-ACETYL-EAA-IND-98.8-NEAT-DR200-DHJ | D109: LINE_DHJ_SOLV_TRAIN1 | E109: 45771 | F109: 45774 | G109: 196 | H109: 0.03 | I109: 0.015 | J109: 204 | K109: Completed
A110: PP202504-0109 | C110: ESS-ACETYL-AAEM-LM-98.8-NEAT-BULK-DST | D110: LINE_DHJ_DKD_UNIT1 | E110: 45772 | F110: 45773 | G110: 198 | H110: 0.01 | I110: 0.005 | J110: 206 | K110: Completed
A111: PP202505-0110 | B111: CR202505-0001 | C111: ESS-ACETYL-ETHACE-LM-98.5-NEAT-BULK-DST | D111: LINE_MHD_EA_TRAIN1 | E111: 45778 | F111: 45779 | G111: 200 | H111: 0.01 | I111: 0.005 | J111: 208 | K111: Completed
A112: PP202505-0111 | B112: CR202505-0002 | C112: ESS-ACETYL-ETHACE-LM-98.5-NEAT-BULK-DST | D112: LINE_MHD_EA_TRAIN2 | E112: 45779 | F112: 45781 | G112: 202 | H112: 0.02 | I112: 0.01 | J112: 210 | K112: Completed
A113: PP202505-0112 | B113: CR202505-0003 | C113: ESS-ACETYL-ETHACE-LM-98.5-NEAT-BULK-DST | D113: LINE_MHD_AA_ANHY | E113: 45780 | F113: 45783 | G113: 204 | H113: 0.03 | I113: 0.015 | J113: 212 | K113: Completed
A114: PP202505-0113 | B114: CR202505-0004 | C114: SPI-ACETYL-ACEANH-PH-98.6-NEAT-DR200_UN-MHD | D114: LINE_MHD_BA_BATCH1 | E114: 45781 | F114: 45782 | G114: 206 | H114: 0.01 | I114: 0.005 | J114: 214 | K114: Completed
A115: PP202505-0114 | B115: CR202505-0005 | C115: SPI-ACETYL-ACEANH-PH-98.6-NEAT-DR200_UN-MHD | D115: LINE_MHD_AAEM_REACT1 | E115: 45782 | F115: 45784 | G115: 208 | H115: 0.02 | I115: 0.01 | J115: 216 | K115: Completed
A116: PP202505-0115 | B116: CR202505-0006 | C116: SPI-ACETYL-ACEANH-PH-98.6-NEAT-DR200_UN-MHD | D116: LINE_LTE_DKD_ESTER1 | E116: 45783 | F116: 45786 | G116: 210 | H116: 0.03 | I116: 0.015 | J116: 218 | K116: Completed
A117: PP202505-0116 | B117: CR202505-0007 | C117: SPI-ACETYL-ACE-IND-98.4-NEAT-ISO20-LTE | D117: LINE_LTE_DKD_ESTER2 | E117: 45784 | F117: 45785 | G117: 212 | H117: 0.01 | I117: 0.005 | J117: 220 | K117: Completed
A118: PP202505-0117 | B118: CR202505-0008 | C118: SPI-ACETYL-ACE-IND-98.4-NEAT-ISO20-LTE | D118: LINE_LTE_ARY_1 | E118: 45785 | F118: 45787 | G118: 214 | H118: 0.02 | I118: 0.01 | J118: 223 | K118: Completed
A119: PP202505-0118 | B119: CR202505-0009 | C119: SPI-ACETYL-ACE-IND-98.4-NEAT-ISO20-LTE | D119: LINE_LTE_ARY_2 | E119: 45786 | F119: 45789 | G119: 216 | H119: 0.03 | I119: 0.015 | J119: 225 | K119: Completed
A120: PP202505-0119 | B120: CR202505-0010 | C120: ESS-ACETYL-BUTACE-TECH-98.3-NEAT-DR200-DHJ | D120: LINE_LTE_FLR_BLOCK200 | E120: 45787 | F120: 45788 | G120: 218 | H120: 0.01 | I120: 0.005 | J120: 227 | K120: Completed
A121: PP202505-0120 | B121: CR202505-0011 | C121: ESS-ACETYL-BUTACE-TECH-98.3-NEAT-DR200-DHJ | D121: LINE_LTE_FLR_BLOCK500 | E121: 45788 | F121: 45790 | G121: 180 | H121: 0.02 | I121: 0.01 | J121: 187 | K121: Completed
A122: PP202505-0121 | B122: CR202505-0012 | C122: ESS-ACETYL-BUTACE-TECH-98.3-NEAT-DR200-DHJ | D122: LINE_DHJ_SOLV_TRAIN1 | E122: 45789 | F122: 45792 | G122: 182 | H122: 0.03 | I122: 0.015 | J122: 189 | K122: Completed
... A210: PP202505-0209 | B210: CR202505-0040 | C210: ESS-ACETYL-BUTACE-PH-98.5-NEAT-ISO20-MHD | D210: LINE_MHD_BA_BATCH1 | E210: 45793 | F210: 45794 | G210: 198 | H210: 0.01 | I210: 0.005 | J210: 206 | K210: Completed
A211: PP202505-0210 | C211: ESS-ACETYL-BUTACE-PH-98.5-NEAT-ISO20-MHD | D211: LINE_MHD_AAEM_REACT1 | E211: 45794 | F211: 45796 | G211: 200 | H211: 0.02 | I211: 0.01 | J211: 208 | K211: Completed
A212: PP202505-0211 | C212: ESS-ACETYL-BUTACE-PH-98.5-NEAT-ISO20-MHD | D212: LINE_LTE_DKD_ESTER1 | E212: 45795 | F212: 45798 | G212: 202 | H212: 0.03 | I212: 0.015 | J212: 210 | K212: Completed
A213: PP202505-0212 | C213: ESS-ACETYL-MAA-IND-98.7-NEAT-DR200-LTE | D213: LINE_LTE_DKD_ESTER2 | E213: 45796 | F213: 45797 | G213: 204 | H213: 0.01 | I213: 0.005 | J213: 212 | K213: Completed
A214: PP202505-0213 | C214: ESS-ACETYL-MAA-IND-98.7-NEAT-DR200-LTE | D214: LINE_LTE_ARY_1 | E214: 45797 | F214: 45799 | G214: 206 | H214: 0.02 | I214: 0.01 | J214: 214 | K214: Completed
A215: PP202505-0214 | C215: ESS-ACETYL-MAA-IND-98.7-NEAT-DR200-LTE | D215: LINE_LTE_ARY_2 | E215: 45798 | F215: 45801 | G215: 208 | H215: 0.03 | I215: 0.015 | J215: 216 | K215: Completed
A216: PP202505-0215 | C216: ESS-ACETYL-EAA-IND-98.8-NEAT-DR200-DHJ | D216: LINE_LTE_FLR_BLOCK200 | E216: 45799 | F216: 45800 | G216: 210 | H216: 0.01 | I216: 0.005 | J216: 218 | K216: Completed
A217: PP202505-0216 | C217: ESS-ACETYL-EAA-IND-98.8-NEAT-DR200-DHJ | D217: LINE_LTE_FLR_BLOCK500 | E217: 45800 | F217: 45802 | G217: 212 | H217: 0.02 | I217: 0.01 | J217: 220 | K217: Completed
A218: PP202505-0217 | C218: ESS-ACETYL-EAA-IND-98.8-NEAT-DR200-DHJ | D218: LINE_DHJ_SOLV_TRAIN1 | E218: 45801 | F218: 45804 | G218: 214 | H218: 0.03 | I218: 0.015 | J218: 223 | K218: Completed
A219: PP202505-0218 | C219: ESS-ACETYL-AAEM-LM-98.8-NEAT-BULK-DST | D219: LINE_DHJ_DKD_UNIT1 | E219: 45802 | F219: 45803 | G219: 216 | H219: 0.01 | I219: 0.005 | J219: 225 | K219: Completed
A220: PP202506-0219 | B220: CR202506-0001 | C220: ESS-ACETYL-ETHACE-LM-98.5-NEAT-BULK-DST | D220: LINE_MHD_EA_TRAIN1 | E220: 45809 | F220: 45810 | G220: 218 | H220: 0.01 | I220: 0.005 | J220: 227 | K220: Completed
A221: PP202506-0220 | B221: CR202506-0002 | C221: ESS-ACETYL-ETHACE-LM-98.5-NEAT-BULK-DST | D221: LINE_MHD_EA_TRAIN2 | E221: 45810 | F221: 45812 | G221: 180 | H221: 0.02 | I221: 0.01 | J221: 187 | K221: Completed
A222: PP202506-0221 | B222: CR202506-0003 | C222: ESS-ACETYL-ETHACE-LM-98.5-NEAT-BULK-DST | D222: LINE_MHD_AA_ANHY | E222: 45811 | F222: 45814 | G222: 182 | H222: 0.03 | I222: 0.015 | J222: 189 | K222: Completed
A223: PP202506-0222 | B223: CR202506-0004 | C223: SPI-ACETYL-ACEANH-PH-98.6-NEAT-DR200_UN-MHD | D223: LINE_MHD_BA_BATCH1 | E223: 45812 | F223: 45813 | G223: 184 | H223: 0.01 | I223: 0.005 | J223: 191 | K223: Completed
A224: PP202506-0223 | B224: CR202506-0005 | C224: SPI-ACETYL-ACEANH-PH-98.6-NEAT-DR200_UN-MHD | D224: LINE_MHD_AAEM_REACT1 | E224: 45813 | F224: 45815 | G224: 186 | H224: 0.02 | I224: 0.01 | J224: 193 | K224: Completed
A225: PP202506-0224 | B225: CR202506-0006 | C225: SPI-ACETYL-ACEANH-PH-98.6-NEAT-DR200_UN-MHD | D225: LINE_LTE_DKD_ESTER1 | E225: 45814 | F225: 45817 | G225: 188 | H225: 0.03 | I225: 0.015 | J225: 196 | K225: Completed
A226: PP202506-0225 | B226: CR202506-0007 | C226: SPI-ACETYL-ACE-IND-98.4-NEAT-ISO20-LTE | D226: LINE_LTE_DKD_ESTER2 | E226: 45815 | F226: 45816 | G226: 190 | H226: 0.01 | I226: 0.005 | J226: 198 | K226: Completed
A227: PP202506-0226 | B227: CR202506-0008 | C227: SPI-ACETYL-ACE-IND-98.4-NEAT-ISO20-LTE | D227: LINE_LTE_ARY_1 | E227: 45816 | F227: 45818 | G227: 192 | H227: 0.02 | I227: 0.01 | J227: 200 | K227: Completed
A228: PP202506-0227 | B228: CR202506-0009 | C228: SPI-ACETYL-ACE-IND-98.4-NEAT-ISO20-LTE | D228: LINE_LTE_ARY_2 | E228: 45817 | F228: 45820 | G228: 194 | H228: 0.03 | I228: 0.015 | J228: 202 | K228: Completed
A229: PP202506-0228 | B229: CR202506-0010 | C229: ESS-ACETYL-BUTACE-TECH-98.3-NEAT-DR200-DHJ | D229: LINE_LTE_FLR_BLOCK200 | E229: 45818 | F229: 45819 | G229: 196 | H229: 0.01 | I229: 0.005 | J229: 204 | K229: Completed
A230: PP202506-0229 | B230: CR202506-0011 | C230: ESS-ACETYL-BUTACE-TECH-98.3-NEAT-DR200-DHJ | D230: LINE_LTE_FLR_BLOCK500 | E230: 45819 | F230: 45821 | G230: 198 | H230: 0.02 | I230: 0.01 | J230: 206 | K230: Completed
A231: PP202506-0230 | B231: CR202506-0012 | C231: ESS-ACETYL-BUTACE-TECH-98.3-NEAT-DR200-DHJ | D231: LINE_DHJ_SOLV_TRAIN1 | E231: 45820 | F231: 45823 | G231: 200 | H231: 0.03 | I231: 0.015 | J231: 208 | K231: Completed
... A319: PP202506-0318 | B319: CR202506-0040 | C319: ESS-ACETYL-BUTACE-PH-98.5-NEAT-ISO20-MHD | D319: LINE_MHD_BA_BATCH1 | E319: 45824 | F319: 45825 | G319: 216 | H319: 0.01 | I319: 0.005 | J319: 225 | K319: Completed
A320: PP202506-0319 | C320: ESS-ACETYL-BUTACE-PH-98.5-NEAT-ISO20-MHD | D320: LINE_MHD_AAEM_REACT1 | E320: 45825 | F320: 45827 | G320: 218 | H320: 0.02 | I320: 0.01 | J320: 227 | K320: Completed
A321: PP202506-0320 | C321: ESS-ACETYL-BUTACE-PH-98.5-NEAT-ISO20-MHD | D321: LINE_LTE_DKD_ESTER1 | E321: 45826 | F321: 45829 | G321: 180 | H321: 0.03 | I321: 0.015 | J321: 187 | K321: Completed
A322: PP202506-0321 | C322: ESS-ACETYL-MAA-IND-98.7-NEAT-DR200-LTE | D322: LINE_LTE_DKD_ESTER2 | E322: 45827 | F322: 45828 | G322: 182 | H322: 0.01 | I322: 0.005 | J322: 189 | K322: Completed
A323: PP202506-0322 | C323: ESS-ACETYL-MAA-IND-98.7-NEAT-DR200-LTE | D323: LINE_LTE_ARY_1 | E323: 45828 | F323: 45830 | G323: 184 | H323: 0.02 | I323: 0.01 | J323: 191 | K323: Completed
A324: PP202506-0323 | C324: ESS-ACETYL-MAA-IND-98.7-NEAT-DR200-LTE | D324: LINE_LTE_ARY_2 | E324: 45829 | F324: 45832 | G324: 186 | H324: 0.03 | I324: 0.015 | J324: 193 | K324: Completed
A325: PP202506-0324 | C325: ESS-ACETYL-EAA-IND-98.8-NEAT-DR200-DHJ | D325: LINE_LTE_FLR_BLOCK200 | E325: 45830 | F325: 45831 | G325: 188 | H325: 0.01 | I325: 0.005 | J325: 196 | K325: Completed
A326: PP202506-0325 | C326: ESS-ACETYL-EAA-IND-98.8-NEAT-DR200-DHJ | D326: LINE_LTE_FLR_BLOCK500 | E326: 45831 | F326: 45833 | G326: 190 | H326: 0.02 | I326: 0.01 | J326: 198 | K326: Completed
A327: PP202506-0326 | C327: ESS-ACETYL-EAA-IND-98.8-NEAT-DR200-DHJ | D327: LINE_DHJ_SOLV_TRAIN1 | E327: 45832 | F327: 45835 | G327: 192 | H327: 0.03 | I327: 0.015 | J327: 200 | K327: Completed
A328: PP202506-0327 | C328: ESS-ACETYL-AAEM-LM-98.8-NEAT-BULK-DST | D328: LINE_DHJ_DKD_UNIT1 | E328: 45833 | F328: 45834 | G328: 194 | H328: 0.01 | I328: 0.005 | J328: 202 | K328: Completed
A329: PP202507-0328 | B329: CR202507-0001 | C329: ESS-ACETYL-ETHACE-LM-98.5-NEAT-BULK-DST | D329: LINE_MHD_EA_TRAIN1 | E329: 45839 | F329: 45840 | G329: 196 | H329: 0.01 | I329: 0.005 | J329: 204 | K329: Completed
A330: PP202507-0329 | B330: CR202507-0002 | C330: ESS-ACETYL-ETHACE-LM-98.5-NEAT-BULK-DST | D330: LINE_MHD_EA_TRAIN2 | E330: 45840 | F330: 45842 | G330: 198 | H330: 0.02 | I330: 0.01 | J330: 206 | K330: Completed
A331: PP202507-0330 | B331: CR202507-0003 | C331: ESS-ACETYL-ETHACE-LM-98.5-NEAT-BULK-DST | D331: LINE_MHD_AA_ANHY | E331: 45841 | F331: 45844 | G331: 200 | H331: 0.03 | I331: 0.015 | J331: 208 | K331: Completed
A332: PP202507-0331 | B332: CR202507-0004 | C332: SPI-ACETYL-ACEANH-PH-98.6-NEAT-DR200_UN-MHD | D332: LINE_MHD_BA_BATCH1 | E332: 45842 | F332: 45843 | G332: 202 | H332: 0.01 | I332: 0.005 | J332: 210 | K332: Completed
A333: PP202507-0332 | B333: CR202507-0005 | C333: SPI-ACETYL-ACEANH-PH-98.6-NEAT-DR200_UN-MHD | D333: LINE_MHD_AAEM_REACT1 | E333: 45843 | F333: 45845 | G333: 204 | H333: 0.02 | I333: 0.01 | J333: 212 | K333: Completed
A334: PP202507-0333 | B334: CR202507-0006 | C334: SPI-ACETYL-ACEANH-PH-98.6-NEAT-DR200_UN-MHD | D334: LINE_LTE_DKD_ESTER1 | E334: 45844 | F334: 45847 | G334: 206 | H334: 0.03 | I334: 0.015 | J334: 214 | K334: Completed
A335: PP202507-0334 | B335: CR202507-0007 | C335: SPI-ACETYL-ACE-IND-98.4-NEAT-ISO20-LTE | D335: LINE_LTE_DKD_ESTER2 | E335: 45845 | F335: 45846 | G335: 208 | H335: 0.01 | I335: 0.005 | J335: 216 | K335: Completed
A336: PP202507-0335 | B336: CR202507-0008 | C336: SPI-ACETYL-ACE-IND-98.4-NEAT-ISO20-LTE | D336: LINE_LTE_ARY_1 | E336: 45846 | F336: 45848 | G336: 210 | H336: 0.02 | I336: 0.01 | J336: 218 | K336: Completed
A337: PP202507-0336 | B337: CR202507-0009 | C337: SPI-ACETYL-ACE-IND-98.4-NEAT-ISO20-LTE | D337: LINE_LTE_ARY_2 | E337: 45847 | F337: 45850 | G337: 212 | H337: 0.03 | I337: 0.015 | J337: 220 | K337: Completed
A338: PP202507-0337 | B338: CR202507-0010 | C338: ESS-ACETYL-BUTACE-TECH-98.3-NEAT-DR200-DHJ | D338: LINE_LTE_FLR_BLOCK200 | E338: 45848 | F338: 45849 | G338: 214 | H338: 0.01 | I338: 0.005 | J338: 223 | K338: Completed
A339: PP202507-0338 | B339: CR202507-0011 | C339: ESS-ACETYL-BUTACE-TECH-98.3-NEAT-DR200-DHJ | D339: LINE_LTE_FLR_BLOCK500 | E339: 45849 | F339: 45851 | G339: 216 | H339: 0.02 | I339: 0.01 | J339: 225 | K339: Completed
A340: PP202507-0339 | B340: CR202507-0012 | C340: ESS-ACETYL-BUTACE-TECH-98.3-NEAT-DR200-DHJ | D340: LINE_DHJ_SOLV_TRAIN1 | E340: 45850 | F340: 45853 | G340: 218 | H340: 0.03 | I340: 0.015 | J340: 227 | K340: Completed
... A428: PP202507-0427 | B428: CR202507-0040 | C428: ESS-ACETYL-BUTACE-PH-98.5-NEAT-ISO20-MHD | D428: LINE_MHD_BA_BATCH1 | E428: 45854 | F428: 45855 | G428: 194 | H428: 0.01 | I428: 0.005 | J428: 202 | K428: Completed
A429: PP202507-0428 | C429: ESS-ACETYL-BUTACE-PH-98.5-NEAT-ISO20-MHD | D429: LINE_MHD_AAEM_REACT1 | E429: 45855 | F429: 45857 | G429: 196 | H429: 0.02 | I429: 0.01 | J429: 204 | K429: Completed
A430: PP202507-0429 | C430: ESS-ACETYL-BUTACE-PH-98.5-NEAT-ISO20-MHD | D430: LINE_LTE_DKD_ESTER1 | E430: 45856 | F430: 45859 | G430: 198 | H430: 0.03 | I430: 0.015 | J430: 206 | K430: Completed
A431: PP202507-0430 | C431: ESS-ACETYL-MAA-IND-98.7-NEAT-DR200-LTE | D431: LINE_LTE_DKD_ESTER2 | E431: 45857 | F431: 45858 | G431: 200 | H431: 0.01 | I431: 0.005 | J431: 208 | K431: Completed
A432: PP202507-0431 | C432: ESS-ACETYL-MAA-IND-98.7-NEAT-DR200-LTE | D432: LINE_LTE_ARY_1 | E432: 45858 | F432: 45860 | G432: 202 | H432: 0.02 | I432: 0.01 | J432: 210 | K432: Completed
A433: PP202507-0432 | C433: ESS-ACETYL-MAA-IND-98.7-NEAT-DR200-LTE | D433: LINE_LTE_ARY_2 | E433: 45859 | F433: 45862 | G433: 204 | H433: 0.03 | I433: 0.015 | J433: 212 | K433: Completed
A434: PP202507-0433 | C434: ESS-ACETYL-EAA-IND-98.8-NEAT-DR200-DHJ | D434: LINE_LTE_FLR_BLOCK200 | E434: 45860 | F434: 45861 | G434: 206 | H434: 0.01 | I434: 0.005 | J434: 214 | K434: Completed
A435: PP202507-0434 | C435: ESS-ACETYL-EAA-IND-98.8-NEAT-DR200-DHJ | D435: LINE_LTE_FLR_BLOCK500 | E435: 45861 | F435: 45863 | G435: 208 | H435: 0.02 | I435: 0.01 | J435: 216 | K435: Completed
A436: PP202507-0435 | C436: ESS-ACETYL-EAA-IND-98.8-NEAT-DR200-DHJ | D436: LINE_DHJ_SOLV_TRAIN1 | E436: 45862 | F436: 45865 | G436: 210 | H436: 0.03 | I436: 0.015 | J436: 218 | K436: Completed
A437: PP202507-0436 | C437: ESS-ACETYL-AAEM-LM-98.8-NEAT-BULK-DST | D437: LINE_DHJ_DKD_UNIT1 | E437: 45863 | F437: 45864 | G437: 212 | H437: 0.01 | I437: 0.005 | J437: 220 | K437: Completed
A438: PP202508-0437 | B438: CR202508-0001 | C438: ESS-ACETYL-ETHACE-LM-98.5-NEAT-BULK-DST | D438: LINE_MHD_EA_TRAIN1 | E438: 45870 | F438: 45871 | G438: 214 | H438: 0.01 | I438: 0.005 | J438: 223 | K438: Completed
A439: PP202508-0438 | B439: CR202508-0002 | C439: ESS-ACETYL-ETHACE-LM-98.5-NEAT-BULK-DST | D439: LINE_MHD_EA_TRAIN2 | E439: 45871 | F439: 45873 | G439: 216 | H439: 0.02 | I439: 0.01 | J439: 225 | K439: Completed
A440: PP202508-0439 | B440: CR202508-0003 | C440: ESS-ACETYL-ETHACE-LM-98.5-NEAT-BULK-DST | D440: LINE_MHD_AA_ANHY | E440: 45872 | F440: 45875 | G440: 218 | H440: 0.03 | I440: 0.015 | J440: 227 | K440: Completed
A441: PP202508-0440 | B441: CR202508-0004 | C441: SPI-ACETYL-ACEANH-PH-98.6-NEAT-DR200_UN-MHD | D441: LINE_MHD_BA_BATCH1 | E441: 45873 | F441: 45874 | G441: 180 | H441: 0.01 | I441: 0.005 | J441: 187 | K441: Completed
A442: PP202508-0441 | B442: CR202508-0005 | C442: SPI-ACETYL-ACEANH-PH-98.6-NEAT-DR200_UN-MHD | D442: LINE_MHD_AAEM_REACT1 | E442: 45874 | F442: 45876 | G442: 182 | H442: 0.02 | I442: 0.01 | J442: 189 | K442: Completed
A443: PP202508-0442 | B443: CR202508-0006 | C443: SPI-ACETYL-ACEANH-PH-98.6-NEAT-DR200_UN-MHD | D443: LINE_LTE_DKD_ESTER1 | E443: 45875 | F443: 45878 | G443: 184 | H443: 0.03 | I443: 0.015 | J443: 191 | K443: Completed
A444: PP202508-0443 | B444: CR202508-0007 | C444: SPI-ACETYL-ACE-IND-98.4-NEAT-ISO20-LTE | D444: LINE_LTE_DKD_ESTER2 | E444: 45876 | F444: 45877 | G444: 186 | H444: 0.01 | I444: 0.005 | J444: 193 | K444: Completed
A445: PP202508-0444 | B445: CR202508-0008 | C445: SPI-ACETYL-ACE-IND-98.4-NEAT-ISO20-LTE | D445: LINE_LTE_ARY_1 | E445: 45877 | F445: 45879 | G445: 188 | H445: 0.02 | I445: 0.01 | J445: 196 | K445: Completed
A446: PP202508-0445 | B446: CR202508-0009 | C446: SPI-ACETYL-ACE-IND-98.4-NEAT-ISO20-LTE | D446: LINE_LTE_ARY_2 | E446: 45878 | F446: 45881 | G446: 190 | H446: 0.03 | I446: 0.015 | J446: 198 | K446: Completed
A447: PP202508-0446 | B447: CR202508-0010 | C447: ESS-ACETYL-BUTACE-TECH-98.3-NEAT-DR200-DHJ | D447: LINE_LTE_FLR_BLOCK200 | E447: 45879 | F447: 45880 | G447: 192 | H447: 0.01 | I447: 0.005 | J447: 200 | K447: Completed
A448: PP202508-0447 | B448: CR202508-0011 | C448: ESS-ACETYL-BUTACE-TECH-98.3-NEAT-DR200-DHJ | D448: LINE_LTE_FLR_BLOCK500 | E448: 45880 | F448: 45882 | G448: 194 | H448: 0.02 | I448: 0.01 | J448: 202 | K448: Completed
...

Sheet Purchase Requisitions
A1: PR Line ID (PK) | B1: Production Plan ID (FK) | C1: Requisition Date | D1: SKU_id (FK) | E1: Quantity | F1: Need by Date | G1: Status
A2: PR202504-0001 | B2: PP202504-0001 | C2: 2025-04-01 | D2: RM-ETH-AL-64175 | E2: 73 | F2: 2025-04-08 | G2: CE
A3: PR202504-0002 | B3: PP202504-0002 | C3: 2025-04-02 | D3: RM-AAC-GL-23011 | E3: 74 | F3: 2025-04-10 | G3: CE
A4: PR202504-0003 | B4: PP202504-0003 | C4: 2025-04-03 | D4: RM-BUT-NB-51720 | E4: 74 | F4: 2025-04-12 | G4: CE
A5: PR202504-0004 | B5: PP202504-0004 | C5: 2025-04-04 | D5: RM-ETL-AC-11804 | E5: 75 | F5: 2025-04-14 | G5: CE
A6: PR202504-0005 | B6: PP202504-0005 | C6: 2025-04-05 | D6: RM-MTH-AA-40218 | E6: 238 | F6: 2025-04-16 | G6: CE
A7: PR202504-0006 | B7: PP202504-0006 | C7: 2025-04-06 | D7: RM-ANI-LN-90355 | E7: 240 | F7: 2025-04-18 | G7: CE
A8: PR202504-0007 | B8: PP202504-0007 | C8: 2025-04-07 | D8: RM-PCA-AN-77210 | E8: 243 | F8: 2025-04-20 | G8: CE
A9: PR202504-0008 | B9: PP202504-0008 | C9: 2025-04-08 | D9: RM-OAN-AS-55102 | E9: 245 | F9: 2025-04-15 | G9: CE
A10: PR202504-0009 | B10: PP202504-0009 | C10: 2025-04-09 | D10: RM-DIK-ET-88412 | E10: 248 | F10: 2025-04-17 | G10: CE
A11: PR202504-0010 | B11: PP202504-0010 | C11: 2025-04-10 | D11: INT-KET-INS-145120 | E11: 250 | F11: 2025-04-19 | G11: CE
A12: PR202504-0011 | B12: PP202504-0011 | C12: 2025-04-11 | D12: INT-DKD-INT-342781 | E12: 253 | F12: 2025-04-21 | G12: CE
A13: PR202504-0012 | B13: PP202504-0012 | C13: 2025-04-12 | D13: INT-ARY-INT-558903 | E13: 255 | F13: 2025-04-23 | G13: CE
... A361: PR202504-0360 | B361: PP202504-0033 | C361: 2025-04-30 | D361: RM-ETH-AL-64241 | E361: 72 | F361: 2025-05-09 | G361: CE
A362: PR202505-0361 | B362: PP202505-0001 | C362: 45778 | D362: RM-ETH-AL-64175 | E362: 73 | F362: 45785 | G362: CE
A363: PR202505-0362 | B363: PP202505-0002 | C363: 45779 | D363: RM-AAC-GL-23011 | E363: 74 | F363: 45787 | G363: CE
A364: PR202505-0363 | B364: PP202505-0003 | C364: 45780 | D364: RM-BUT-NB-51720 | E364: 74 | F364: 45789 | G364: CE
A365: PR202505-0364 | B365: PP202505-0004 | C365: 45781 | D365: RM-ETL-AC-11804 | E365: 75 | F365: 45791 | G365: CE
A366: PR202505-0365 | B366: PP202505-0005 | C366: 45782 | D366: RM-MTH-AA-40218 | E366: 238 | F366: 45793 | G366: CE
A367: PR202505-0366 | B367: PP202505-0006 | C367: 45783 | D367: RM-ANI-LN-90355 | E367: 240 | F367: 45795 | G367: CE
A368: PR202505-0367 | B368: PP202505-0007 | C368: 45784 | D368: RM-PCA-AN-77210 | E368: 243 | F368: 45797 | G368: CE
A369: PR202505-0368 | B369: PP202505-0008 | C369: 45785 | D369: RM-OAN-AS-55102 | E369: 245 | F369: 45792 | G369: CE
A370: PR202505-0369 | B370: PP202505-0009 | C370: 45786 | D370: RM-DIK-ET-88412 | E370: 248 | F370: 45794 | G370: CE
A371: PR202505-0370 | B371: PP202505-0010 | C371: 45787 | D371: INT-KET-INS-145120 | E371: 250 | F371: 45796 | G371: CE
A372: PR202505-0371 | B372: PP202505-0011 | C372: 45788 | D372: INT-DKD-INT-342781 | E372: 253 | F372: 45798 | G372: CE
A373: PR202505-0372 | B373: PP202505-0012 | C373: 45789 | D373: INT-ARY-INT-558903 | E373: 255 | F373: 45800 | G373: CE
... A4321: PR202603-4320 | B4321: PP202603-0033 | C4321: 46100 | D4321: RM-ETH-AL-64241 | E4321: 72 | F4321: 46109 | G4321: TE

Sheet Plants
A1: plant_code (Primary Key) | B1: plant_name | C1: city | D1: district | E1: state | F1: country | G1: latitude | H1: longitude | I1: business_unit | J1: operating_status | K1: iso_certifications | L1: responsible_care | M1: port_proximity_km | N1: storage_tankage_kl | O1: hazardous_waste_facility | P1: ehs_notes | Q1: effective_from | R1: status | S1: notes
A2: MHD | B2: Mahad Manufacturing Complex | C2: Mahad | D2: Raigad | E2: Maharashtra | F2: India | G2: 18.083 | H2: 73.416 | I2: Essentials | J2: Active | K2: ISO 9001:2015, ISO 14001:2015, ISO 45001:2018 | L2: Yes | M2: 110 | N2: 8500 | O2: Yes | P2: Solvent handling with VOC controls; DG drum yard; firewater ring main. | Q2: 2020-04-01 | R2: Active | S2: Illustrative site master; aligned to annual report commentary on capacity debottlenecking.
A3: LTE | B3: Lote Parshuram Specialty Site | C3: Lote Parshuram | D3: Ratnagiri | E3: Maharashtra | F3: India | G3: 17.85 | H3: 73.225 | I3: Specialties | J3: Active | K3: ISO 9001:2015, ISO 14001:2015, ISO 45001:2018 | L3: Yes | M3: 45 | N3: 2500 | O3: Yes | P3: Fluoro/DG segregation; nitrogen blanketing; low-temp storage (2-8°C) for sensitive inputs. | Q3: 2021-07-01 | R3: Active | S3: Illustrative; aligned to annual report commentary on specialty expansions and compliance.
A4: DHJ | B4: Dahej Greenfield Project | C4: Dahej | D4: Bharuch | E4: Gujarat | F4: India | G4: 21.705 | H4: 72.624 | I4: Mixed | J4: Planned | K4: Planned: ISO 9001:2015, ISO 14001:2015, ISO 45001:2018 | L4: No | M4: 15 | N4: 6000 | O4: Planned | P4: Planned VOC abatement; hazardous area classification; port-linked bulk logistics. | Q4: 2026-01-01 | R4: Planned | S4: Illustrative greenfield entry; aligned to commentary on future multi-product flexibility.
A5: DST | B5: External Distillery Cluster (Partner) | C5: N/A | D5: N/A | E5: Maharashtra | F5: India | G5: 0 | H5: 0 | I5: External | J5: External | K5: N/A | L5: N/A | M5: 0 | N5: 0 | O5: N/A | P5: Partner feedstock sourcing; QA sampling at receipt; limited EHS control beyond supplier audits. | Q5: 2020-01-01 | R5: External | S5: Illustrative partner location for ethanol/feedstock; aligned to commentary on backward integration sourcing.
A6: TPL | B6: Tarapur Tolling / Third-Party Site | C6: Tarapur | D6: Palghar | E6: Maharashtra | F6: India | G6: 19.862 | H6: 72.742 | I6: External | J6: External | K6: ISO 9001:2015 | L6: No | M6: 70 | N6: 1200 | O6: No | P6: Tolling operations under contract; DG packing per SOP; batch traceability via COA. | Q6: 2022-04-01 | R6: External | S6: Illustrative tolling site to manage peak demand; aligned to annual report commentary on flexible manufacturing.

Sheet Lines
A1: line_id (Primary Key) | B1: line_name | C1: plant_id (FK) | D1: area | E1: family | F1: process | G1: design_capacity_tpd | H1: pack_out | I1: hazard_zone | J1: commissioned_on | K1: status | L1: notes
A2: LINE_MHD_EA_TRAIN1 | B2: Ethyl Acetate Train 1 | C2: MHD | D2: Solvents Block A | E2: ACETYL | F2: Continuous Esterification | G2: 220 | H2: ISO20,IBC1KL,BULK | I2: Flammable (Zone 2) | J2: 42156 | K2: Active | L2: High-volume ester line; VOC abatement; illustrative
A3: LINE_MHD_EA_TRAIN2 | B3: Ethyl Acetate Train 2 | C3: MHD | D3: Solvents Block A | E3: ACETYL | F3: Continuous Esterification | G3: 260 | H3: ISO20,IBC1KL,BULK | I3: Flammable (Zone 2) | J3: 43388 | K3: Active | L3: Debottlenecked for export grades; illustrative
A4: LINE_MHD_AA_ANHY | B4: Acetic Anhydride Unit | C4: MHD | D4: Acid Anhydrides | E4: ACETYL | F4: Continuous Dehydration/Distillation | G4: 180 | H4: ISO20,DR200_UN,BULK | I4: Corrosive/Flammable | J4: 42449 | K4: Active | L4: Corrosive service metallurgy; UN packing; illustrative
A5: LINE_MHD_BA_BATCH1 | B5: Butyl Acetate Batch 1 | C5: MHD | D5: Solvents Block B | E5: ACETYL | F5: Batch Esterification | G5: 120 | H5: ISO20,DR200,IBC1KL | I5: Flammable (Zone 2) | J5: 41948 | K5: Active | L5: Flexible campaign scheduling; illustrative
A6: LINE_MHD_AAEM_REACT1 | B6: AAEM Reactor Line 1 | C6: MHD | D6: Acrylates Area | E6: ACETYL | F6: Batch Esterification/Polymerizable | G6: 85 | H6: IBC1KL,DR200 | I6: Corrosive/Flammable | J6: 44440 | K6: Active | L6: Inhibitor dosing & low-temp controls; illustrative
A7: LINE_LTE_DKD_ESTER1 | B7: DKD Ester Line 1 | C7: LTE | D7: DKD Block | E7: DKD | F7: Condensation/Isolation | G7: 22 | H7: DR200,DR200_UN,IBC1KL | I7: Flammable (Zone 2) | J7: 43506 | K7: Active | L7: Moisture-sensitive handling; chilled utilities; illustrative
A8: LINE_LTE_DKD_ESTER2 | B8: DKD Ester Line 2 | C8: LTE | D8: DKD Block | E8: DKD | F8: Condensation/Isolation | G8: 28 | H8: DR200,DR200_UN,IBC1KL | I8: Flammable (Zone 2) | J8: 44798 | K8: Active | L8: Higher purity campaigns; illustrative
A9: LINE_LTE_ARY_1 | B9: Arylides Intermediate Line 1 | C9: LTE | D9: Arylides Block | E9: ARYLIDE | F9: Batch Condensation/Isolation | G9: 18 | H9: BAG25,DR200_UN | I9: Dust/Combustible | J9: 42867 | K9: Active | L9: Dust collection & ATEX practices; illustrative
A10: LINE_LTE_ARY_2 | B10: Arylides Intermediate Line 2 | C10: LTE | D10: Arylides Block | E10: ARYLIDE | F10: Batch Condensation/Isolation | G10: 24 | H10: BAG25,DR200_UN | I10: Dust/Combustible | J10: 44944 | K10: Active | L10: Wet cake handling; fast turnaround; illustrative
A11: LINE_LTE_FLR_BLOCK200 | B11: Fluoro Block Reactor 200L | C11: LTE | D11: Fluoro Suites | E11: FLUORO | F11: Electrochemical Fluorination | G11: 5 | H11: BAG25,DR200_UN | I11: DG (Fluoro) | J11: 44042 | K11: Active | L11: DG segregation; dedicated ventilation; illustrative
A12: LINE_LTE_FLR_BLOCK500 | B12: Fluoro Block Reactor 500L | C12: LTE | D12: Fluoro Suites | E12: FLUORO | F12: Electrochemical Fluorination | G12: 8 | H12: BAG25,DR200_UN | I12: DG (Fluoro) | J12: 45383 | K12: Active | L12: Scale-up for export blocks; illustrative
A13: LINE_DHJ_SOLV_TRAIN1 | B13: Dahej Solvents Train 1 | C13: DHJ | D13: Bulk Solvents | E13: ACETYL | F13: Continuous Esterification | G13: 300 | H13: ISO20,BULK | I13: Flammable (Zone 2) | J13: 46082 | K13: Planned | L13: Greenfield capacity; port-linked logistics; illustrative
... A17: LINE_LTE_DKD_AMIDE1 | B17: DKD Amidation Line 1 | C17: LTE | D17: DKD Block | E17: DKD | F17: Amidation/Condensation | G17: 15 | H17: DR200,IBC1KL | I17: Flammable (Zone 2) | J17: 44136 | K17: Active | L17: Specialty DKD derivatives line; campaign-based; illustrative

Sheet Production Runs
A1: Production Run ID (PK) | B1: Production Plan ID (FK) | C1: Line ID (FK) | D1: SKU ID (FK) | E1: Quantity Produced | F1: Scrappage (%) | G1: Quality Defects (%) | H1: Usable Quantity | I1: Start DateTime | J1: End DateTime
A2: RUN202504-0001 | B2: PP202504-0001 | C2: LINE_MHD_EA_TRAIN1 | D2: ESS-ACETYL-ETHACE-LM-98.5-NEAT-BULK-DST | E2: 188 | F2: 0.001 | G2: 0.002 | H2: 187.4 | I2: 45748 | J2: 45748
A3: RUN202504-0002 | B3: PP202504-0002 | C3: LINE_MHD_EA_TRAIN2 | D3: ESS-ACETYL-ETHACE-LM-98.5-NEAT-BULK-DST | E3: 190 | F3: 0.002 | G3: 0.003 | H3: 189.1 | I3: 45749 | J3: 45749
A4: RUN202504-0003 | B4: PP202504-0003 | C4: LINE_MHD_AA_ANHY | D4: ESS-ACETYL-ETHACE-LM-98.5-NEAT-BULK-DST | E4: 192 | F4: 0.003 | G4: 0.004 | H4: 190.7 | I4: 45750 | J4: 45750
A5: RUN202504-0004 | B5: PP202504-0004 | C5: LINE_MHD_BA_BATCH1 | D5: SPI-ACETYL-ACEANH-PH-98.6-NEAT-DR200_UN-MHD | E5: 194 | F5: 0.004 | G5: 0.005 | H5: 192.3 | I5: 45751 | J5: 45751
A6: RUN202504-0005 | B6: PP202504-0005 | C6: LINE_MHD_AAEM_REACT1 | D6: SPI-ACETYL-ACEANH-PH-98.6-NEAT-DR200_UN-MHD | E6: 196 | F6: 0.005 | G6: 0.006 | H6: 193.8 | I6: 45752 | J6: 45753
A7: RUN202504-0006 | B7: PP202504-0006 | C7: LINE_LTE_DKD_ESTER1 | D7: SPI-ACETYL-ACEANH-PH-98.6-NEAT-DR200_UN-MHD | E7: 198 | F7: 0.006 | G7: 0.007 | H7: 195.4 | I7: 45753 | J7: 45754
A8: RUN202504-0007 | B8: PP202504-0007 | C8: LINE_LTE_DKD_ESTER2 | D8: SPI-ACETYL-ACE-IND-98.4-NEAT-ISO20-LTE | E8: 200 | F8: 0.007 | G8: 0.008 | H8: 197 | I8: 45754 | J8: 45755
A9: RUN202504-0008 | B9: PP202504-0008 | C9: LINE_LTE_ARY_1 | D9: SPI-ACETYL-ACE-IND-98.4-NEAT-ISO20-LTE | E9: 202 | F9: 0.008 | G9: 0.009 | H9: 198.6 | I9: 45755 | J9: 45756
A10: RUN202504-0009 | B10: PP202504-0009 | C10: LINE_LTE_ARY_2 | D10: SPI-ACETYL-ACE-IND-98.4-NEAT-ISO20-LTE | E10: 204 | F10: 0.009 | G10: 0.01 | H10: 200.1 | I10: 45756 | J10: 45757
A11: RUN202504-0010 | B11: PP202504-0010 | C11: LINE_LTE_FLR_BLOCK200 | D11: ESS-ACETYL-BUTACE-TECH-98.3-NEAT-DR200-DHJ | E11: 206 | F11: 0.01 | G11: 0.011 | H11: 201.7 | I11: 45757 | J11: 45758
A12: RUN202504-0011 | B12: PP202504-0011 | C12: LINE_LTE_FLR_BLOCK500 | D12: ESS-ACETYL-BUTACE-TECH-98.3-NEAT-DR200-DHJ | E12: 208 | F12: 0.011 | G12: 0.012 | H12: 203.2 | I12: 45758 | J12: 45759
A13: RUN202504-0012 | B13: PP202504-0012 | C13: LINE_DHJ_SOLV_TRAIN1 | D13: ESS-ACETYL-BUTACE-TECH-98.3-NEAT-DR200-DHJ | E13: 210 | F13: 0.012 | G13: 0.013 | H13: 204.8 | I13: 45759 | J13: 45760
... A302: RUN202504-0301 | B302: PP202504-0083 | C302: LINE_DHJ_DKD_UNIT1 | D302: ESS-ACETYL-ETHACE-LM-99.7-NEAT-IBC1KL-DST | E302: 188 | F302: 0.001 | G302: 0.002 | H302: 187.4 | I302: 45748 | J302: 45748
A303: RUN202504-0302 | C303: LINE_DST_FEED_BLEND | D303: ESS-ACETYL-ETHACE-LM-99.7-NEAT-IBC1KL-DST | E303: 190 | F303: 0.002 | G303: 0.003 | H303: 189.1 | I303: 45749 | J303: 45749
A304: RUN202504-0303 | C304: LINE_MHD_SOL_BLEND | D304: ESS-ACETYL-ETHACE-LM-99.7-NEAT-IBC1KL-DST | E304: 192 | F304: 0.003 | G304: 0.004 | H304: 190.7 | I304: 45750 | J304: 45751
A305: RUN202504-0304 | C305: LINE_LTE_DKD_AMIDE1 | D305: ESS-ACETYL-ACEANH-IND-98.8-NEAT-BULK-MHD | E305: 194 | F305: 0.004 | G305: 0.005 | H305: 192.3 | I305: 45751 | J305: 45752
A306: RUN202504-0305 | C306: LINE_MHD_EA_TRAIN1 | D306: ESS-ACETYL-ACEANH-IND-98.8-NEAT-BULK-MHD | E306: 196 | F306: 0.005 | G306: 0.006 | H306: 193.8 | I306: 45752 | J306: 45752
A307: RUN202504-0306 | C307: LINE_MHD_EA_TRAIN2 | D307: ESS-ACETYL-ACEANH-IND-98.8-NEAT-BULK-MHD | E307: 198 | F307: 0.006 | G307: 0.007 | H307: 195.4 | I307: 45753 | J307: 45753
A308: RUN202504-0307 | C308: LINE_MHD_AA_ANHY | D308: ESS-ACETYL-ACE-PH-98.5-NEAT-DR200_UN-LTE | E308: 200 | F308: 0.007 | G308: 0.008 | H308: 197 | I308: 45754 | J308: 45755
A309: RUN202504-0308 | C309: LINE_MHD_BA_BATCH1 | D309: ESS-ACETYL-ACE-PH-98.5-NEAT-DR200_UN-LTE | E309: 202 | F309: 0.008 | G309: 0.009 | H309: 198.6 | I309: 45755 | J309: 45756
A310: RUN202504-0309 | C310: LINE_MHD_AAEM_REACT1 | D310: ESS-ACETYL-ACE-PH-98.5-NEAT-DR200_UN-LTE | E310: 204 | F310: 0.009 | G310: 0.01 | H310: 200.1 | I310: 45756 | J310: 45757
A311: RUN202504-0310 | C311: LINE_LTE_DKD_ESTER1 | D311: ESS-ACETYL-BUTACE-IND-98.9-NEAT-ISO20-DHJ | E311: 206 | F311: 0.01 | G311: 0.011 | H311: 201.7 | I311: 45757 | J311: 45758
A312: RUN202504-0311 | C312: LINE_LTE_DKD_ESTER2 | D312: ESS-ACETYL-BUTACE-IND-98.9-NEAT-ISO20-DHJ | E312: 208 | F312: 0.011 | G312: 0.012 | H312: 203.2 | I312: 45758 | J312: 45759
A313: RUN202505-0312 | B313: PP202505-0001 | C313: LINE_MHD_EA_TRAIN1 | D313: ESS-ACETYL-ETHACE-LM-98.5-NEAT-BULK-DST | E313: 210 | F313: 0.001 | G313: 0.002 | H313: 209.4 | I313: 45778 | J313: 45778
A314: RUN202505-0313 | B314: PP202505-0002 | C314: LINE_MHD_EA_TRAIN2 | D314: ESS-ACETYL-ETHACE-LM-98.5-NEAT-BULK-DST | E314: 212 | F314: 0.002 | G314: 0.003 | H314: 210.9 | I314: 45779 | J314: 45779
A315: RUN202505-0314 | B315: PP202505-0003 | C315: LINE_MHD_AA_ANHY | D315: ESS-ACETYL-ETHACE-LM-98.5-NEAT-BULK-DST | E315: 214 | F315: 0.003 | G315: 0.004 | H315: 212.5 | I315: 45780 | J315: 45780
A316: RUN202505-0315 | B316: PP202505-0004 | C316: LINE_MHD_BA_BATCH1 | D316: SPI-ACETYL-ACEANH-PH-98.6-NEAT-DR200_UN-MHD | E316: 186 | F316: 0.004 | G316: 0.005 | H316: 184.3 | I316: 45781 | J316: 45781
A317: RUN202505-0316 | B317: PP202505-0005 | C317: LINE_MHD_AAEM_REACT1 | D317: SPI-ACETYL-ACEANH-PH-98.6-NEAT-DR200_UN-MHD | E317: 188 | F317: 0.005 | G317: 0.006 | H317: 185.9 | I317: 45782 | J317: 45783
A318: RUN202505-0317 | B318: PP202505-0006 | C318: LINE_LTE_DKD_ESTER1 | D318: SPI-ACETYL-ACEANH-PH-98.6-NEAT-DR200_UN-MHD | E318: 190 | F318: 0.006 | G318: 0.007 | H318: 187.5 | I318: 45783 | J318: 45784
A319: RUN202505-0318 | B319: PP202505-0007 | C319: LINE_LTE_DKD_ESTER2 | D319: SPI-ACETYL-ACE-IND-98.4-NEAT-ISO20-LTE | E319: 192 | F319: 0.007 | G319: 0.008 | H319: 189.1 | I319: 45784 | J319: 45785
A320: RUN202505-0319 | B320: PP202505-0008 | C320: LINE_LTE_ARY_1 | D320: SPI-ACETYL-ACE-IND-98.4-NEAT-ISO20-LTE | E320: 194 | F320: 0.008 | G320: 0.009 | H320: 190.7 | I320: 45785 | J320: 45786
A321: RUN202505-0320 | B321: PP202505-0009 | C321: LINE_LTE_ARY_2 | D321: SPI-ACETYL-ACE-IND-98.4-NEAT-ISO20-LTE | E321: 196 | F321: 0.009 | G321: 0.01 | H321: 192.3 | I321: 45786 | J321: 45787
A322: RUN202505-0321 | B322: PP202505-0010 | C322: LINE_LTE_FLR_BLOCK200 | D322: ESS-ACETYL-BUTACE-TECH-98.3-NEAT-DR200-DHJ | E322: 198 | F322: 0.01 | G322: 0.011 | H322: 193.9 | I322: 45787 | J322: 45788
A323: RUN202505-0322 | B323: PP202505-0011 | C323: LINE_LTE_FLR_BLOCK500 | D323: ESS-ACETYL-BUTACE-TECH-98.3-NEAT-DR200-DHJ | E323: 200 | F323: 0.011 | G323: 0.012 | H323: 195.4 | I323: 45788 | J323: 45789
A324: RUN202505-0323 | B324: PP202505-0012 | C324: LINE_DHJ_SOLV_TRAIN1 | D324: ESS-ACETYL-BUTACE-TECH-98.3-NEAT-DR200-DHJ | E324: 202 | F324: 0.012 | G324: 0.013 | H324: 197 | I324: 45789 | J324: 45790
... A613: RUN202505-0612 | B613: PP202505-0083 | C613: LINE_DHJ_DKD_UNIT1 | D613: ESS-ACETYL-ETHACE-LM-99.7-NEAT-IBC1KL-DST | E613: 210 | F613: 0.001 | G613: 0.002 | H613: 209.4 | I613: 45799 | J613: 45799
A614: RUN202505-0613 | C614: LINE_DST_FEED_BLEND | D614: ESS-ACETYL-ETHACE-LM-99.7-NEAT-IBC1KL-DST | E614: 212 | F614: 0.002 | G614: 0.003 | H614: 210.9 | I614: 45800 | J614: 45800
A615: RUN202505-0614 | C615: LINE_MHD_SOL_BLEND | D615: ESS-ACETYL-ETHACE-LM-99.7-NEAT-IBC1KL-DST | E615: 214 | F615: 0.003 | G615: 0.004 | H615: 212.5 | I615: 45801 | J615: 45802
A616: RUN202505-0615 | C616: LINE_LTE_DKD_AMIDE1 | D616: ESS-ACETYL-ACEANH-IND-98.8-NEAT-BULK-MHD | E616: 186 | F616: 0.004 | G616: 0.005 | H616: 184.3 | I616: 45802 | J616: 45803
A617: RUN202505-0616 | C617: LINE_MHD_EA_TRAIN1 | D617: ESS-ACETYL-ACEANH-IND-98.8-NEAT-BULK-MHD | E617: 188 | F617: 0.005 | G617: 0.006 | H617: 185.9 | I617: 45803 | J617: 45803
A618: RUN202505-0617 | C618: LINE_MHD_EA_TRAIN2 | D618: ESS-ACETYL-ACEANH-IND-98.8-NEAT-BULK-MHD | E618: 190 | F618: 0.006 | G618: 0.007 | H618: 187.5 | I618: 45804 | J618: 45804
A619: RUN202505-0618 | C619: LINE_MHD_AA_ANHY | D619: ESS-ACETYL-ACE-PH-98.5-NEAT-DR200_UN-LTE | E619: 192 | F619: 0.007 | G619: 0.008 | H619: 189.1 | I619: 45805 | J619: 45806
A620: RUN202505-0619 | C620: LINE_MHD_BA_BATCH1 | D620: ESS-ACETYL-ACE-PH-98.5-NEAT-DR200_UN-LTE | E620: 194 | F620: 0.008 | G620: 0.009 | H620: 190.7 | I620: 45806 | J620: 45807
A621: RUN202505-0620 | C621: LINE_MHD_AAEM_REACT1 | D621: ESS-ACETYL-ACE-PH-98.5-NEAT-DR200_UN-LTE | E621: 196 | F621: 0.009 | G621: 0.01 | H621: 192.3 | I621: 45807 | J621: 45808
A622: RUN202505-0621 | C622: LINE_LTE_DKD_ESTER1 | D622: ESS-ACETYL-BUTACE-IND-98.9-NEAT-ISO20-DHJ | E622: 198 | F622: 0.01 | G622: 0.011 | H622: 193.9 | I622: 45808 | J622: 45808
A623: RUN202505-0622 | C623: LINE_LTE_DKD_ESTER2 | D623: ESS-ACETYL-BUTACE-IND-98.9-NEAT-ISO20-DHJ | E623: 200 | F623: 0.011 | G623: 0.012 | H623: 195.4 | I623: 45778 | J623: 45779
A624: RUN202506-0623 | B624: PP202506-0001 | C624: LINE_MHD_EA_TRAIN1 | D624: ESS-ACETYL-ETHACE-LM-98.5-NEAT-BULK-DST | E624: 202 | F624: 0.001 | G624: 0.002 | H624: 201.4 | I624: 45809 | J624: 45809
A625: RUN202506-0624 | B625: PP202506-0002 | C625: LINE_MHD_EA_TRAIN2 | D625: ESS-ACETYL-ETHACE-LM-98.5-NEAT-BULK-DST | E625: 204 | F625: 0.002 | G625: 0.003 | H625: 203 | I625: 45810 | J625: 45810
A626: RUN202506-0625 | B626: PP202506-0003 | C626: LINE_MHD_AA_ANHY | D626: ESS-ACETYL-ETHACE-LM-98.5-NEAT-BULK-DST | E626: 206 | F626: 0.003 | G626: 0.004 | H626: 204.6 | I626: 45811 | J626: 45811
A627: RUN202506-0626 | B627: PP202506-0004 | C627: LINE_MHD_BA_BATCH1 | D627: SPI-ACETYL-ACEANH-PH-98.6-NEAT-DR200_UN-MHD | E627: 208 | F627: 0.004 | G627: 0.005 | H627: 206.1 | I627: 45812 | J627: 45812
A628: RUN202506-0627 | B628: PP202506-0005 | C628: LINE_MHD_AAEM_REACT1 | D628: SPI-ACETYL-ACEANH-PH-98.6-NEAT-DR200_UN-MHD | E628: 210 | F628: 0.005 | G628: 0.006 | H628: 207.7 | I628: 45813 | J628: 45814
A629: RUN202506-0628 | B629: PP202506-0006 | C629: LINE_LTE_DKD_ESTER1 | D629: SPI-ACETYL-ACEANH-PH-98.6-NEAT-DR200_UN-MHD | E629: 212 | F629: 0.006 | G629: 0.007 | H629: 209.3 | I629: 45814 | J629: 45815
A630: RUN202506-0629 | B630: PP202506-0007 | C630: LINE_LTE_DKD_ESTER2 | D630: SPI-ACETYL-ACE-IND-98.4-NEAT-ISO20-LTE | E630: 214 | F630: 0.007 | G630: 0.008 | H630: 210.8 | I630: 45815 | J630: 45816
A631: RUN202506-0630 | B631: PP202506-0008 | C631: LINE_LTE_ARY_1 | D631: SPI-ACETYL-ACE-IND-98.4-NEAT-ISO20-LTE | E631: 186 | F631: 0.008 | G631: 0.009 | H631: 182.9 | I631: 45816 | J631: 45817
A632: RUN202506-0631 | B632: PP202506-0009 | C632: LINE_LTE_ARY_2 | D632: SPI-ACETYL-ACE-IND-98.4-NEAT-ISO20-LTE | E632: 188 | F632: 0.009 | G632: 0.01 | H632: 184.4 | I632: 45817 | J632: 45818
A633: RUN202506-0632 | B633: PP202506-0010 | C633: LINE_LTE_FLR_BLOCK200 | D633: ESS-ACETYL-BUTACE-TECH-98.3-NEAT-DR200-DHJ | E633: 190 | F633: 0.01 | G633: 0.011 | H633: 186 | I633: 45818 | J633: 45819
A634: RUN202506-0633 | B634: PP202506-0011 | C634: LINE_LTE_FLR_BLOCK500 | D634: ESS-ACETYL-BUTACE-TECH-98.3-NEAT-DR200-DHJ | E634: 192 | F634: 0.011 | G634: 0.012 | H634: 187.6 | I634: 45819 | J634: 45820
A635: RUN202506-0634 | B635: PP202506-0012 | C635: LINE_DHJ_SOLV_TRAIN1 | D635: ESS-ACETYL-BUTACE-TECH-98.3-NEAT-DR200-DHJ | E635: 194 | F635: 0.012 | G635: 0.013 | H635: 189.2 | I635: 45820 | J635: 45821
... A924: RUN202506-0923 | B924: PP202506-0083 | C924: LINE_DHJ_DKD_UNIT1 | D924: ESS-ACETYL-ETHACE-LM-99.7-NEAT-IBC1KL-DST | E924: 202 | F924: 0.001 | G924: 0.002 | H924: 201.4 | I924: 45809 | J924: 45809
A925: RUN202506-0924 | C925: LINE_DST_FEED_BLEND | D925: ESS-ACETYL-ETHACE-LM-99.7-NEAT-IBC1KL-DST | E925: 204 | F925: 0.002 | G925: 0.003 | H925: 203 | I925: 45810 | J925: 45810
A926: RUN202506-0925 | C926: LINE_MHD_SOL_BLEND | D926: ESS-ACETYL-ETHACE-LM-99.7-NEAT-IBC1KL-DST | E926: 206 | F926: 0.003 | G926: 0.004 | H926: 204.6 | I926: 45811 | J926: 45812
A927: RUN202506-0926 | C927: LINE_LTE_DKD_AMIDE1 | D927: ESS-ACETYL-ACEANH-IND-98.8-NEAT-BULK-MHD | E927: 208 | F927: 0.004 | G927: 0.005 | H927: 206.1 | I927: 45812 | J927: 45813
A928: RUN202506-0927 | C928: LINE_MHD_EA_TRAIN1 | D928: ESS-ACETYL-ACEANH-IND-98.8-NEAT-BULK-MHD | E928: 210 | F928: 0.005 | G928: 0.006 | H928: 207.7 | I928: 45813 | J928: 45813
A929: RUN202506-0928 | C929: LINE_MHD_EA_TRAIN2 | D929: ESS-ACETYL-ACEANH-IND-98.8-NEAT-BULK-MHD | E929: 212 | F929: 0.006 | G929: 0.007 | H929: 209.3 | I929: 45814 | J929: 45814
A930: RUN202506-0929 | C930: LINE_MHD_AA_ANHY | D930: ESS-ACETYL-ACE-PH-98.5-NEAT-DR200_UN-LTE | E930: 214 | F930: 0.007 | G930: 0.008 | H930: 210.8 | I930: 45815 | J930: 45816
A931: RUN202506-0930 | C931: LINE_MHD_BA_BATCH1 | D931: ESS-ACETYL-ACE-PH-98.5-NEAT-DR200_UN-LTE | E931: 186 | F931: 0.008 | G931: 0.009 | H931: 182.9 | I931: 45816 | J931: 45817
A932: RUN202506-0931 | C932: LINE_MHD_AAEM_REACT1 | D932: ESS-ACETYL-ACE-PH-98.5-NEAT-DR200_UN-LTE | E932: 188 | F932: 0.009 | G932: 0.01 | H932: 184.4 | I932: 45817 | J932: 45818
A933: RUN202506-0932 | C933: LINE_LTE_DKD_ESTER1 | D933: ESS-ACETYL-BUTACE-IND-98.9-NEAT-ISO20-DHJ | E933: 190 | F933: 0.01 | G933: 0.011 | H933: 186 | I933: 45818 | J933: 45819
A934: RUN202506-0933 | C934: LINE_LTE_DKD_ESTER2 | D934: ESS-ACETYL-BUTACE-IND-98.9-NEAT-ISO20-DHJ | E934: 192 | F934: 0.011 | G934: 0.012 | H934: 187.6 | I934: 45819 | J934: 45820
A935: RUN202507-0934 | B935: PP202507-0001 | C935: LINE_MHD_EA_TRAIN1 | D935: ESS-ACETYL-ETHACE-LM-98.5-NEAT-BULK-DST | E935: 194 | F935: 0.001 | G935: 0.002 | H935: 193.4 | I935: 45839 | J935: 45839
A936: RUN202507-0935 | B936: PP202507-0002 | C936: LINE_MHD_EA_TRAIN2 | D936: ESS-ACETYL-ETHACE-LM-98.5-NEAT-BULK-DST | E936: 196 | F936: 0.002 | G936: 0.003 | H936: 195 | I936: 45840 | J936: 45840
A937: RUN202507-0936 | B937: PP202507-0003 | C937: LINE_MHD_AA_ANHY | D937: ESS-ACETYL-ETHACE-LM-98.5-NEAT-BULK-DST | E937: 198 | F937: 0.003 | G937: 0.004 | H937: 196.6 | I937: 45841 | J937: 45841
A938: RUN202507-0937 | B938: PP202507-0004 | C938: LINE_MHD_BA_BATCH1 | D938: SPI-ACETYL-ACEANH-PH-98.6-NEAT-DR200_UN-MHD | E938: 200 | F938: 0.004 | G938: 0.005 | H938: 198.2 | I938: 45842 | J938: 45842
A939: RUN202507-0938 | B939: PP202507-0005 | C939: LINE_MHD_AAEM_REACT1 | D939: SPI-ACETYL-ACEANH-PH-98.6-NEAT-DR200_UN-MHD | E939: 202 | F939: 0.005 | G939: 0.006 | H939: 199.8 | I939: 45843 | J939: 45844
A940: RUN202507-0939 | B940: PP202507-0006 | C940: LINE_LTE_DKD_ESTER1 | D940: SPI-ACETYL-ACEANH-PH-98.6-NEAT-DR200_UN-MHD | E940: 204 | F940: 0.006 | G940: 0.007 | H940: 201.4 | I940: 45844 | J940: 45845
A941: RUN202507-0940 | B941: PP202507-0007 | C941: LINE_LTE_DKD_ESTER2 | D941: SPI-ACETYL-ACE-IND-98.4-NEAT-ISO20-LTE | E941: 206 | F941: 0.007 | G941: 0.008 | H941: 202.9 | I941: 45845 | J941: 45846
A942: RUN202507-0941 | B942: PP202507-0008 | C942: LINE_LTE_ARY_1 | D942: SPI-ACETYL-ACE-IND-98.4-NEAT-ISO20-LTE | E942: 208 | F942: 0.008 | G942: 0.009 | H942: 204.5 | I942: 45846 | J942: 45847
A943: RUN202507-0942 | B943: PP202507-0009 | C943: LINE_LTE_ARY_2 | D943: SPI-ACETYL-ACE-IND-98.4-NEAT-ISO20-LTE | E943: 210 | F943: 0.009 | G943: 0.01 | H943: 206 | I943: 45847 | J943: 45848
A944: RUN202507-0943 | B944: PP202507-0010 | C944: LINE_LTE_FLR_BLOCK200 | D944: ESS-ACETYL-BUTACE-TECH-98.3-NEAT-DR200-DHJ | E944: 212 | F944: 0.01 | G944: 0.011 | H944: 207.6 | I944: 45848 | J944: 45849
A945: RUN202507-0944 | B945: PP202507-0011 | C945: LINE_LTE_FLR_BLOCK500 | D945: ESS-ACETYL-BUTACE-TECH-98.3-NEAT-DR200-DHJ | E945: 214 | F945: 0.011 | G945: 0.012 | H945: 209.1 | I945: 45849 | J945: 45850
A946: RUN202507-0945 | B946: PP202507-0012 | C946: LINE_DHJ_SOLV_TRAIN1 | D946: ESS-ACETYL-BUTACE-TECH-98.3-NEAT-DR200-DHJ | E946: 186 | F946: 0.012 | G946: 0.013 | H946: 181.4 | I946: 45850 | J946: 45851
... A1235: RUN202507-1234 | B1235: PP202507-0083 | C1235: LINE_DHJ_DKD_UNIT1 | D1235: ESS-ACETYL-ETHACE-LM-99.7-NEAT-IBC1KL-DST | E1235: 194 | F1235: 0.001 | G1235: 0.002 | H1235: 193.4 | I1235: 45860 | J1235: 45860
A1236: RUN202507-1235 | C1236: LINE_DST_FEED_BLEND | D1236: ESS-ACETYL-ETHACE-LM-99.7-NEAT-IBC1KL-DST | E1236: 196 | F1236: 0.002 | G1236: 0.003 | H1236: 195 | I1236: 45861 | J1236: 45861
A1237: RUN202507-1236 | C1237: LINE_MHD_SOL_BLEND | D1237: ESS-ACETYL-ETHACE-LM-99.7-NEAT-IBC1KL-DST | E1237: 198 | F1237: 0.003 | G1237: 0.004 | H1237: 196.6 | I1237: 45862 | J1237: 45863
A1238: RUN202507-1237 | C1238: LINE_LTE_DKD_AMIDE1 | D1238: ESS-ACETYL-ACEANH-IND-98.8-NEAT-BULK-MHD | E1238: 200 | F1238: 0.004 | G1238: 0.005 | H1238: 198.2 | I1238: 45863 | J1238: 45864
A1239: RUN202507-1238 | C1239: LINE_MHD_EA_TRAIN1 | D1239: ESS-ACETYL-ACEANH-IND-98.8-NEAT-BULK-MHD | E1239: 202 | F1239: 0.005 | G1239: 0.006 | H1239: 199.8 | I1239: 45864 | J1239: 45864
A1240: RUN202507-1239 | C1240: LINE_MHD_EA_TRAIN2 | D1240: ESS-ACETYL-ACEANH-IND-98.8-NEAT-BULK-MHD | E1240: 204 | F1240: 0.006 | G1240: 0.007 | H1240: 201.4 | I1240: 45865 | J1240: 45865
A1241: RUN202507-1240 | C1241: LINE_MHD_AA_ANHY | D1241: ESS-ACETYL-ACE-PH-98.5-NEAT-DR200_UN-LTE | E1241: 206 | F1241: 0.007 | G1241: 0.008 | H1241: 202.9 | I1241: 45866 | J1241: 45867
A1242: RUN202507-1241 | C1242: LINE_MHD_BA_BATCH1 | D1242: ESS-ACETYL-ACE-PH-98.5-NEAT-DR200_UN-LTE | E1242: 208 | F1242: 0.008 | G1242: 0.009 | H1242: 204.5 | I1242: 45867 | J1242: 45868
A1243: RUN202507-1242 | C1243: LINE_MHD_AAEM_REACT1 | D1243: ESS-ACETYL-ACE-PH-98.5-NEAT-DR200_UN-LTE | E1243: 210 | F1243: 0.009 | G1243: 0.01 | H1243: 206 | I1243: 45868 | J1243: 45869
A1244: RUN202507-1243 | C1244: LINE_LTE_DKD_ESTER1 | D1244: ESS-ACETYL-BUTACE-IND-98.9-NEAT-ISO20-DHJ | E1244: 212 | F1244: 0.01 | G1244: 0.011 | H1244: 207.6 | I1244: 45869 | J1244: 45869
A1245: RUN202507-1244 | C1245: LINE_LTE_DKD_ESTER2 | D1245: ESS-ACETYL-BUTACE-IND-98.9-NEAT-ISO20-DHJ | E1245: 214 | F1245: 0.011 | G1245: 0.012 | H1245: 209.1 | I1245: 45839 | J1245: 45840
A1246: RUN202508-1245 | B1246: PP202508-0001 | C1246: LINE_MHD_EA_TRAIN1 | D1246: ESS-ACETYL-ETHACE-LM-98.5-NEAT-BULK-DST | E1246: 186 | F1246: 0.001 | G1246: 0.002 | H1246: 185.4 | I1246: 45870 | J1246: 45870
A1247: RUN202508-1246 | B1247: PP202508-0002 | C1247: LINE_MHD_EA_TRAIN2 | D1247: ESS-ACETYL-ETHACE-LM-98.5-NEAT-BULK-DST | E1247: 188 | F1247: 0.002 | G1247: 0.003 | H1247: 187.1 | I1247: 45871 | J1247: 45871
A1248: RUN202508-1247 | B1248: PP202508-0003 | C1248: LINE_MHD_AA_ANHY | D1248: ESS-ACETYL-ETHACE-LM-98.5-NEAT-BULK-DST | E1248: 190 | F1248: 0.003 | G1248: 0.004 | H1248: 188.7 | I1248: 45872 | J1248: 45872
A1249: RUN202508-1248 | B1249: PP202508-0004 | C1249: LINE_MHD_BA_BATCH1 | D1249: SPI-ACETYL-ACEANH-PH-98.6-NEAT-DR200_UN-MHD | E1249: 192 | F1249: 0.004 | G1249: 0.005 | H1249: 190.3 | I1249: 45873 | J1249: 45873
A1250: RUN202508-1249 | B1250: PP202508-0005 | C1250: LINE_MHD_AAEM_REACT1 | D1250: SPI-ACETYL-ACEANH-PH-98.6-NEAT-DR200_UN-MHD | E1250: 194 | F1250: 0.005 | G1250: 0.006 | H1250: 191.9 | I1250: 45874 | J1250: 45875
A1251: RUN202508-1250 | B1251: PP202508-0006 | C1251: LINE_LTE_DKD_ESTER1 | D1251: SPI-ACETYL-ACEANH-PH-98.6-NEAT-DR200_UN-MHD | E1251: 196 | F1251: 0.006 | G1251: 0.007 | H1251: 193.5 | I1251: 45875 | J1251: 45876
A1252: RUN202508-1251 | B1252: PP202508-0007 | C1252: LINE_LTE_DKD_ESTER2 | D1252: SPI-ACETYL-ACE-IND-98.4-NEAT-ISO20-LTE | E1252: 198 | F1252: 0.007 | G1252: 0.008 | H1252: 195 | I1252: 45876 | J1252: 45877
...

Sheet Batches
A1: Batch No./Lot No. | B1: Production Run ID (FK) | C1: PR Line Item_ID (FK) | D1: SKU ID (FK) | E1: Quantity | F1: Value (in terms of cost) USD | G1: Date of Delivery / Manufacture
A2: BATFG202504-0001 | B2: RUN202504-0001 | D2: ESS-ACETYL-ETHACE-LM-98.5-NEAT-BULK-DST | E2: 45.5 | F2: 43225 | G2: 45748
A3: BATFG202504-0002 | B3: RUN202504-0002 | D3: ESS-ACETYL-ETHACE-LM-98.5-NEAT-BULK-DST | E3: 46 | F3: 43700 | G3: 45749
A4: BATFG202504-0003 | B4: RUN202504-0003 | D4: ESS-ACETYL-ETHACE-LM-98.5-NEAT-BULK-DST | E4: 46.5 | F4: 44175 | G4: 45750
A5: BATFG202504-0004 | B5: RUN202504-0004 | D5: SPI-ACETYL-ACEANH-PH-98.6-NEAT-DR200_UN-MHD | E5: 47 | F5: 44650 | G5: 45751
A6: BATFG202504-0005 | B6: RUN202504-0005 | D6: SPI-ACETYL-ACEANH-PH-98.6-NEAT-DR200_UN-MHD | E6: 47.5 | F6: 45125 | G6: 45752
A7: BATFG202504-0006 | B7: RUN202504-0006 | D7: SPI-ACETYL-ACEANH-PH-98.6-NEAT-DR200_UN-MHD | E7: 48 | F7: 45600 | G7: 45753
A8: BATFG202504-0007 | B8: RUN202504-0007 | D8: SPI-ACETYL-ACE-IND-98.4-NEAT-ISO20-LTE | E8: 48.5 | F8: 46075 | G8: 45754
A9: BATFG202504-0008 | B9: RUN202504-0008 | D9: SPI-ACETYL-ACE-IND-98.4-NEAT-ISO20-LTE | E9: 49 | F9: 46550 | G9: 45755
A10: BATFG202504-0009 | B10: RUN202504-0009 | D10: SPI-ACETYL-ACE-IND-98.4-NEAT-ISO20-LTE | E10: 49.5 | F10: 47025 | G10: 45756
A11: BATFG202504-0010 | B11: RUN202504-0010 | D11: ESS-ACETYL-BUTACE-TECH-98.3-NEAT-DR200-DHJ | E11: 50 | F11: 47500 | G11: 45757
A12: BATFG202504-0011 | B12: RUN202504-0011 | D12: ESS-ACETYL-BUTACE-TECH-98.3-NEAT-DR200-DHJ | E12: 50.5 | F12: 47975 | G12: 45758
A13: BATFG202504-0012 | B13: RUN202504-0012 | D13: ESS-ACETYL-BUTACE-TECH-98.3-NEAT-DR200-DHJ | E13: 51 | F13: 48450 | G13: 45759
... A401: BATFG202504-0400 | B401: RUN202504-0089 | D401: ESS-ACETYL-BUTACE-IND-98.3-NEAT-ISO20-MHD | E401: 45 | F401: 42750 | G401: 45757
A402: BATFG202504-0401 | B402: RUN202504-0090 | D402: ESS-ACETYL-BUTACE-IND-98.3-NEAT-ISO20-MHD | E402: 45.5 | F402: 43225 | G402: 2025-04-11
A403: BATFG202504-0402 | B403: RUN202504-0091 | D403: ESS-ACETYL-BUTACE-IND-98.3-NEAT-ISO20-MHD | E403: 46 | F403: 43700 | G403: 2025-04-12
A404: BATFG202504-0403 | B404: RUN202504-0092 | D404: SPI-ACETYL-MAA-TECH-98.7-NEAT-DR200-LTE | E404: 46.5 | F404: 44175 | G404: 2025-04-13
A405: BATFG202504-0404 | B405: RUN202504-0093 | D405: SPI-ACETYL-MAA-TECH-98.7-NEAT-DR200-LTE | E405: 47 | F405: 44650 | G405: 2025-04-14
A406: BATFG202504-0405 | B406: RUN202504-0094 | D406: SPI-ACETYL-MAA-TECH-98.7-NEAT-DR200-LTE | E406: 47.5 | F406: 45125 | G406: 2025-04-15
A407: BATFG202504-0406 | B407: RUN202504-0095 | D407: ESS-ACETYL-EAA-INK-98.3-NEAT-DR200-DHJ | E407: 48 | F407: 45600 | G407: 2025-04-16
A408: BATFG202504-0407 | B408: RUN202504-0096 | D408: ESS-ACETYL-EAA-INK-98.3-NEAT-DR200-DHJ | E408: 48.5 | F408: 46075 | G408: 2025-04-17
A409: BATFG202504-0408 | B409: RUN202504-0097 | D409: ESS-ACETYL-EAA-INK-98.3-NEAT-DR200-DHJ | E409: 49 | F409: 46550 | G409: 2025-04-18
A410: BATFG202504-0409 | B410: RUN202504-0098 | D410: ESS-ACETYL-AAEM-PH-99.3-NEAT-BULK-DST | E410: 49.5 | F410: 47025 | G410: 2025-04-19
A411: BATFG202504-0410 | B411: RUN202504-0099 | D411: ESS-ACETYL-AAEM-PH-99.3-NEAT-BULK-DST | E411: 50 | F411: 47500 | G411: 2025-04-20
A412: BATFG202504-0411 | B412: RUN202504-0100 | D412: ESS-ACETYL-AAEM-PH-99.3-NEAT-BULK-DST | E412: 50.5 | F412: 47975 | G412: 2025-04-21
A413: BATFG202504-0412 | B413: RUN202504-0101 | D413: ESS-DKD-DKDINT-LM-98.0-NEAT-DR200-MHD | E413: 51 | F413: 58650 | G413: 2025-04-22
... A501: BATFG202504-0500 | B501: RUN202504-0189 | D501: ESS-ACETYL-AAEM-TECH-98.8-NEAT-BULK-LTE | E501: 45 | F501: 42750 | G501: 2025-04-20
A502: BATFG202505-0501 | B502: RUN202505-0001 | D502: ESS-ACETYL-ETHACE-LM-98.5-NEAT-BULK-DST | E502: 45.5 | F502: 43225 | G502: 45778
A503: BATFG202505-0502 | B503: RUN202505-0002 | D503: ESS-ACETYL-ETHACE-LM-98.5-NEAT-BULK-DST | E503: 46 | F503: 43700 | G503: 45779
A504: BATFG202505-0503 | B504: RUN202505-0003 | D504: ESS-ACETYL-ETHACE-LM-98.5-NEAT-BULK-DST | E504: 46.5 | F504: 44175 | G504: 45780
A505: BATFG202505-0504 | B505: RUN202505-0004 | D505: SPI-ACETYL-ACEANH-PH-98.6-NEAT-DR200_UN-MHD | E505: 47 | F505: 44650 | G505: 45781
A506: BATFG202505-0505 | B506: RUN202505-0005 | D506: SPI-ACETYL-ACEANH-PH-98.6-NEAT-DR200_UN-MHD | E506: 47.5 | F506: 45125 | G506: 45782
A507: BATFG202505-0506 | B507: RUN202505-0006 | D507: SPI-ACETYL-ACEANH-PH-98.6-NEAT-DR200_UN-MHD | E507: 48 | F507: 45600 | G507: 45783
A508: BATFG202505-0507 | B508: RUN202505-0007 | D508: SPI-ACETYL-ACE-IND-98.4-NEAT-ISO20-LTE | E508: 48.5 | F508: 46075 | G508: 45784
A509: BATFG202505-0508 | B509: RUN202505-0008 | D509: SPI-ACETYL-ACE-IND-98.4-NEAT-ISO20-LTE | E509: 49 | F509: 46550 | G509: 45785
A510: BATFG202505-0509 | B510: RUN202505-0009 | D510: SPI-ACETYL-ACE-IND-98.4-NEAT-ISO20-LTE | E510: 49.5 | F510: 47025 | G510: 45786
A511: BATFG202505-0510 | B511: RUN202505-0010 | D511: ESS-ACETYL-BUTACE-TECH-98.3-NEAT-DR200-DHJ | E511: 50 | F511: 47500 | G511: 45787
A512: BATFG202505-0511 | B512: RUN202505-0011 | D512: ESS-ACETYL-BUTACE-TECH-98.3-NEAT-DR200-DHJ | E512: 50.5 | F512: 47975 | G512: 45788
A513: BATFG202505-0512 | B513: RUN202505-0012 | D513: ESS-ACETYL-BUTACE-TECH-98.3-NEAT-DR200-DHJ | E513: 51 | F513: 48450 | G513: 45789
... A6001: BATFG202603-6000 | B6001: RUN202603-0189 | D6001: ESS-ACETYL-AAEM-TECH-98.8-NEAT-BULK-LTE | E6001: 45 | F6001: 42750 | G6001: 46085

Sheet Storage Nodes
A1: node_id (Primary Key) | B1: node_name | C1: node_type | D1: country | E1: city | F1: operator | G1: storage_type | H1: pack_supported | I1: families_supported | J1: dg_classes_supported | K1: licenses | L1: docs_capability | M1: temperature_control | N1: capacity_kl | O1: pallet_positions | P1: throughput_tpm | Q1: latitude | R1: longitude | S1: notes
A2: TNK_EUR_RTM | B2: Rotterdam Tank Terminal | C2: Tank Terminal | D2: Netherlands | E2: Rotterdam | F2: Vopak (illustrative) | G2: Tank | H2: BULK,ISO20 | I2: ACETYL,DKD | J2: 3,8 | K2: ADR,IMDG,Seveso | L2: SDS,COA,REACH,BL | M2: Ambient | N2: 25000 | O2: 0 | P2: 18000 | Q2: 51.955 | R2: 4.142 | S2: EU hub terminal; IMO-ready lanes; illustrative
A3: TNK_EUR_ANT | B3: Antwerp Chemical Tank Farm | C3: Tank Terminal | D3: Belgium | E3: Antwerp | F3: ADPO (illustrative) | G3: Tank | H3: BULK,ISO20 | I3: ACETYL,DKD,ARYLIDE | J3: 3,8 | K3: ADR,IMDG,Seveso | L3: SDS,COA,REACH,CMR | M3: Ambient | N3: 18000 | O3: 0 | P3: 12000 | Q3: 51.26 | R3: 4.4 | S3: Benelux distribution; customs brokerage supported; illustrative
A4: TNK_EUR_GEN | B4: Genoa Port Tank Terminal | C4: Tank Terminal | D4: Italy | E4: Genoa | F4: PSA (illustrative) | G4: Tank | H4: BULK,ISO20 | I4: ACETYL | J4: 3 | K4: ADR,IMDG | L4: SDS,COA,BL | M4: Ambient | N4: 9000 | O4: 0 | P4: 6500 | Q4: 44.405 | R4: 8.944 | S4: Mediterranean hub; coastal feeder connectivity; illustrative
A5: WH_EU_DEU_HAM | B5: Hamburg Chemical Warehouse | C5: Warehouse | D5: Germany | E5: Hamburg | F5: Kuehne+Nagel (illustrative) | G5: Warehouse | H5: DR200_UN,DR200,IBC1KL,BAG25 | I5: ACETYL,ARYLIDE,FLUORO | J5: 3,6.1,8 | K5: ADR,IMDG | L5: SDS,COA,REACH,CMR | M5: Ambient | N5: 1200 | O5: 4200 | P5: 3500 | Q5: 53.546 | R5: 9.966 | S5: EU inland consolidation; DG segregation; illustrative
A6: CFS_IN_NHAV | B6: JNPT / Nhava Sheva CFS | C6: Port/CFS | D6: India | E6: Navi Mumbai | F6: DP World CFS (illustrative) | G6: Yard/Warehouse | H6: ISO20,DR200_UN,DR200,IBC1KL,BAG25,BULK | I6: ACETYL,DKD,ARYLIDE,FLUORO | J6: 3,8 | K6: Customs Bonded,CFS License | L6: SDS,COA,Invoice,Packing List,BL | M6: Ambient | N6: 5000 | O6: 2500 | P6: 9000 | Q6: 18.948 | R6: 72.953 | S6: Export stuffing/de-stuffing; bonded operations; illustrative
A7: WH_IN_WEST_BHI | B7: Bhiwandi Distribution Center | C7: Warehouse | D7: India | E7: Bhiwandi | F7: 3PL West (illustrative) | G7: Warehouse | H7: DR200_UN,DR200,IBC1KL,BAG25 | I7: ACETYL,DKD,ARYLIDE,FLUORO | J7: 3,8 | K7: State Warehouse License,PESO (DG) | L7: COA,Invoice,Ewaybill | M7: Ambient | N7: 900 | O7: 6000 | P7: 6500 | Q7: 19.281 | R7: 73.056 | S7: Mumbai metro servicing; cross-dock to customers; illustrative
A8: WH_IN_GUJ_AHD | B8: Ahmedabad Chemicals Warehouse | C8: Warehouse | D8: India | E8: Ahmedabad | F8: 3PL Gujarat (illustrative) | G8: Warehouse | H8: DR200_UN,DR200,IBC1KL,BAG25 | I8: ACETYL,DKD,ARYLIDE | J8: 3,8 | K8: State Warehouse License | L8: COA,Invoice,Ewaybill | M8: Ambient | N8: 700 | O8: 4200 | P8: 4800 | Q8: 23.022 | R8: 72.571 | S8: Gujarat industrial belt coverage; DG compliant bays; illustrative
A9: WH_IN_SOUTH_HYD | B9: Hyderabad Regional Warehouse | C9: Warehouse | D9: India | E9: Hyderabad | F9: 3PL South (illustrative) | G9: Warehouse | H9: DR200,IBC1KL,BAG25 | I9: ACETYL,ARYLIDE,FLUORO | J9: 3,8 | K9: State Warehouse License | L9: COA,Invoice,Ewaybill | M9: Ambient | N9: 550 | O9: 3800 | P9: 4200 | Q9: 17.385 | R9: 78.487 | S9: South India servicing; powder and liquid zones; illustrative
A10: WH_IN_NORTH_BAW | B10: Bhiwadi/Gurgaon Logistics Hub | C10: Warehouse | D10: India | E10: Bhiwadi | F10: 3PL North (illustrative) | G10: Warehouse | H10: DR200,IBC1KL,BAG25 | I10: ACETYL,ARYLIDE | J10: 3,8 | K10: State Warehouse License | L10: COA,Invoice,Ewaybill | M10: Ambient | N10: 600 | O10: 4500 | P10: 5000 | Q10: 28.21 | R10: 76.865 | S10: NCR coverage; faster deliveries to North customers; illustrative
A11: WH_IN_EAST_KOL | B11: Kolkata Warehouse (East) | C11: Warehouse | D11: India | E11: Kolkata | F11: 3PL East (illustrative) | G11: Warehouse | H11: DR200,IBC1KL,BAG25 | I11: ACETYL,ARYLIDE | J11: 3,8 | K11: State Warehouse License | L11: COA,Invoice,Ewaybill | M11: Ambient | N11: 420 | O11: 2600 | P11: 2800 | Q11: 22.572 | R11: 88.364 | S11: Eastern corridor support; port-adjacent distribution; illustrative
A12: WH_US_EAST_NJ | B12: US East Warehouse (New Jersey) | C12: Warehouse | D12: United States | E12: Newark, NJ | F12: 3PL US East (illustrative) | G12: Warehouse | H12: DR200_UN,DR200,IBC1KL | I12: ACETYL,DKD | J12: 3,8 | K12: DOT HazMat,OSHA | L12: SDS,COA,Commercial Invoice,US customs docs | M12: Ambient | N12: 800 | O12: 3200 | P12: 3800 | Q12: 40.735 | R12: -74.172 | S12: East coast import distribution; HazMat compliant; illustrative
A13: WH_US_MID_CHI | B13: US Midwest Warehouse (Chicago) | C13: Warehouse | D13: United States | E13: Chicago, IL | F13: 3PL US Midwest (illustrative) | G13: Warehouse | H13: DR200,IBC1KL,BAG25 | I13: ACETYL,ARYLIDE,FLUORO | J13: 3,8 | K13: DOT HazMat,OSHA | L13: SDS,COA,US inland POD | M13: Ambient | N13: 650 | O13: 2800 | P13: 3100 | Q13: 41.878 | R13: -87.63 | S13: Midwest coverage; LTL-friendly operations; illustrative
A14: WH_UAE_SHJ | B14: Sharjah Bonded Warehouse | C14: Bonded Warehouse | D14: United Arab Emirates | E14: Sharjah | F14: Freezone Operator (illustrative) | G14: Warehouse | H14: DR200_UN,IBC1KL,BAG25 | I14: ACETYL,DKD,FLUORO | J14: 3,8 | K14: FTZ Bonded,Customs | L14: SDS,COA,Invoice,Packing List | M14: Ambient | N14: 500 | O14: 2200 | P14: 2600 | Q14: 25.346 | R14: 55.42 | S14: GCC re-export node; LC/documentation support; illustrative
A15: WH_CHN_SHA | B15: Shanghai Chemical Warehouse | C15: Warehouse | D15: China | E15: Shanghai | F15: 3PL China (illustrative) | G15: Warehouse | H15: DR200_UN,DR200,IBC1KL,BAG25 | I15: ACETYL,FLUORO | J15: 3,8 | K15: China DG Warehouse License | L15: SDS,COA,CIQ/Customs docs | M15: Ambient | N15: 700 | O15: 3000 | P15: 3400 | Q15: 31.23 | R15: 121.474 | S15: China distribution; local DG compliance; illustrative

Sheet Bins
A1: bin_id (Primary Key) | B1: node_id (FK) | C1: zone | D1: aisle | E1: rack | F1: level | G1: position | H1: bin_type | I1: families_allowed | J1: pack_supported | K1: dg_allowed | L1: temp_control | M1: max_units | N1: max_weight_kg | O1: segregation_class | P1: status | Q1: notes
A2: TNK_EUR_RTM_TB01 | B2: TNK_EUR_RTM | C2: TANK | D2: - | E2: - | F2: - | G2: - | H2: TANK_BAY | I2: ACETYL,DKD | J2: BULK,ISO20 | K2: DG per IMDG (Bulk) | L2: Ambient | M2: 1 | N2: 30000 | O2: DG_Bulk | P2: Active | Q2: Tank bay (bulk liquids); illustrative
A3: TNK_EUR_RTM_TB02 | B3: TNK_EUR_RTM | C3: TANK | D3: - | E3: - | F3: - | G3: - | H3: TANK_BAY | I3: ACETYL,DKD | J3: BULK,ISO20 | K3: DG per IMDG (Bulk) | L3: Ambient | M3: 1 | N3: 30000 | O3: DG_Bulk | P3: Active | Q3: Tank bay (bulk liquids); illustrative
A4: TNK_EUR_RTM_TB03 | B4: TNK_EUR_RTM | C4: TANK | D4: - | E4: - | F4: - | G4: - | H4: TANK_BAY | I4: ACETYL,DKD | J4: BULK,ISO20 | K4: DG per IMDG (Bulk) | L4: Ambient | M4: 1 | N4: 30000 | O4: DG_Bulk | P4: Active | Q4: Tank bay (bulk liquids); illustrative
A5: TNK_EUR_RTM_TB04 | B5: TNK_EUR_RTM | C5: TANK | D5: - | E5: - | F5: - | G5: - | H5: TANK_BAY | I5: ACETYL,DKD | J5: BULK,ISO20 | K5: DG per IMDG (Bulk) | L5: Ambient | M5: 1 | N5: 30000 | O5: DG_Bulk | P5: Active | Q5: Tank bay (bulk liquids); illustrative
A6: TNK_EUR_RTM_TB05 | B6: TNK_EUR_RTM | C6: TANK | D6: - | E6: - | F6: - | G6: - | H6: TANK_BAY | I6: ACETYL,DKD | J6: BULK,ISO20 | K6: DG per IMDG (Bulk) | L6: Ambient | M6: 1 | N6: 30000 | O6: DG_Bulk | P6: Active | Q6: Tank bay (bulk liquids); illustrative
A7: TNK_EUR_RTM_TB06 | B7: TNK_EUR_RTM | C7: TANK | D7: - | E7: - | F7: - | G7: - | H7: TANK_BAY | I7: ACETYL,DKD | J7: BULK,ISO20 | K7: DG per IMDG (Bulk) | L7: Ambient | M7: 1 | N7: 30000 | O7: DG_Bulk | P7: Active | Q7: Tank bay (bulk liquids); illustrative
A8: TNK_EUR_RTM_TB07 | B8: TNK_EUR_RTM | C8: TANK | D8: - | E8: - | F8: - | G8: - | H8: TANK_BAY | I8: ACETYL,DKD | J8: BULK,ISO20 | K8: DG per IMDG (Bulk) | L8: Ambient | M8: 1 | N8: 30000 | O8: DG_Bulk | P8: Active | Q8: Tank bay (bulk liquids); illustrative
A9: TNK_EUR_RTM_TB08 | B9: TNK_EUR_RTM | C9: TANK | D9: - | E9: - | F9: - | G9: - | H9: TANK_BAY | I9: ACETYL,DKD | J9: BULK,ISO20 | K9: DG per IMDG (Bulk) | L9: Ambient | M9: 1 | N9: 30000 | O9: DG_Bulk | P9: Active | Q9: Tank bay (bulk liquids); illustrative
A10: TNK_EUR_RTM_DZ-A-01 | B10: TNK_EUR_RTM | C10: DRUM | D10: A | E10: R01 | F10: 1 | G10: 1 | H10: PALLET_SLOT | I10: ACETYL,DKD | J10: DR200,DR200_UN,IBC1KL | K10: Flammable Liquids; Corrosive; DG per IMDG | L10: Ambient | M10: 4 | N10: 1200 | O10: DG_Pallet | P10: Active | Q10: DG pallet slot (drums/IBCs); illustrative
A11: TNK_EUR_RTM_DZ-A-02 | B11: TNK_EUR_RTM | C11: DRUM | D11: A | E11: R01 | F11: 1 | G11: 2 | H11: PALLET_SLOT | I11: ACETYL,DKD | J11: DR200,DR200_UN,IBC1KL | K11: Flammable Liquids; Corrosive; DG per IMDG | L11: Ambient | M11: 4 | N11: 1200 | O11: DG_Pallet | P11: Active | Q11: DG pallet slot (drums/IBCs); illustrative
A12: TNK_EUR_RTM_DZ-A-03 | B12: TNK_EUR_RTM | C12: DRUM | D12: A | E12: R01 | F12: 2 | G12: 1 | H12: PALLET_SLOT | I12: ACETYL,DKD | J12: DR200,DR200_UN,IBC1KL | K12: Flammable Liquids; Corrosive; DG per IMDG | L12: Ambient | M12: 4 | N12: 1200 | O12: DG_Pallet | P12: Active | Q12: DG pallet slot (drums/IBCs); illustrative
A13: TNK_EUR_RTM_DZ-A-04 | B13: TNK_EUR_RTM | C13: DRUM | D13: A | E13: R01 | F13: 2 | G13: 2 | H13: PALLET_SLOT | I13: ACETYL,DKD | J13: DR200,DR200_UN,IBC1KL | K13: Flammable Liquids; Corrosive; DG per IMDG | L13: Ambient | M13: 4 | N13: 1200 | O13: DG_Pallet | P13: Active | Q13: DG pallet slot (drums/IBCs); illustrative
A14: TNK_EUR_RTM_DZ-A-05 | B14: TNK_EUR_RTM | C14: DRUM | D14: A | E14: R02 | F14: 1 | G14: 1 | H14: PALLET_SLOT | I14: ACETYL,DKD | J14: DR200,DR200_UN,IBC1KL | K14: Flammable Liquids; Corrosive; DG per IMDG | L14: Ambient | M14: 4 | N14: 1200 | O14: DG_Pallet | P14: Active | Q14: DG pallet slot (drums/IBCs); illustrative
A15: TNK_EUR_RTM_DZ-A-06 | B15: TNK_EUR_RTM | C15: DRUM | D15: A | E15: R02 | F15: 1 | G15: 2 | H15: PALLET_SLOT | I15: ACETYL,DKD | J15: DR200,DR200_UN,IBC1KL | K15: Flammable Liquids; Corrosive; DG per IMDG | L15: Ambient | M15: 4 | N15: 1200 | O15: DG_Pallet | P15: Active | Q15: DG pallet slot (drums/IBCs); illustrative
A16: TNK_EUR_RTM_DZ-A-07 | B16: TNK_EUR_RTM | C16: DRUM | D16: A | E16: R02 | F16: 2 | G16: 1 | H16: PALLET_SLOT | I16: ACETYL,DKD | J16: DR200,DR200_UN,IBC1KL | K16: Flammable Liquids; Corrosive; DG per IMDG | L16: Ambient | M16: 4 | N16: 1200 | O16: DG_Pallet | P16: Active | Q16: DG pallet slot (drums/IBCs); illustrative
A17: TNK_EUR_RTM_DZ-A-08 | B17: TNK_EUR_RTM | C17: DRUM | D17: A | E17: R02 | F17: 2 | G17: 2 | H17: PALLET_SLOT | I17: ACETYL,DKD | J17: DR200,DR200_UN,IBC1KL | K17: Flammable Liquids; Corrosive; DG per IMDG | L17: Ambient | M17: 4 | N17: 1200 | O17: DG_Pallet | P17: Active | Q17: DG pallet slot (drums/IBCs); illustrative
A18: TNK_EUR_RTM_DZ-A-09 | B18: TNK_EUR_RTM | C18: DRUM | D18: A | E18: R03 | F18: 1 | G18: 1 | H18: PALLET_SLOT | I18: ACETYL,DKD | J18: DR200,DR200_UN,IBC1KL | K18: Flammable Liquids; Corrosive; DG per IMDG | L18: Ambient | M18: 4 | N18: 1200 | O18: DG_Pallet | P18: Active | Q18: DG pallet slot (drums/IBCs); illustrative
A19: TNK_EUR_RTM_DZ-A-10 | B19: TNK_EUR_RTM | C19: DRUM | D19: A | E19: R03 | F19: 1 | G19: 2 | H19: PALLET_SLOT | I19: ACETYL,DKD | J19: DR200,DR200_UN,IBC1KL | K19: Flammable Liquids; Corrosive; DG per IMDG | L19: Ambient | M19: 4 | N19: 1200 | O19: DG_Pallet | P19: Active | Q19: DG pallet slot (drums/IBCs); illustrative
A20: TNK_EUR_RTM_DZ-B-01 | B20: TNK_EUR_RTM | C20: DRUM | D20: B | E20: R01 | F20: 1 | G20: 1 | H20: PALLET_SLOT | I20: ACETYL,DKD | J20: DR200,DR200_UN,IBC1KL | K20: Flammable Liquids; Corrosive; DG per IMDG | L20: Ambient | M20: 4 | N20: 1200 | O20: DG_Pallet | P20: Active | Q20: DG pallet slot (drums/IBCs); illustrative
A21: TNK_EUR_RTM_DZ-B-02 | B21: TNK_EUR_RTM | C21: DRUM | D21: B | E21: R01 | F21: 1 | G21: 2 | H21: PALLET_SLOT | I21: ACETYL,DKD | J21: DR200,DR200_UN,IBC1KL | K21: Flammable Liquids; Corrosive; DG per IMDG | L21: Ambient | M21: 4 | N21: 1200 | O21: DG_Pallet | P21: Active | Q21: DG pallet slot (drums/IBCs); illustrative
... A69: TNK_EUR_RTM_BZ-B-10 | B69: TNK_EUR_RTM | C69: BAG | D69: B | E69: R02 | F69: 5 | G69: 1 | H69: PALLET_SLOT | I69: ACETYL,DKD | J69: BAG25 | K69: Dust/Combustible; DG per IMDG (as applicable) | L69: Ambient | M69: 50 | N69: 1200 | O69: SOLID_BAG | P69: Active | Q69: Pallet slot for bags/solids; illustrative
A70: TNK_EUR_ANT_TB01 | B70: TNK_EUR_ANT | C70: TANK | D70: - | E70: - | F70: - | G70: - | H70: TANK_BAY | I70: ACETYL,DKD,ARYLIDE | J70: BULK,ISO20 | K70: DG per IMDG (Bulk) | L70: Ambient | M70: 1 | N70: 30000 | O70: DG_Bulk | P70: Active | Q70: Tank bay (bulk liquids); illustrative
A71: TNK_EUR_ANT_TB02 | B71: TNK_EUR_ANT | C71: TANK | D71: - | E71: - | F71: - | G71: - | H71: TANK_BAY | I71: ACETYL,DKD,ARYLIDE | J71: BULK,ISO20 | K71: DG per IMDG (Bulk) | L71: Ambient | M71: 1 | N71: 30000 | O71: DG_Bulk | P71: Active | Q71: Tank bay (bulk liquids); illustrative
A72: TNK_EUR_ANT_TB03 | B72: TNK_EUR_ANT | C72: TANK | D72: - | E72: - | F72: - | G72: - | H72: TANK_BAY | I72: ACETYL,DKD,ARYLIDE | J72: BULK,ISO20 | K72: DG per IMDG (Bulk) | L72: Ambient | M72: 1 | N72: 30000 | O72: DG_Bulk | P72: Active | Q72: Tank bay (bulk liquids); illustrative
A73: TNK_EUR_ANT_TB04 | B73: TNK_EUR_ANT | C73: TANK | D73: - | E73: - | F73: - | G73: - | H73: TANK_BAY | I73: ACETYL,DKD,ARYLIDE | J73: BULK,ISO20 | K73: DG per IMDG (Bulk) | L73: Ambient | M73: 1 | N73: 30000 | O73: DG_Bulk | P73: Active | Q73: Tank bay (bulk liquids); illustrative
A74: TNK_EUR_ANT_TB05 | B74: TNK_EUR_ANT | C74: TANK | D74: - | E74: - | F74: - | G74: - | H74: TANK_BAY | I74: ACETYL,DKD,ARYLIDE | J74: BULK,ISO20 | K74: DG per IMDG (Bulk) | L74: Ambient | M74: 1 | N74: 30000 | O74: DG_Bulk | P74: Active | Q74: Tank bay (bulk liquids); illustrative
A75: TNK_EUR_ANT_TB06 | B75: TNK_EUR_ANT | C75: TANK | D75: - | E75: - | F75: - | G75: - | H75: TANK_BAY | I75: ACETYL,DKD,ARYLIDE | J75: BULK,ISO20 | K75: DG per IMDG (Bulk) | L75: Ambient | M75: 1 | N75: 30000 | O75: DG_Bulk | P75: Active | Q75: Tank bay (bulk liquids); illustrative
A76: TNK_EUR_ANT_TB07 | B76: TNK_EUR_ANT | C76: TANK | D76: - | E76: - | F76: - | G76: - | H76: TANK_BAY | I76: ACETYL,DKD,ARYLIDE | J76: BULK,ISO20 | K76: DG per IMDG (Bulk) | L76: Ambient | M76: 1 | N76: 30000 | O76: DG_Bulk | P76: Active | Q76: Tank bay (bulk liquids); illustrative
A77: TNK_EUR_ANT_TB08 | B77: TNK_EUR_ANT | C77: TANK | D77: - | E77: - | F77: - | G77: - | H77: TANK_BAY | I77: ACETYL,DKD,ARYLIDE | J77: BULK,ISO20 | K77: DG per IMDG (Bulk) | L77: Ambient | M77: 1 | N77: 30000 | O77: DG_Bulk | P77: Active | Q77: Tank bay (bulk liquids); illustrative
A78: TNK_EUR_ANT_DZ-A-01 | B78: TNK_EUR_ANT | C78: DRUM | D78: A | E78: R01 | F78: 1 | G78: 1 | H78: PALLET_SLOT | I78: ACETYL,DKD,ARYLIDE | J78: DR200,DR200_UN,IBC1KL | K78: Flammable Liquids; Corrosive; DG per IMDG | L78: Ambient | M78: 4 | N78: 1200 | O78: DG_Pallet | P78: Active | Q78: DG pallet slot (drums/IBCs); illustrative
A79: TNK_EUR_ANT_DZ-A-02 | B79: TNK_EUR_ANT | C79: DRUM | D79: A | E79: R01 | F79: 1 | G79: 2 | H79: PALLET_SLOT | I79: ACETYL,DKD,ARYLIDE | J79: DR200,DR200_UN,IBC1KL | K79: Flammable Liquids; Corrosive; DG per IMDG | L79: Ambient | M79: 4 | N79: 1200 | O79: DG_Pallet | P79: Active | Q79: DG pallet slot (drums/IBCs); illustrative
A80: TNK_EUR_ANT_DZ-A-03 | B80: TNK_EUR_ANT | C80: DRUM | D80: A | E80: R01 | F80: 2 | G80: 1 | H80: PALLET_SLOT | I80: ACETYL,DKD,ARYLIDE | J80: DR200,DR200_UN,IBC1KL | K80: Flammable Liquids; Corrosive; DG per IMDG | L80: Ambient | M80: 4 | N80: 1200 | O80: DG_Pallet | P80: Active | Q80: DG pallet slot (drums/IBCs); illustrative
A81: TNK_EUR_ANT_DZ-A-04 | B81: TNK_EUR_ANT | C81: DRUM | D81: A | E81: R01 | F81: 2 | G81: 2 | H81: PALLET_SLOT | I81: ACETYL,DKD,ARYLIDE | J81: DR200,DR200_UN,IBC1KL | K81: Flammable Liquids; Corrosive; DG per IMDG | L81: Ambient | M81: 4 | N81: 1200 | O81: DG_Pallet | P81: Active | Q81: DG pallet slot (drums/IBCs); illustrative
A82: TNK_EUR_ANT_DZ-A-05 | B82: TNK_EUR_ANT | C82: DRUM | D82: A | E82: R02 | F82: 1 | G82: 1 | H82: PALLET_SLOT | I82: ACETYL,DKD,ARYLIDE | J82: DR200,DR200_UN,IBC1KL | K82: Flammable Liquids; Corrosive; DG per IMDG | L82: Ambient | M82: 4 | N82: 1200 | O82: DG_Pallet | P82: Active | Q82: DG pallet slot (drums/IBCs); illustrative
A83: TNK_EUR_ANT_DZ-A-06 | B83: TNK_EUR_ANT | C83: DRUM | D83: A | E83: R02 | F83: 1 | G83: 2 | H83: PALLET_SLOT | I83: ACETYL,DKD,ARYLIDE | J83: DR200,DR200_UN,IBC1KL | K83: Flammable Liquids; Corrosive; DG per IMDG | L83: Ambient | M83: 4 | N83: 1200 | O83: DG_Pallet | P83: Active | Q83: DG pallet slot (drums/IBCs); illustrative
A84: TNK_EUR_ANT_DZ-A-07 | B84: TNK_EUR_ANT | C84: DRUM | D84: A | E84: R02 | F84: 2 | G84: 1 | H84: PALLET_SLOT | I84: ACETYL,DKD,ARYLIDE | J84: DR200,DR200_UN,IBC1KL | K84: Flammable Liquids; Corrosive; DG per IMDG | L84: Ambient | M84: 4 | N84: 1200 | O84: DG_Pallet | P84: Active | Q84: DG pallet slot (drums/IBCs); illustrative
A85: TNK_EUR_ANT_DZ-A-08 | B85: TNK_EUR_ANT | C85: DRUM | D85: A | E85: R02 | F85: 2 | G85: 2 | H85: PALLET_SLOT | I85: ACETYL,DKD,ARYLIDE | J85: DR200,DR200_UN,IBC1KL | K85: Flammable Liquids; Corrosive; DG per IMDG | L85: Ambient | M85: 4 | N85: 1200 | O85: DG_Pallet | P85: Active | Q85: DG pallet slot (drums/IBCs); illustrative
A86: TNK_EUR_ANT_DZ-A-09 | B86: TNK_EUR_ANT | C86: DRUM | D86: A | E86: R03 | F86: 1 | G86: 1 | H86: PALLET_SLOT | I86: ACETYL,DKD,ARYLIDE | J86: DR200,DR200_UN,IBC1KL | K86: Flammable Liquids; Corrosive; DG per IMDG | L86: Ambient | M86: 4 | N86: 1200 | O86: DG_Pallet | P86: Active | Q86: DG pallet slot (drums/IBCs); illustrative
A87: TNK_EUR_ANT_DZ-A-10 | B87: TNK_EUR_ANT | C87: DRUM | D87: A | E87: R03 | F87: 1 | G87: 2 | H87: PALLET_SLOT | I87: ACETYL,DKD,ARYLIDE | J87: DR200,DR200_UN,IBC1KL | K87: Flammable Liquids; Corrosive; DG per IMDG | L87: Ambient | M87: 4 | N87: 1200 | O87: DG_Pallet | P87: Active | Q87: DG pallet slot (drums/IBCs); illustrative
A88: TNK_EUR_ANT_DZ-B-01 | B88: TNK_EUR_ANT | C88: DRUM | D88: B | E88: R01 | F88: 1 | G88: 1 | H88: PALLET_SLOT | I88: ACETYL,DKD,ARYLIDE | J88: DR200,DR200_UN,IBC1KL | K88: Flammable Liquids; Corrosive; DG per IMDG | L88: Ambient | M88: 4 | N88: 1200 | O88: DG_Pallet | P88: Active | Q88: DG pallet slot (drums/IBCs); illustrative
A89: TNK_EUR_ANT_DZ-B-02 | B89: TNK_EUR_ANT | C89: DRUM | D89: B | E89: R01 | F89: 1 | G89: 2 | H89: PALLET_SLOT | I89: ACETYL,DKD,ARYLIDE | J89: DR200,DR200_UN,IBC1KL | K89: Flammable Liquids; Corrosive; DG per IMDG | L89: Ambient | M89: 4 | N89: 1200 | O89: DG_Pallet | P89: Active | Q89: DG pallet slot (drums/IBCs); illustrative
... A137: TNK_EUR_ANT_BZ-B-10 | B137: TNK_EUR_ANT | C137: BAG | D137: B | E137: R02 | F137: 5 | G137: 1 | H137: PALLET_SLOT | I137: ACETYL,DKD,ARYLIDE | J137: BAG25 | K137: Dust/Combustible; DG per IMDG (as applicable) | L137: Ambient | M137: 50 | N137: 1200 | O137: SOLID_BAG | P137: Active | Q137: Pallet slot for bags/solids; illustrative
A138: TNK_EUR_GEN_TB01 | B138: TNK_EUR_GEN | C138: TANK | D138: - | E138: - | F138: - | G138: - | H138: TANK_BAY | I138: ACETYL | J138: BULK,ISO20 | K138: DG per IMDG (Bulk) | L138: Ambient | M138: 1 | N138: 30000 | O138: DG_Bulk | P138: Active | Q138: Tank bay (bulk liquids); illustrative
A139: TNK_EUR_GEN_TB02 | B139: TNK_EUR_GEN | C139: TANK | D139: - | E139: - | F139: - | G139: - | H139: TANK_BAY | I139: ACETYL | J139: BULK,ISO20 | K139: DG per IMDG (Bulk) | L139: Ambient | M139: 1 | N139: 30000 | O139: DG_Bulk | P139: Active | Q139: Tank bay (bulk liquids); illustrative
A140: TNK_EUR_GEN_TB03 | B140: TNK_EUR_GEN | C140: TANK | D140: - | E140: - | F140: - | G140: - | H140: TANK_BAY | I140: ACETYL | J140: BULK,ISO20 | K140: DG per IMDG (Bulk) | L140: Ambient | M140: 1 | N140: 30000 | O140: DG_Bulk | P140: Active | Q140: Tank bay (bulk liquids); illustrative
A141: TNK_EUR_GEN_TB04 | B141: TNK_EUR_GEN | C141: TANK | D141: - | E141: - | F141: - | G141: - | H141: TANK_BAY | I141: ACETYL | J141: BULK,ISO20 | K141: DG per IMDG (Bulk) | L141: Ambient | M141: 1 | N141: 30000 | O141: DG_Bulk | P141: Active | Q141: Tank bay (bulk liquids); illustrative
A142: TNK_EUR_GEN_TB05 | B142: TNK_EUR_GEN | C142: TANK | D142: - | E142: - | F142: - | G142: - | H142: TANK_BAY | I142: ACETYL | J142: BULK,ISO20 | K142: DG per IMDG (Bulk) | L142: Ambient | M142: 1 | N142: 30000 | O142: DG_Bulk | P142: Active | Q142: Tank bay (bulk liquids); illustrative
A143: TNK_EUR_GEN_TB06 | B143: TNK_EUR_GEN | C143: TANK | D143: - | E143: - | F143: - | G143: - | H143: TANK_BAY | I143: ACETYL | J143: BULK,ISO20 | K143: DG per IMDG (Bulk) | L143: Ambient | M143: 1 | N143: 30000 | O143: DG_Bulk | P143: Active | Q143: Tank bay (bulk liquids); illustrative
A144: TNK_EUR_GEN_TB07 | B144: TNK_EUR_GEN | C144: TANK | D144: - | E144: - | F144: - | G144: - | H144: TANK_BAY | I144: ACETYL | J144: BULK,ISO20 | K144: DG per IMDG (Bulk) | L144: Ambient | M144: 1 | N144: 30000 | O144: DG_Bulk | P144: Active | Q144: Tank bay (bulk liquids); illustrative
A145: TNK_EUR_GEN_TB08 | B145: TNK_EUR_GEN | C145: TANK | D145: - | E145: - | F145: - | G145: - | H145: TANK_BAY | I145: ACETYL | J145: BULK,ISO20 | K145: DG per IMDG (Bulk) | L145: Ambient | M145: 1 | N145: 30000 | O145: DG_Bulk | P145: Active | Q145: Tank bay (bulk liquids); illustrative
A146: TNK_EUR_GEN_DZ-A-01 | B146: TNK_EUR_GEN | C146: DRUM | D146: A | E146: R01 | F146: 1 | G146: 1 | H146: PALLET_SLOT | I146: ACETYL | J146: DR200,DR200_UN,IBC1KL | K146: Flammable Liquids; Corrosive; DG per IMDG | L146: Ambient | M146: 4 | N146: 1200 | O146: DG_Pallet | P146: Active | Q146: DG pallet slot (drums/IBCs); illustrative
A147: TNK_EUR_GEN_DZ-A-02 | B147: TNK_EUR_GEN | C147: DRUM | D147: A | E147: R01 | F147: 1 | G147: 2 | H147: PALLET_SLOT | I147: ACETYL | J147: DR200,DR200_UN,IBC1KL | K147: Flammable Liquids; Corrosive; DG per IMDG | L147: Ambient | M147: 4 | N147: 1200 | O147: DG_Pallet | P147: Active | Q147: DG pallet slot (drums/IBCs); illustrative
A148: TNK_EUR_GEN_DZ-A-03 | B148: TNK_EUR_GEN | C148: DRUM | D148: A | E148: R01 | F148: 2 | G148: 1 | H148: PALLET_SLOT | I148: ACETYL | J148: DR200,DR200_UN,IBC1KL | K148: Flammable Liquids; Corrosive; DG per IMDG | L148: Ambient | M148: 4 | N148: 1200 | O148: DG_Pallet | P148: Active | Q148: DG pallet slot (drums/IBCs); illustrative
A149: TNK_EUR_GEN_DZ-A-04 | B149: TNK_EUR_GEN | C149: DRUM | D149: A | E149: R01 | F149: 2 | G149: 2 | H149: PALLET_SLOT | I149: ACETYL | J149: DR200,DR200_UN,IBC1KL | K149: Flammable Liquids; Corrosive; DG per IMDG | L149: Ambient | M149: 4 | N149: 1200 | O149: DG_Pallet | P149: Active | Q149: DG pallet slot (drums/IBCs); illustrative
A150: TNK_EUR_GEN_DZ-A-05 | B150: TNK_EUR_GEN | C150: DRUM | D150: A | E150: R02 | F150: 1 | G150: 1 | H150: PALLET_SLOT | I150: ACETYL | J150: DR200,DR200_UN,IBC1KL | K150: Flammable Liquids; Corrosive; DG per IMDG | L150: Ambient | M150: 4 | N150: 1200 | O150: DG_Pallet | P150: Active | Q150: DG pallet slot (drums/IBCs); illustrative
A151: TNK_EUR_GEN_DZ-A-06 | B151: TNK_EUR_GEN | C151: DRUM | D151: A | E151: R02 | F151: 1 | G151: 2 | H151: PALLET_SLOT | I151: ACETYL | J151: DR200,DR200_UN,IBC1KL | K151: Flammable Liquids; Corrosive; DG per IMDG | L151: Ambient | M151: 4 | N151: 1200 | O151: DG_Pallet | P151: Active | Q151: DG pallet slot (drums/IBCs); illustrative
A152: TNK_EUR_GEN_DZ-A-07 | B152: TNK_EUR_GEN | C152: DRUM | D152: A | E152: R02 | F152: 2 | G152: 1 | H152: PALLET_SLOT | I152: ACETYL | J152: DR200,DR200_UN,IBC1KL | K152: Flammable Liquids; Corrosive; DG per IMDG | L152: Ambient | M152: 4 | N152: 1200 | O152: DG_Pallet | P152: Active | Q152: DG pallet slot (drums/IBCs); illustrative
A153: TNK_EUR_GEN_DZ-A-08 | B153: TNK_EUR_GEN | C153: DRUM | D153: A | E153: R02 | F153: 2 | G153: 2 | H153: PALLET_SLOT | I153: ACETYL | J153: DR200,DR200_UN,IBC1KL | K153: Flammable Liquids; Corrosive; DG per IMDG | L153: Ambient | M153: 4 | N153: 1200 | O153: DG_Pallet | P153: Active | Q153: DG pallet slot (drums/IBCs); illustrative
A154: TNK_EUR_GEN_DZ-A-09 | B154: TNK_EUR_GEN | C154: DRUM | D154: A | E154: R03 | F154: 1 | G154: 1 | H154: PALLET_SLOT | I154: ACETYL | J154: DR200,DR200_UN,IBC1KL | K154: Flammable Liquids; Corrosive; DG per IMDG | L154: Ambient | M154: 4 | N154: 1200 | O154: DG_Pallet | P154: Active | Q154: DG pallet slot (drums/IBCs); illustrative
A155: TNK_EUR_GEN_DZ-A-10 | B155: TNK_EUR_GEN | C155: DRUM | D155: A | E155: R03 | F155: 1 | G155: 2 | H155: PALLET_SLOT | I155: ACETYL | J155: DR200,DR200_UN,IBC1KL | K155: Flammable Liquids; Corrosive; DG per IMDG | L155: Ambient | M155: 4 | N155: 1200 | O155: DG_Pallet | P155: Active | Q155: DG pallet slot (drums/IBCs); illustrative
A156: TNK_EUR_GEN_DZ-B-01 | B156: TNK_EUR_GEN | C156: DRUM | D156: B | E156: R01 | F156: 1 | G156: 1 | H156: PALLET_SLOT | I156: ACETYL | J156: DR200,DR200_UN,IBC1KL | K156: Flammable Liquids; Corrosive; DG per IMDG | L156: Ambient | M156: 4 | N156: 1200 | O156: DG_Pallet | P156: Active | Q156: DG pallet slot (drums/IBCs); illustrative
A157: TNK_EUR_GEN_DZ-B-02 | B157: TNK_EUR_GEN | C157: DRUM | D157: B | E157: R01 | F157: 1 | G157: 2 | H157: PALLET_SLOT | I157: ACETYL | J157: DR200,DR200_UN,IBC1KL | K157: Flammable Liquids; Corrosive; DG per IMDG | L157: Ambient | M157: 4 | N157: 1200 | O157: DG_Pallet | P157: Active | Q157: DG pallet slot (drums/IBCs); illustrative
... A286: WH_IN_WEST_BHI_BZ-B-04 | B286: WH_IN_WEST_BHI | C286: BAG | D286: B | E286: R01 | F286: 1 | G286: 4 | H286: PALLET_SLOT | I286: ARYLIDE,FLUORO | J286: BAG25 | K286: DG per IMDG (Fluoro); Flammable Liquids | L286: Ambient | M286: 4 | N286: 1200 | O286: DG_Pallet | P286: Active | Q286: Warehouse pallet slot (bags); illustrative

Sheet Quality Holds
A1: QH ID (Primary Key) | B1: Batch No. (FK) | C1: Material Type | D1: SKU ID (FK) | E1: Supplier ID (FK) | F1: PR Line Item ID (FK) | G1: Production Run ID (FK) | H1: Hold Date | I1: Hold Reason | J1: Defect Type | K1: Defect Description | L1: Severity | M1: Quantity Held | N1: UOM | O1: Hold Location (FK) | P1: Hold Status | Q1: Review Date | R1: Reviewed By | S1: Resolution Type | T1: Resolution Date | U1: Resolution Notes | V1: Days on Hold | W1: Impact on OTIFQ | X1: Exception ID (FK) | Y1: Attachments URL
